Workbook

Sheet MIS 2026
B1: QUALITY | E1: KEY TRADE DETAILS | W1: ISSUES OF THE DAY | X1: SALES DETAILS | AT1: L/C or ADVANCE DETAILS | BB1: SI, CERT, BAG MARKING INSTRUCTION & BUYER BANK DETAILS | BF1: SHIPMENT DETAILS | BV1: SALES INVOICING DETAILS | BY1: OBL TRACKING | CH1: CERT TRACKING | CL1: NEGO BANKING | CQ1: FINAL PAYMENT DETAILS | CS1: FNF STAGE | DL1: =SUBTOTAL(9,DL3:DL3) -> 0 | DQ1: =SUBTOTAL(9,DQ3:DQ3) -> 0 | DR1: =SUBTOTAL(9,DR3:DR3) -> 0 | DZ1: TRADE | EA1: =SUBTOTAL(9,EA3:EA3) -> 0 | EB1: POD QUALITY REPORT | EE1: PURCHASE DETAILS | EW1: PAYEMENT TO OTHER VENDORS | FL1: CYCLE TIME ( Need to Improve) | FS1: SAP ENTRIES
A2: TRADER STATUS | B2: KOR (Planned) | C2: NC | D2: Comm | E2: POSITION | F2: SAP SO ref | G2: Check | H2: BUYER NAME | I2: Origin | J2: Destination | K2: POD | L2: BL NO. | M2: BL/Stuffed Qty(MT) | N2: ETD/SOB | O2: ETA | P2: OBL Location | Q2: Crop / HBL | R2: CERT Location | S2: Nego Banking | T2: Origin Issue/Remarks | U2: Updates | V2: Addendums ( If Any) - With counterparty sign remark | W2: =TODAY() -> 46172 | X2: Deal Ticket Rcvd Date | Y2: SAP Deal Tkt No. | Z2: Sales Contract Dt. | AA2: SAP SO No. | AB2: Buyer Name | AC2: Shipment period | AD2: LDS | AE2: Toler% | AF2: Qty | AG2: Min Qty | AH2: UOM | AI2: Sales Price/ UOM | AJ2: Sales Contract value | AK2: Sales INCO | AL2: Sales - PMT Type | AM2: Adv % (TT) | AN2: 2nd Pmt % (DP/TT) | AO2: FNF % (TT) | AP2: PT DAYS | AQ2: Valency POC | AR2: Broker | AS2: Brokarage | AT2: LC No. | AU2: LC Issue date | AV2: Expiry Date | AW2: LDS as per LC | AX2: Bank | AY2: Adv Dates as per Contract | AZ2: Adv Amt | BA2: Adv Date | BB2: SI, CERT, BAG MARKING INSTRUCTION shared Date | BC2: Lot No: | BD2: IMPORTER Address on Certs | BE2: BUYER BANK DETAILS | BF2: SI, CERT, BAG MARKING INSTRUCTION shared Date | BG2: IMPORTER Address on Certs | BH2: BUYER BANK DETAILS | BI2: BL Number | BJ2: BL Net Wt./ Stuffed Qty | BK2: Conts Type | BL2: Conts Qty | BM2: SOB/ETD | BN2: Transhipment ETA | BO2: Final ETA | BP2: POL | BQ2: POD | BR2: Shipping Line | BS2: FREE DAYS AS PER BOOKING | BT2: VESSEL NAME | BU2: VOYAGE NO | BV2: Sales Invoice # -SAP | BW2: SAP Inv Date | BX2: SAP Sales Inv Amt | BY2: BL draft Recd/Sent | BZ2: OBL Final recd dt | CA2: OBL DHL Origin to SG | CB2: OBL Rcvd Date in SIG | CC2: OBL DHL SIG TO VIETNAM OR INDIA | CD2: OBL RCVD DATE AT DEST | CE2: OBL LOCATION | CF2: DHL -BL From SIG to Vietnam (Spcl case) | CG2: OBL Rcvd in Vietnam | CH2: Final Certs scan rcvd dt | CI2: Cert DHL no from Origin | CJ2: Cert Rcvd Date in Destination | CK2: CERTS Status | CL2: Nego Bank name | CM2: Nego Date | CN2: Bank to bank AWB details | CO2: Nego Docs in Buyer Bank Rcvd Date | CP2: Nego Status | CQ2: 98%/Final payment Amt | CR2: 98%/ Final Pmt Rcevd Date | CS2: VINA/RBS REPORT | CT2: LANDED QTY | CU2: QTY DIFFERENCE | CV2: % CHANGE | CW2: TOTAL AMOUNT RECEIVED TILL NOW ( ADV + MID ) | CX2: 2 % VALUE OF LANDED QTY | CY2: USD / LBS | CZ2: LANDED KOR | DA2: VARIANCE KOR | DB2: LANDED NC | DC2: VARIANCE NC | DD2: LANDED MOS% | DE2: VARIANCE MOS | DF2: QTY CLAIM | DG2: KOR CLAIM (FOR 1:1) | DH2: KOR CLAIM (FOR 1:2) | DI2: NC CLAIM | DJ2: MOS CLAIM | DK2: Total Qty & Qlty CLAIM | DL2: OTHER CLAIMS (IF ANY) | DM2: OTHER CLAIMS REMARKS | DN2: TOTAL F & F CLAIM | DO2: NET BILL VALUE | DP2: AMOUNT RECEIVED TILL NOW ( ADV + MID )2 | DQ2: NET PAYABLES | DR2: NET RECIVABLES | DS2: PAYABLE BY | DT2: CN/DN - REMARKS | DU2: SAP CN/DN No | DV2: SAP CN/DN INV No: | DW2: SAP Entries Completed Date | DX2: FNF INTERACTION WITH BUYER | DY2: F&F SAP STATUS | DZ2: CLOSE/OPEN | EA2: LOST PREMUIM CLAIM | EB2: Stuffed KOR | EC2: Stuffed NC | ED2: Stuffed MOIST | EE2: SAP PO No | EF2: PO Date | EG2: PI No. | EH2: Supplier | EI2: Valency /FOB | EJ2: Pur Qty (MT) | EK2: Pur Rate USD | EL2: Advance Amt. | EM2: Advance PMT Date | EN2: Order Value USD | EO2: Purchase INCO | EP2: Pur pmt Type | EQ2: Pur pmt Term | ER2: Bal Paid | ES2: Supplier Pmt Date | ET2: Delivery terms | EU2: Remarks (if Any) | EV2: Status for Cashflow | EW2: Freight Amt | EX2: Frt/Mt | EY2: Freight Inv recd dt | EZ2: Freight pmt date | FA2: Insurance no. | FB2: Insurance Dt | FC2: Comm $ | FD2: Total Comm Value (USD) | FE2: Comm - Sales Payment 1 | FF2: Comm - Sales Payment 2 | FG2: SAP Comm - Purch 3rd party | FH2: Deal Ticket Vs Contract | FI2: Contract Vs Advance | FL2: Freight Pmt VS Darft BL | FM2: Insurance Vs SOB) | FN2: OBL Copy Vs SOB) | FO2: Bank Nego Vs SOB | FP2: Certs Copy Vs SOB) | FQ2: ETD VS ETA | FR2: ETA Vs FNF Entries | FS2: Deal Ticket | FT2: SO | FU2: PO | FV2: MIGO | FW2: BATCH NO | FX2: MIR7 {Vendor} | FY2: MIR7 {Comm} | FZ2: MIR7 {Comm} | GA2: MIR7 {freight} | GB2: MIR7 {Ins} | GC2: OD | GD2: INVOICE | GE2: PI | GF2: Status | GG2: Remarks | GH2: Sale Retun VA01 | GI2: Sale Return VL01N | GJ2: Sale Return VF01 | GK2: Sale Debit/Credit Note VA01 | GL2: Sale Debit/Credit Inv VF01 | GM2: Pur Debit/Credit Note MIR7 | GN2: BL MIRROR COPY
A3: =IF(DZ3="CLOSE","Trade closed",IF(DZ3="PMT Pending","FNF Settlement is Due",IF(CS3<>0,"FNF Reconcillation Onging",IF(CR3<>0," Final Pmt Recd , FNF Pending",IF(CM3<>0,"Exp Dox Presented to Bank, Pmt Pending",IF(BZ3<>0,"OBL Scan Recd, Nego Pending",IF(BM3<>0,"Sailed, OBL & Certs Pending",IF(BJ3<>0,"Stuffed, Yet to Sail",IF(BB3<>0,"SI Sent, Shipment Awaited",IF(BA3<>0,"Advance Rcvd, SI Pending",IF(Z3<>0,"SC Raised, Advance Pending",IF(X3<>0,"Deal Ticket Rcvd SC Pending", "Entry Pending")))))))))))) -> Exp Dox Presented to Bank, Pmt Pending | B3: 51 | C3: 190 | D3: RCN | E3: =IF(AND(LEFT(TRIM(AA3&""),1)="3",BI3<>""),"CLOSE POSITION", IF(AND(LEFT(TRIM(AA3&""),1)="3",BI3=""),"SHORT POSITION", IF(AND(LEFT(TRIM(AA3&""),1)<>"3",BI3<>""),"LONG POSITION","ENTRY PENDING"))) -> CLOSE POSITION | F3: =AA3 -> 32014425 | H3: =AB3 -> VALENCY AGRO // HSS // ORGANIC FOODS INDIA EXIM | I3: NIGERIA(OGB) | J3: INDIA | K3: =IF(BQ3<>0,BQ3,"") -> TUTICORIN, INDIA | L3: =IF(BI3<>0,BI3,"") -> MEDULG618084 | M3: =IF(BJ3<>0,BJ3,"") -> 107.05 | N3: =IF(BM3<>0,BM3,"") -> 46090 | O3: =IF(BO3<>0,BO3,"") -> 46143 | P3: =CE3 -> OBL In Destination - INDIA | R3: =CK3 -> CERTS in Destination - INDIA | S3: =CP3 -> Docs in Buyer's Nego Bank | T3: =IFERROR(_xlfn.XLOOKUP(F3, '[2]Data 2026'!$H$12:$H$111, '[2]Data 2026'!$CL$12:$CL$111),"") | U3: Payment by Valency Agro will be done, 90 days after BL date- CARGO CLEARED. | V3: ADDENDUM 11/02-COUNTER SIGNED RCVD | X3: 46380 | Y3: 20009386 | Z3: 46380 | AA3: 32014425 | AB3: VALENCY AGRO // HSS // ORGANIC FOODS INDIA EXIM | AC3: BY 15TH MARCH | AD3: 46096 | AE3: 0.1 | AF3: 100 | AG3: =AF3*(1-AE3) -> 90 | AH3: MT | AI3: 1615 | AJ3: 161500 | AK3: CFR | AL3: 90 DAYS FROM BL DATE | AM3: 0 | AN3: 1 | AO3: 0 | AP3: 180 DAYS | AQ3: Mr.Chirag | AT3: - | AU3: - | AV3: - | AZ3: =AF3*AI3*AM3 -> 0 | BB3: 46030 | BF3: 46030 | BI3: MEDULG618084 | BJ3: 107.05 | BK3: 40' | BL3: 4 | BM3: 46090 | BN3: Hambantota, LK 26-04 | BO3: 46143 | BP3: Ogbomosho | BQ3: TUTICORIN, INDIA | BR3: MSC | BT3: MSC NISHA V - | BU3: FN608B | BV3: 90083238 | BX3: =BJ3*AI3 -> 172885.75 | BY3: 46126 | BZ3: 46122 | CA3: 4213158176 | CB3: 46126 | CE3: =IF(J3="VIETNAM", IF(CG3<>"","OBL in Vietnam Office", IF(CF3<>"","OBL in Transit from Vietnam Office", IF(CD3<>0,"OBL In Destination - "&J3, IF(CC3<>0,"OBL in Transit to Destination - "&J3, IF(CB3<>0,"OBL in SIG Office", IF(CA3<>0,"OBL in Transit from Origin to SIG", IF(BZ3<>0,"OBL in Origin - "&I3, IF(BY3<>0,"Draft Rcvd","No OBL Yet")))))))), IF(CO3<>0,"OBL In Destination - "&J3, IF(CM3<>0,"OBL in Transit with Nego Docs - "&J3, IF(CB3<>0,"OBL in SIG Office", IF(CA3<>0,"OBL in Transit from Origin to SIG", IF(BZ3<>0,"OBL in Origin - "&I3, IF(BY3<>0,"Draft Rcvd","No OBL Yet"))))))) -> OBL In Destination - INDIA | CH3: 46126 | CI3: 7012074694 | CJ3: 46125 | CK3: =IF(CJ3<>0,"CERTS in Destination - "&J3,IF(CI3<>0,"CERT in Transit to -"&J3,IF(CH3<>0,"CERT in Origin - "&I3,IF(CH3="","No CERTS Yet")))) -> CERTS in Destination - INDIA | CL3: ICICI BANK | CM3: 46126 | CN3: 5993795931 | CO3: 43922 | CP3: =IF(CO3<>0,"Docs in Buyer's Nego Bank",IF(CN3<>0,"Docs in Transit to Buyer's Nego Bank",IF(CM3<>0,"Docs in Our Nego Bank",IF(CL3="TT PAYMENT","Not Applicable","")))) -> Docs in Buyer's Nego Bank | CQ3: =(AN3*AI3*BJ3)-AZ3 -> 172885.75 | CU3: =IF(CS3="","",BJ3-CT3) | CV3: =IF(CS3="","",CU3/BJ3) | CW3: =IF(CS3="","",AZ3+CQ3) | CX3: =IF(CS3="","",BX3*2%) | CY3: =IF(CS3="","",AI3/B3) | DA3: =IF(CS3="","",B3-CZ3) | DC3: =IF(CS3="","",IF(CS3="","",DB3-C3)) | DE3: =IF(CS3="","",10%-DD3) | DF3: =IF(CS3="","",CU3*AI3) | DG3: =IF(CS3="","",IF(DA3>2,2*DA3*CT3*CY3,DA3*CT3*CY3)) | DH3: =IF(CS3="","",IF(DA3>2,2*(DA3-2*CT3*CY3),0)) | DI3: =IF(CS3="","",IF(DC3>0,DC3*0.5*CT3,0)) | DJ3: =IF(CS3="","",IF(DE3<0,DE3*CT3*AI3*1%,0)) | DK3: =IF(CS3="","",SUM(DF3:DJ3)) | DN3: =IF(CS3="","",SUM(DK3:DL3)) | DO3: =IF(CS3="","",BJ3*AI3-DN3) | DP3: =IF(CS3="","",AZ3+CQ3) | DQ3: =IF(CS3="","",IF((DP3-DO3)>0,DP3-DO3,"")) | DR3: =IF(CS3="","",IF((DO3-DP3)>0,(DO3-DP3),"")) | DS3: =IF(CS3="","",IF(DQ3="",H3,"VALENCY")) | DT3: =IF(DN3="","",IF(DN3>0,"CN", "DN")) | DY3: NO VINA/RBS REPORT | EA3: =IF(CS3="","", MIN(0,(IF(DA3>2,2,1)*DA3*CT3*CY3)) ) | EB3: 46.855 | EC3: 197 | ED3: 9 | EE3: 4900009449 | EH3: Valency Nigeria | EJ3: =BJ3 -> 107.05 | EK3: 2010 | EL3: - | EN3: =EK3*EJ3 -> 215170.5 | EO3: FOB | EV3: =IF(CR3<>0,"Final Pmt Recd",IF(CM3<>0,"Export Loan",IF(BZ3<>0,"Nego Pending",IF(Z3<>0,"Yet to load","Yet to load")))) -> Export Loan | EX3: =EW3/BJ3 -> 0 | EY3: Freight paid by origin | FD3: =FC3*BJ3 -> 0 | FL3: =IFERROR(EZ3-BY3,"") -> -46126 | FM3: =IFERROR(BM3-FB3,"") -> 46090 | FS3: 20009386 | FT3: 32014425 | FU3: 4900009449 | FV3: 5000271563 | FW3: 0000093574 | FX3: 5105710238 | GC3: 40081687 | GD3: 90083238 | GF3: done
A4: =IF(DZ4="CLOSE","Trade closed",IF(DZ4="PMT Pending","FNF Settlement is Due",IF(CS4<>0,"FNF Reconcillation Onging",IF(CR4<>0," Final Pmt Recd , FNF Pending",IF(CM4<>0,"Exp Dox Presented to Bank, Pmt Pending",IF(BZ4<>0,"OBL Scan Recd, Nego Pending",IF(BM4<>0,"Sailed, OBL & Certs Pending",IF(BJ4<>0,"Stuffed, Yet to Sail",IF(BB4<>0,"SI Sent, Shipment Awaited",IF(BA4<>0,"Advance Rcvd, SI Pending",IF(Z4<>0,"SC Raised, Advance Pending",IF(X4<>0,"Deal Ticket Rcvd SC Pending", "Entry Pending")))))))))))) -> Final Pmt Recd , FNF Pending | B4: 51 | C4: 190 | D4: RCN | E4: =IF(AND(LEFT(TRIM(AA4&""),1)="3",BI4<>""),"CLOSE POSITION", IF(AND(LEFT(TRIM(AA4&""),1)="3",BI4=""),"SHORT POSITION", IF(AND(LEFT(TRIM(AA4&""),1)<>"3",BI4<>""),"LONG POSITION","ENTRY PENDING"))) -> CLOSE POSITION | F4: =AA4 -> 32013748 | H4: =AB4 -> ST. PAULS CASHEW FACTORY | I4: NIGERIA(OGB) | J4: INDIA | K4: =IF(BQ4<>0,BQ4,"") -> TUTICORIN, INDIA | L4: =IF(BI4<>0,BI4,"") -> MEDULG619041 | M4: =IF(BJ4<>0,BJ4,"") -> 50.45 | N4: =IF(BM4<>0,BM4,"") -> 46099 | O4: =IF(BO4<>0,BO4,"") -> 46158 | P4: =CE4 -> OBL In Destination - INDIA | R4: =CK4 -> CERTS in Destination - INDIA | S4: =CP4 -> Docs in Buyer's Nego Bank | T4: =IFERROR(_xlfn.XLOOKUP(F4, '[2]Data 2026'!$H$12:$H$111, '[2]Data 2026'!$CL$12:$CL$111),"") | U4: PAYMENT RCVD 14/5 | V4: ADDENDUM 11/02-COUNTER SIGNED RCVD | X4: 46380 | Y4: 20009014 | Z4: 46017 | AA4: 32013748 | AB4: ST. PAULS CASHEW FACTORY | AC4: BY 15TH MARCH | AD4: 46096 | AE4: 0.1 | AF4: 50 | AG4: =AF4*(1-AE4) -> 45 | AH4: MT | AI4: 1610 | AJ4: =AI4*AF4 -> 80500 | AK4: CFR | AL4: DP SIGHT | AM4: 0 | AN4: 1 | AO4: 0 | AP4: 180 DAYS | AQ4: Mr. George | AT4: - | AU4: - | AV4: - | BA4: 46382 | BB4: 46030 | BF4: 46030 | BI4: MEDULG619041 | BJ4: 50.45 | BK4: 40' | BL4: 2 | BM4: 46099 | BN4: Colombo, LK 28-04, IN MSDU6442397 | BO4: 46158 | BP4: Ogbomosho | BQ4: TUTICORIN, INDIA | BR4: MSC | BT4: MSC TASMANIA | BU4: WP609R | BV4: 90083303 | BX4: =BJ4*AI4 -> 81224.5 | BZ4: 46120 | CA4: 4213158176 | CB4: 46126 | CE4: =IF(J4="VIETNAM", IF(CG4<>"","OBL in Vietnam Office", IF(CF4<>"","OBL in Transit from Vietnam Office", IF(CD4<>0,"OBL In Destination - "&J4, IF(CC4<>0,"OBL in Transit to Destination - "&J4, IF(CB4<>0,"OBL in SIG Office", IF(CA4<>0,"OBL in Transit from Origin to SIG", IF(BZ4<>0,"OBL in Origin - "&I4, IF(BY4<>0,"Draft Rcvd","No OBL Yet")))))))), IF(CO4<>0,"OBL In Destination - "&J4, IF(CM4<>0,"OBL in Transit with Nego Docs - "&J4, IF(CB4<>0,"OBL in SIG Office", IF(CA4<>0,"OBL in Transit from Origin to SIG", IF(BZ4<>0,"OBL in Origin - "&I4, IF(BY4<>0,"Draft Rcvd","No OBL Yet"))))))) -> OBL In Destination - INDIA | CH4: 46127 | CI4: 2574551980 | CJ4: 46133 | CK4: =IF(CJ4<>0,"CERTS in Destination - "&J4,IF(CI4<>0,"CERT in Transit to -"&J4,IF(CH4<>0,"CERT in Origin - "&I4,IF(CH4="","No CERTS Yet")))) -> CERTS in Destination - INDIA | CL4: HABIB BANK | CM4: 46128 | CN4: 4920872821 | CO4: 45017 | CP4: =IF(CO4<>0,"Docs in Buyer's Nego Bank",IF(CN4<>0,"Docs in Transit to Buyer's Nego Bank",IF(CM4<>0,"Docs in Our Nego Bank",IF(CL4="TT PAYMENT","Not Applicable","")))) -> Docs in Buyer's Nego Bank | CQ4: =(AN4*AI4*BJ4)-AZ4 -> 81224.5 | CR4: 46156 | CU4: =IF(CS4="","",BJ4-CT4) | CV4: =IF(CS4="","",CU4/BJ4) | CW4: =IF(CS4="","",AZ4+CQ4) | CX4: =IF(CS4="","",BX4*2%) | CY4: =IF(CS4="","",AI4/B4) | DA4: =IF(CS4="","",B4-CZ4) | DC4: =IF(CS4="","",IF(CS4="","",DB4-C4)) | DE4: =IF(CS4="","",10%-DD4) | DF4: =IF(CS4="","",CU4*AI4) | DG4: =IF(CS4="","",IF(DA4>2,2*DA4*CT4*CY4,DA4*CT4*CY4)) | DH4: =IF(CS4="","",IF(DA4>2,2*(DA4-2*CT4*CY4),0)) | DI4: =IF(CS4="","",IF(DC4>0,DC4*0.5*CT4,0)) | DJ4: =IF(CS4="","",IF(DE4<0,DE4*CT4*AI4*1%,0)) | DK4: =IF(CS4="","",SUM(DF4:DJ4)) | DN4: =IF(CS4="","",SUM(DK4:DL4)) | DO4: =IF(CS4="","",BJ4*AI4-DN4) | DP4: =IF(CS4="","",AZ4+CQ4) | DQ4: =IF(CS4="","",IF((DP4-DO4)>0,DP4-DO4,"")) | DR4: =IF(CS4="","",IF((DO4-DP4)>0,(DO4-DP4),"")) | DS4: =IF(CS4="","",IF(DQ4="",H4,"VALENCY")) | DT4: =IF(DN4="","",IF(DN4>0,"CN", "DN")) | DY4: NO VINA/RBS REPORT | EA4: =IF(CS4="","", MIN(0,(IF(DA4>2,2,1)*DA4*CT4*CY4)) ) | EB4: 46.735 | EC4: 197 | ED4: 8.95 | EE4: 4900009467 | EH4: Valency Nigeria | EJ4: =BJ4 -> 50.45 | EK4: 2010 | EL4: - | EN4: =EK4*EJ4 -> 101404.5 | EV4: =IF(CR4<>0,"Final Pmt Recd",IF(CM4<>0,"Export Loan",IF(BZ4<>0,"Nego Pending",IF(Z4<>0,"Yet to load","Yet to load")))) -> Final Pmt Recd | EX4: =EW4/BJ4 -> 0 | EY4: Freight paid by origin | FD4: =FC4*BJ4 -> 0 | FL4: =IFERROR(EZ4-BY4,"") -> 0 | FM4: =IFERROR(BM4-FB4,"") -> 46099 | FS4: 20009014 | FT4: 32013748 | FU4: 0 | GD4: 90083303 | GF4: done
A5: =IF(DZ5="CLOSE","Trade closed",IF(DZ5="PMT Pending","FNF Settlement is Due",IF(CS5<>0,"FNF Reconcillation Onging",IF(CR5<>0," Final Pmt Recd , FNF Pending",IF(CM5<>0,"Exp Dox Presented to Bank, Pmt Pending",IF(BZ5<>0,"OBL Scan Recd, Nego Pending",IF(BM5<>0,"Sailed, OBL & Certs Pending",IF(BJ5<>0,"Stuffed, Yet to Sail",IF(BB5<>0,"SI Sent, Shipment Awaited",IF(BA5<>0,"Advance Rcvd, SI Pending",IF(Z5<>0,"SC Raised, Advance Pending",IF(X5<>0,"Deal Ticket Rcvd SC Pending", "Entry Pending")))))))))))) -> Exp Dox Presented to Bank, Pmt Pending | B5: 47 | C5: 185 | D5: RCN | E5: =IF(AND(LEFT(TRIM(AA5&""),1)="3",BI5<>""),"CLOSE POSITION", IF(AND(LEFT(TRIM(AA5&""),1)="3",BI5=""),"SHORT POSITION", IF(AND(LEFT(TRIM(AA5&""),1)<>"3",BI5<>""),"LONG POSITION","ENTRY PENDING"))) -> CLOSE POSITION | F5: =AA5 -> 32015281-1 | H5: =AB5 -> Valency Agro (Processing) | I5: GHANA | J5: INDIA | K5: =IF(BQ5<>0,BQ5,"") -> MUNDRA, INDIA | L5: =IF(BI5<>0,BI5,"") -> TMA0158642 | M5: =IF(BJ5<>0,BJ5,"") -> 100 | N5: =IF(BM5<>0,BM5,"") -> 46099 | O5: =IF(BO5<>0,BO5,"") -> 46146 | P5: =CE5 -> OBL In Destination - INDIA | R5: =CK5 -> CERTS in Destination - INDIA | S5: =CP5 -> Docs in Buyer's Nego Bank | T5: =IFERROR(_xlfn.XLOOKUP(F5, '[2]Data 2026'!$H$12:$H$111, '[2]Data 2026'!$CL$12:$CL$111),"") | U5: Payment by Valency Agro will be done, 90 days after BL date- CARGO CLEARED. | X5: 46093 | Y5: 20009747 | Z5: =X5 -> 46093 | AA5: 32015281-1 | AB5: Valency Agro (Processing) | AC5: March - 26 | AD5: 46112 | AE5: 0.1 | AF5: 100 | AG5: =AF5*(1-AE5) -> 90 | AH5: MT | AI5: 1585 | AJ5: =AI5*AF5 -> 158500 | AK5: CIF | AL5: 90 DAYS FROM BL DATE | AM5: 0 | AN5: 1 | AO5: 0 | AP5: 180 DAYS | AQ5: Mr. Naveen | AR5: Direct | AT5: - | AU5: - | AV5: - | AZ5: =AF5*AI5*AM5 -> 0 | BA5: =Z5 -> 46093 | BB5: 46078 | BF5: 46078 | BI5: TMA0158642 | BJ5: 100 | BK5: 40' | BL5: 4 | BM5: 46099 | BO5: 46146 | BP5: GHANA | BQ5: MUNDRA, INDIA | BR5: CMA CGM | BT5: MAERSK HANGZHOU | BU5: 0WWQ0E1MA | BV5: 90082901 | BX5: =BJ5*AI5 -> 158500 | BZ5: 46121 | CA5: 5548360370 | CB5: 46126 | CE5: =IF(J5="VIETNAM", IF(CG5<>"","OBL in Vietnam Office", IF(CF5<>"","OBL in Transit from Vietnam Office", IF(CD5<>0,"OBL In Destination - "&J5, IF(CC5<>0,"OBL in Transit to Destination - "&J5, IF(CB5<>0,"OBL in SIG Office", IF(CA5<>0,"OBL in Transit from Origin to SIG", IF(BZ5<>0,"OBL in Origin - "&I5, IF(BY5<>0,"Draft Rcvd","No OBL Yet")))))))), IF(CO5<>0,"OBL In Destination - "&J5, IF(CM5<>0,"OBL in Transit with Nego Docs - "&J5, IF(CB5<>0,"OBL in SIG Office", IF(CA5<>0,"OBL in Transit from Origin to SIG", IF(BZ5<>0,"OBL in Origin - "&I5, IF(BY5<>0,"Draft Rcvd","No OBL Yet"))))))) -> OBL In Destination - INDIA | CH5: 46146 | CI5: 2243774470 | CJ5: 46153 | CK5: =IF(CJ5<>0,"CERTS in Destination - "&J5,IF(CI5<>0,"CERT in Transit to -"&J5,IF(CH5<>0,"CERT in Origin - "&I5,IF(CH5="","No CERTS Yet")))) -> CERTS in Destination - INDIA | CL5: ICICI BANK | CM5: 46126 | CN5: 5993795931 | CO5: 43922 | CP5: =IF(CO5<>0,"Docs in Buyer's Nego Bank",IF(CN5<>0,"Docs in Transit to Buyer's Nego Bank",IF(CM5<>0,"Docs in Our Nego Bank",IF(CL5="TT PAYMENT","Not Applicable","")))) -> Docs in Buyer's Nego Bank | CQ5: =(AN5*AI5*BJ5)-AZ5 -> 158500 | CU5: =IF(CS5="","",BJ5-CT5) | CV5: =IF(CS5="","",CU5/BJ5) | CW5: =IF(CS5="","",AZ5+CQ5) | CX5: =IF(CS5="","",BX5*2%) | CY5: =IF(CS5="","",AI5/B5) | DA5: =IF(CS5="","",B5-CZ5) | DC5: =IF(CS5="","",IF(CS5="","",DB5-C5)) | DE5: =IF(CS5="","",10%-DD5) | DF5: =IF(CS5="","",CU5*AI5) | DG5: =IF(CS5="","",IF(DA5>2,2*DA5*CT5*CY5,DA5*CT5*CY5)) | DH5: =IF(CS5="","",IF(DA5>2,2*(DA5-2*CT5*CY5),0)) | DI5: =IF(CS5="","",IF(DC5>0,DC5*0.5*CT5,0)) | DJ5: =IF(CS5="","",IF(DE5<0,DE5*CT5*AI5*1%,0)) | DK5: =IF(CS5="","",SUM(DF5:DJ5)) | DN5: =IF(CS5="","",SUM(DK5:DL5)) | DO5: =IF(CS5="","",BJ5*AI5-DN5) | DP5: =IF(CS5="","",AZ5+CQ5) | DQ5: =IF(CS5="","",IF((DP5-DO5)>0,DP5-DO5,"")) | DR5: =IF(CS5="","",IF((DO5-DP5)>0,(DO5-DP5),"")) | DS5: =IF(CS5="","",IF(DQ5="",H5,"VALENCY")) | DT5: =IF(DN5="","",IF(DN5>0,"CN", "DN")) | DY5: NO VINA/RBS REPORT | EA5: =IF(CS5="","", MIN(0,(IF(DA5>2,2,1)*DA5*CT5*CY5)) ) | EB5: =_xleta.IF -> #VALUE! | EH5: Valora Exim | EI5: FOB | EN5: =EK5*EJ5 -> 0 | EV5: =IF(CR5<>0,"Final Pmt Recd",IF(CM5<>0,"Export Loan",IF(BZ5<>0,"Nego Pending",IF(Z5<>0,"Yet to load","Yet to load")))) -> Export Loan | EX5: =EW5/BJ5 -> 0 | EY5: Freight paid by origin | FD5: =FC5*BJ5 -> 0 | FL5: =IFERROR(EZ5-BY5,"") -> 0 | FM5: =IFERROR(BM5-FB5,"") -> 46099 | FS5: =Y5 -> 20009747 | FT5: =AA5 -> 32015281-1 | GD5: 90082901 | GF5: done
A6: =IF(DZ6="CLOSE","Trade closed",IF(DZ6="PMT Pending","FNF Settlement is Due",IF(CS6<>0,"FNF Reconcillation Onging",IF(CR6<>0," Final Pmt Recd , FNF Pending",IF(CM6<>0,"Exp Dox Presented to Bank, Pmt Pending",IF(BZ6<>0,"OBL Scan Recd, Nego Pending",IF(BM6<>0,"Sailed, OBL & Certs Pending",IF(BJ6<>0,"Stuffed, Yet to Sail",IF(BB6<>0,"SI Sent, Shipment Awaited",IF(BA6<>0,"Advance Rcvd, SI Pending",IF(Z6<>0,"SC Raised, Advance Pending",IF(X6<>0,"Deal Ticket Rcvd SC Pending", "Entry Pending")))))))))))) -> SI Sent, Shipment Awaited | B6: 49 | C6: 200 | D6: RCN | E6: =IF(AND(LEFT(TRIM(AA6&""),1)="3",BI6<>""),"CLOSE POSITION", IF(AND(LEFT(TRIM(AA6&""),1)="3",BI6=""),"SHORT POSITION", IF(AND(LEFT(TRIM(AA6&""),1)<>"3",BI6<>""),"LONG POSITION","ENTRY PENDING"))) -> SHORT POSITION | F6: =AA6 -> 32014480 | H6: =AB6 -> AMITH CASHEWS PVT LTD | I6: IVC | J6: INDIA | K6: =IF(BQ6<>0,BQ6,"") -> MANGALORE, INDIA | L6: =IF(BI6<>0,BI6,"") | M6: =IF(BJ6<>0,BJ6,"") | N6: =IF(BM6<>0,BM6,"") | O6: =IF(BO6<>0,BO6,"") | P6: =CE6 -> No OBL Yet | R6: =CK6 -> No CERTS Yet | S6: =CP6 | T6: CLARIFICATION ON LATEST SOB | U6: 267489694 | X6: 46072 | Y6: 20009532 | Z6: 46072 | AA6: 32014480 | AB6: AMITH CASHEWS PVT LTD | AC6: April - 26 | AD6: 46142 | AE6: 0.1 | AF6: 100 | AG6: =AF6*(1-AE6) -> 90 | AH6: MT | AI6: 1545 | AJ6: =AI6*AF6 -> 154500 | AK6: CIF | AL6: DP SIGHT | AM6: 0.1 | AN6: 0.9 | AO6: 0 | AP6: 180 DAYS | AQ6: Mr. George | AR6: Mr. Rao | AS6: 5 | AU6: - | AV6: - | AY6: 46078 | AZ6: =AF6*AI6*AM6 -> 15450 | BA6: 46086 | BB6: 46083 | BF6: 46083 | BK6: 40' | BP6: IVC | BQ6: MANGALORE, INDIA | BX6: =BJ6*AI6 -> 0 | CE6: =IF(J6="VIETNAM", IF(CG6<>"","OBL in Vietnam Office", IF(CF6<>"","OBL in Transit from Vietnam Office", IF(CD6<>0,"OBL In Destination - "&J6, IF(CC6<>0,"OBL in Transit to Destination - "&J6, IF(CB6<>0,"OBL in SIG Office", IF(CA6<>0,"OBL in Transit from Origin to SIG", IF(BZ6<>0,"OBL in Origin - "&I6, IF(BY6<>0,"Draft Rcvd","No OBL Yet")))))))), IF(CO6<>0,"OBL In Destination - "&J6, IF(CM6<>0,"OBL in Transit with Nego Docs - "&J6, IF(CB6<>0,"OBL in SIG Office", IF(CA6<>0,"OBL in Transit from Origin to SIG", IF(BZ6<>0,"OBL in Origin - "&I6, IF(BY6<>0,"Draft Rcvd","No OBL Yet"))))))) -> No OBL Yet | CK6: =IF(CJ6<>0,"CERTS in Destination - "&J6,IF(CI6<>0,"CERT in Transit to -"&J6,IF(CH6<>0,"CERT in Origin - "&I6,IF(CH6="","No CERTS Yet")))) -> No CERTS Yet | CP6: =IF(CO6<>0,"Docs in Buyer's Nego Bank",IF(CN6<>0,"Docs in Transit to Buyer's Nego Bank",IF(CM6<>0,"Docs in Our Nego Bank",IF(CL6="TT PAYMENT","Not Applicable","")))) | CQ6: =(AN6*AI6*BJ6)-AZ6 -> -15450 | CU6: =IF(CS6="","",BJ6-CT6) | CV6: =IF(CS6="","",CU6/BJ6) | CW6: =IF(CS6="","",AZ6+CQ6) | CX6: =IF(CS6="","",BX6*2%) | CY6: =IF(CS6="","",AI6/B6) | DA6: =IF(CS6="","",B6-CZ6) | DC6: =IF(CS6="","",IF(CS6="","",DB6-C6)) | DE6: =IF(CS6="","",10%-DD6) | DF6: =IF(CS6="","",CU6*AI6) | DG6: =IF(CS6="","",IF(DA6>2,2*DA6*CT6*CY6,DA6*CT6*CY6)) | DH6: =IF(CS6="","",IF(DA6>2,2*(DA6-2*CT6*CY6),0)) | DI6: =IF(CS6="","",IF(DC6>0,DC6*0.5*CT6,0)) | DJ6: =IF(CS6="","",IF(DE6<0,DE6*CT6*AI6*1%,0)) | DK6: =IF(CS6="","",SUM(DF6:DJ6)) | DN6: =IF(CS6="","",SUM(DK6:DL6)) | DO6: =IF(CS6="","",BJ6*AI6-DN6) | DP6: =IF(CS6="","",AZ6+CQ6) | DQ6: =IF(CS6="","",IF((DP6-DO6)>0,DP6-DO6,"")) | DR6: =IF(CS6="","",IF((DO6-DP6)>0,(DO6-DP6),"")) | DS6: =IF(CS6="","",IF(DQ6="",H6,"VALENCY")) | DT6: =IF(DN6="","",IF(DN6>0,"CN", "DN")) | DY6: NO VINA/RBS REPORT | EA6: =IF(CS6="","", MIN(0,(IF(DA6>2,2,1)*DA6*CT6*CY6)) ) | EH6: VALENCY IVC | EN6: =EK6*EJ6 -> 0 | EV6: =IF(CR6<>0,"Final Pmt Recd",IF(CM6<>0,"Export Loan",IF(BZ6<>0,"Nego Pending",IF(Z6<>0,"Yet to load","Yet to load")))) -> Yet to load | EX6: =EW6/BJ6 -> #DIV/0! | EY6: Freight paid by origin | FD6: =FC6*BJ6 -> 0 | FL6: =IFERROR(EZ6-BY6,"") -> 0 | FM6: =IFERROR(BM6-FB6,"") -> 0 | FS6: =Y6 -> 20009532 | FT6: =AA6 -> 32014480
A7: =IF(DZ7="CLOSE","Trade closed",IF(DZ7="PMT Pending","FNF Settlement is Due",IF(CS7<>0,"FNF Reconcillation Onging",IF(CR7<>0," Final Pmt Recd , FNF Pending",IF(CM7<>0,"Exp Dox Presented to Bank, Pmt Pending",IF(BZ7<>0,"OBL Scan Recd, Nego Pending",IF(BM7<>0,"Sailed, OBL & Certs Pending",IF(BJ7<>0,"Stuffed, Yet to Sail",IF(BB7<>0,"SI Sent, Shipment Awaited",IF(BA7<>0,"Advance Rcvd, SI Pending",IF(Z7<>0,"SC Raised, Advance Pending",IF(X7<>0,"Deal Ticket Rcvd SC Pending", "Entry Pending")))))))))))) -> SI Sent, Shipment Awaited | B7: 48 | C7: 200 | D7: RCN | E7: =IF(AND(LEFT(TRIM(AA7&""),1)="3",BI7<>""),"CLOSE POSITION", IF(AND(LEFT(TRIM(AA7&""),1)="3",BI7=""),"SHORT POSITION", IF(AND(LEFT(TRIM(AA7&""),1)<>"3",BI7<>""),"LONG POSITION","ENTRY PENDING"))) -> CLOSE POSITION | F7: =AA7 -> 32014497 | H7: =AB7 -> FAVOURITE CASHEWS | I7: IVC | J7: INDIA | K7: =IF(BQ7<>0,BQ7,"") -> MANGALORE, INDIA | L7: =IF(BI7<>0,BI7,"") -> 267489852 | M7: =IF(BJ7<>0,BJ7,"") | N7: =IF(BM7<>0,BM7,"") | O7: =IF(BO7<>0,BO7,"") -> 46202 | P7: =CE7 -> No OBL Yet | R7: =CK7 -> No CERTS Yet | S7: =CP7 | T7: CLARIFICATION ON LATEST SOB | U7: ADVANCE RCVD 10/03- 267489852 | X7: 46076 | Y7: 20009551 | Z7: 46074 | AA7: 32014497 | AB7: FAVOURITE CASHEWS | AC7: April - 26 | AD7: 46142 | AE7: 0.1 | AF7: 200 | AG7: =AF7*(1-AE7) -> 180 | AH7: MT | AI7: 1510 | AJ7: =AI7*AF7 -> 302000 | AK7: CIF | AL7: DP SIGHT | AM7: 0.1 | AN7: 0.9 | AO7: 0 | AP7: 180 DAYS | AQ7: Mr. George | AR7: Mr. Rao | AS7: 5 | AT7: - | AU7: - | AV7: - | AZ7: =AF7*AI7*AM7 -> 30200 | BA7: 46091 | BB7: 46083 | BF7: 46083 | BI7: 267489852 | BK7: 40' | BO7: 46202 | BP7: IVC | BQ7: MANGALORE, INDIA | BX7: =BJ7*AI7 -> 0 | CE7: =IF(J7="VIETNAM", IF(CG7<>"","OBL in Vietnam Office", IF(CF7<>"","OBL in Transit from Vietnam Office", IF(CD7<>0,"OBL In Destination - "&J7, IF(CC7<>0,"OBL in Transit to Destination - "&J7, IF(CB7<>0,"OBL in SIG Office", IF(CA7<>0,"OBL in Transit from Origin to SIG", IF(BZ7<>0,"OBL in Origin - "&I7, IF(BY7<>0,"Draft Rcvd","No OBL Yet")))))))), IF(CO7<>0,"OBL In Destination - "&J7, IF(CM7<>0,"OBL in Transit with Nego Docs - "&J7, IF(CB7<>0,"OBL in SIG Office", IF(CA7<>0,"OBL in Transit from Origin to SIG", IF(BZ7<>0,"OBL in Origin - "&I7, IF(BY7<>0,"Draft Rcvd","No OBL Yet"))))))) -> No OBL Yet | CK7: =IF(CJ7<>0,"CERTS in Destination - "&J7,IF(CI7<>0,"CERT in Transit to -"&J7,IF(CH7<>0,"CERT in Origin - "&I7,IF(CH7="","No CERTS Yet")))) -> No CERTS Yet | CP7: =IF(CO7<>0,"Docs in Buyer's Nego Bank",IF(CN7<>0,"Docs in Transit to Buyer's Nego Bank",IF(CM7<>0,"Docs in Our Nego Bank",IF(CL7="TT PAYMENT","Not Applicable","")))) | CQ7: =(AN7*AI7*BJ7)-AZ7 -> -30200 | CU7: =IF(CS7="","",BJ7-CT7) | CV7: =IF(CS7="","",CU7/BJ7) | CW7: =IF(CS7="","",AZ7+CQ7) | CX7: =IF(CS7="","",BX7*2%) | CY7: =IF(CS7="","",AI7/B7) | DA7: =IF(CS7="","",B7-CZ7) | DC7: =IF(CS7="","",IF(CS7="","",DB7-C7)) | DE7: =IF(CS7="","",10%-DD7) | DF7: =IF(CS7="","",CU7*AI7) | DG7: =IF(CS7="","",IF(DA7>2,2*DA7*CT7*CY7,DA7*CT7*CY7)) | DH7: =IF(CS7="","",IF(DA7>2,2*(DA7-2*CT7*CY7),0)) | DI7: =IF(CS7="","",IF(DC7>0,DC7*0.5*CT7,0)) | DJ7: =IF(CS7="","",IF(DE7<0,DE7*CT7*AI7*1%,0)) | DK7: =IF(CS7="","",SUM(DF7:DJ7)) | DN7: =IF(CS7="","",SUM(DK7:DL7)) | DO7: =IF(CS7="","",BJ7*AI7-DN7) | DP7: =IF(CS7="","",AZ7+CQ7) | DQ7: =IF(CS7="","",IF((DP7-DO7)>0,DP7-DO7,"")) | DR7: =IF(CS7="","",IF((DO7-DP7)>0,(DO7-DP7),"")) | DS7: =IF(CS7="","",IF(DQ7="",H7,"VALENCY")) | DT7: =IF(DN7="","",IF(DN7>0,"CN", "DN")) | DY7: NO VINA/RBS REPORT | EA7: =IF(CS7="","", MIN(0,(IF(DA7>2,2,1)*DA7*CT7*CY7)) ) | EH7: VALENCY IVC | EN7: =EK7*EJ7 -> 0 | EV7: =IF(CR7<>0,"Final Pmt Recd",IF(CM7<>0,"Export Loan",IF(BZ7<>0,"Nego Pending",IF(Z7<>0,"Yet to load","Yet to load")))) -> Yet to load | EX7: =EW7/BJ7 -> #DIV/0! | EY7: Freight paid by origin | FD7: =FC7*BJ7 -> 0 | FL7: =IFERROR(EZ7-BY7,"") -> 0 | FM7: =IFERROR(BM7-FB7,"") -> 0 | FS7: =Y7 -> 20009551 | FT7: =AA7 -> 32014497
A8: =IF(DZ8="CLOSE","Trade closed",IF(DZ8="PMT Pending","FNF Settlement is Due",IF(CS8<>0,"FNF Reconcillation Onging",IF(CR8<>0," Final Pmt Recd , FNF Pending",IF(CM8<>0,"Exp Dox Presented to Bank, Pmt Pending",IF(BZ8<>0,"OBL Scan Recd, Nego Pending",IF(BM8<>0,"Sailed, OBL & Certs Pending",IF(BJ8<>0,"Stuffed, Yet to Sail",IF(BB8<>0,"SI Sent, Shipment Awaited",IF(BA8<>0,"Advance Rcvd, SI Pending",IF(Z8<>0,"SC Raised, Advance Pending",IF(X8<>0,"Deal Ticket Rcvd SC Pending", "Entry Pending")))))))))))) -> OBL Scan Recd, Nego Pending | B8: 49 | C8: 185 | D8: RCN | E8: =IF(AND(LEFT(TRIM(AA8&""),1)="3",BI8<>""),"CLOSE POSITION", IF(AND(LEFT(TRIM(AA8&""),1)="3",BI8=""),"SHORT POSITION", IF(AND(LEFT(TRIM(AA8&""),1)<>"3",BI8<>""),"LONG POSITION","ENTRY PENDING"))) -> CLOSE POSITION | F8: =AA8 -> 32015806-1 | H8: =AB8 -> INDIA ENTERPRISES | I8: NIGERIA(SAKI) | J8: INDIA | K8: =IF(BQ8<>0,BQ8,"") -> MANGALORE, INDIA | L8: =IF(BI8<>0,BI8,"") -> MEDULG632861 | M8: =IF(BJ8<>0,BJ8,"") -> 100.48 | N8: =IF(BM8<>0,BM8,"") -> 46158 | O8: =IF(BO8<>0,BO8,"") -> 46193 | P8: =CE8 -> OBL in Origin - NIGERIA(SAKI) | R8: =CK8 -> No CERTS Yet | S8: =CP8 | T8: OBL Expected on 25/5 | U8: OBL RCVD 25/5- CERT PENDING | V8: ADDENDUM 01-EXTENSION TILL 15TH MAY | W8: OBL COURRIER PENDING | X8: 46090 | Y8: 20009815 | Z8: 46104 | AA8: 32015806-1 | AB8: INDIA ENTERPRISES | AC8: April - 26 | AD8: 46157 | AE8: 0.1 | AF8: 100 | AG8: =AF8*(1-AE8) -> 90 | AH8: MT | AI8: 1575 | AJ8: 315000 | AK8: CIF | AL8: DP SIGHT | AM8: 0.1 | AN8: 0.9 | AO8: 0 | AP8: 180 DAYS | AQ8: Mr. George | AT8: - | AU8: - | AV8: - | AY8: 46094 | AZ8: =AF8*AI8*AM8 -> 15750 | BA8: 46106 | BB8: 46094 | BI8: MEDULG632861 | BJ8: 100.48 | BK8: 40' | BM8: 46158 | BN8: DFSU6311600 | BO8: 46193 | BP8: NIGERIA | BQ8: MANGALORE, INDIA | BR8: MSC | BX8: =BJ8*AI8 -> 158256 | BZ8: 46168 | CE8: =IF(J8="VIETNAM", IF(CG8<>"","OBL in Vietnam Office", IF(CF8<>"","OBL in Transit from Vietnam Office", IF(CD8<>0,"OBL In Destination - "&J8, IF(CC8<>0,"OBL in Transit to Destination - "&J8, IF(CB8<>0,"OBL in SIG Office", IF(CA8<>0,"OBL in Transit from Origin to SIG", IF(BZ8<>0,"OBL in Origin - "&I8, IF(BY8<>0,"Draft Rcvd","No OBL Yet")))))))), IF(CO8<>0,"OBL In Destination - "&J8, IF(CM8<>0,"OBL in Transit with Nego Docs - "&J8, IF(CB8<>0,"OBL in SIG Office", IF(CA8<>0,"OBL in Transit from Origin to SIG", IF(BZ8<>0,"OBL in Origin - "&I8, IF(BY8<>0,"Draft Rcvd","No OBL Yet"))))))) -> OBL in Origin - NIGERIA(SAKI) | CK8: =IF(CJ8<>0,"CERTS in Destination - "&J8,IF(CI8<>0,"CERT in Transit to -"&J8,IF(CH8<>0,"CERT in Origin - "&I8,IF(CH8="","No CERTS Yet")))) -> No CERTS Yet | CP8: =IF(CO8<>0,"Docs in Buyer's Nego Bank",IF(CN8<>0,"Docs in Transit to Buyer's Nego Bank",IF(CM8<>0,"Docs in Our Nego Bank",IF(CL8="TT PAYMENT","Not Applicable","")))) | CQ8: =(AN8*AI8*BJ8)-AZ8 -> 126680.4 | CU8: =IF(CS8="","",BJ8-CT8) | CV8: =IF(CS8="","",CU8/BJ8) | CW8: =IF(CS8="","",AZ8+CQ8) | CX8: =IF(CS8="","",BX8*2%) | CY8: =IF(CS8="","",AI8/B8) | DA8: =IF(CS8="","",B8-CZ8) | DC8: =IF(CS8="","",IF(CS8="","",DB8-C8)) | DE8: =IF(CS8="","",10%-DD8) | DF8: =IF(CS8="","",CU8*AI8) | DG8: =IF(CS8="","",IF(DA8>2,2*DA8*CT8*CY8,DA8*CT8*CY8)) | DH8: =IF(CS8="","",IF(DA8>2,2*(DA8-2*CT8*CY8),0)) | DI8: =IF(CS8="","",IF(DC8>0,DC8*0.5*CT8,0)) | DJ8: =IF(CS8="","",IF(DE8<0,DE8*CT8*AI8*1%,0)) | DK8: =IF(CS8="","",SUM(DF8:DJ8)) | DN8: =IF(CS8="","",SUM(DK8:DL8)) | DO8: =IF(CS8="","",BJ8*AI8-DN8) | DP8: =IF(CS8="","",AZ8+CQ8) | DQ8: =IF(CS8="","",IF((DP8-DO8)>0,DP8-DO8,"")) | DR8: =IF(CS8="","",IF((DO8-DP8)>0,(DO8-DP8),"")) | DS8: =IF(CS8="","",IF(DQ8="",H8,"VALENCY")) | DT8: =IF(DN8="","",IF(DN8>0,"CN", "DN")) | DY8: NO VINA/RBS REPORT | EA8: =IF(CS8="","", MIN(0,(IF(DA8>2,2,1)*DA8*CT8*CY8)) ) | EH8: Valency Nigeria | EN8: =EK8*EJ8 -> 0 | EV8: =IF(CR8<>0,"Final Pmt Recd",IF(CM8<>0,"Export Loan",IF(BZ8<>0,"Nego Pending",IF(Z8<>0,"Yet to load","Yet to load")))) -> Nego Pending | EX8: =EW8/BJ8 -> 0 | EY8: Freight paid by origin | FD8: =FC8*BJ8 -> 0 | FL8: =IFERROR(EZ8-BY8,"") -> 0 | FM8: =IFERROR(BM8-FB8,"") -> 46158 | FS8: =Y8 -> 20009815 | FT8: =AA8 -> 32015806-1
A9: =IF(DZ9="CLOSE","Trade closed",IF(DZ9="PMT Pending","FNF Settlement is Due",IF(CS9<>0,"FNF Reconcillation Onging",IF(CR9<>0," Final Pmt Recd , FNF Pending",IF(CM9<>0,"Exp Dox Presented to Bank, Pmt Pending",IF(BZ9<>0,"OBL Scan Recd, Nego Pending",IF(BM9<>0,"Sailed, OBL & Certs Pending",IF(BJ9<>0,"Stuffed, Yet to Sail",IF(BB9<>0,"SI Sent, Shipment Awaited",IF(BA9<>0,"Advance Rcvd, SI Pending",IF(Z9<>0,"SC Raised, Advance Pending",IF(X9<>0,"Deal Ticket Rcvd SC Pending", "Entry Pending")))))))))))) -> Sailed, OBL & Certs Pending | B9: 49 | C9: 185 | D9: RCN | E9: =IF(AND(LEFT(TRIM(AA9&""),1)="3",BI9<>""),"CLOSE POSITION", IF(AND(LEFT(TRIM(AA9&""),1)="3",BI9=""),"SHORT POSITION", IF(AND(LEFT(TRIM(AA9&""),1)<>"3",BI9<>""),"LONG POSITION","ENTRY PENDING"))) -> CLOSE POSITION | F9: =AA9 -> 32015806-2 | H9: =AB9 -> INDIA ENTERPRISES | I9: NIGERIA(SAKI) | J9: INDIA | K9: =IF(BQ9<>0,BQ9,"") -> MANGALORE, INDIA | L9: =IF(BI9<>0,BI9,"") -> MEDULG632812 | M9: =IF(BJ9<>0,BJ9,"") -> 99.989 | N9: =IF(BM9<>0,BM9,"") -> 46158 | O9: =IF(BO9<>0,BO9,"") -> 46193 | P9: =CE9 -> No OBL Yet | R9: =CK9 -> No CERTS Yet | S9: =CP9 | T9: OBL Expected on 25/5 | U9: PENDING OBL & CERTS-OBL EXPETCED 25/5 | V9: ADDENDUM 01-EXTENSION TILL 15TH MAY | W9: OBL EXPECTED 25/5 | X9: 46090 | Y9: 20009815 | Z9: 46104 | AA9: 32015806-2 | AB9: INDIA ENTERPRISES | AC9: April - 26 | AD9: 46157 | AE9: 0.1 | AF9: 100 | AG9: =AF9*(1-AE9) -> 90 | AH9: MT | AI9: 1575 | AJ9: 315000 | AK9: CIF | AL9: DP SIGHT | AM9: 0.1 | AN9: 0.9 | AO9: 0 | AP9: 180 DAYS | AQ9: Mr. George | AT9: - | AU9: - | AV9: - | AY9: 46094 | AZ9: =AF9*AI9*AM9 -> 15750 | BA9: 46106 | BB9: 46094 | BI9: MEDULG632812 | BJ9: 99.989 | BK9: 40' | BM9: 46158 | BN9: BMOU4009029 | BO9: 46193 | BP9: NIGERIA | BQ9: MANGALORE, INDIA | BR9: MSC | BX9: =BJ9*AI9 -> 157482.68 | CE9: =IF(J9="VIETNAM", IF(CG9<>"","OBL in Vietnam Office", IF(CF9<>"","OBL in Transit from Vietnam Office", IF(CD9<>0,"OBL In Destination - "&J9, IF(CC9<>0,"OBL in Transit to Destination - "&J9, IF(CB9<>0,"OBL in SIG Office", IF(CA9<>0,"OBL in Transit from Origin to SIG", IF(BZ9<>0,"OBL in Origin - "&I9, IF(BY9<>0,"Draft Rcvd","No OBL Yet")))))))), IF(CO9<>0,"OBL In Destination - "&J9, IF(CM9<>0,"OBL in Transit with Nego Docs - "&J9, IF(CB9<>0,"OBL in SIG Office", IF(CA9<>0,"OBL in Transit from Origin to SIG", IF(BZ9<>0,"OBL in Origin - "&I9, IF(BY9<>0,"Draft Rcvd","No OBL Yet"))))))) -> No OBL Yet | CK9: =IF(CJ9<>0,"CERTS in Destination - "&J9,IF(CI9<>0,"CERT in Transit to -"&J9,IF(CH9<>0,"CERT in Origin - "&I9,IF(CH9="","No CERTS Yet")))) -> No CERTS Yet | CP9: =IF(CO9<>0,"Docs in Buyer's Nego Bank",IF(CN9<>0,"Docs in Transit to Buyer's Nego Bank",IF(CM9<>0,"Docs in Our Nego Bank",IF(CL9="TT PAYMENT","Not Applicable","")))) | CQ9: =(AN9*AI9*BJ9)-AZ9 -> 125984.41 | CU9: =IF(CS9="","",BJ9-CT9) | CV9: =IF(CS9="","",CU9/BJ9) | CW9: =IF(CS9="","",AZ9+CQ9) | CX9: =IF(CS9="","",BX9*2%) | CY9: =IF(CS9="","",AI9/B9) | DA9: =IF(CS9="","",B9-CZ9) | DC9: =IF(CS9="","",IF(CS9="","",DB9-C9)) | DE9: =IF(CS9="","",10%-DD9) | DF9: =IF(CS9="","",CU9*AI9) | DG9: =IF(CS9="","",IF(DA9>2,2*DA9*CT9*CY9,DA9*CT9*CY9)) | DH9: =IF(CS9="","",IF(DA9>2,2*(DA9-2*CT9*CY9),0)) | DI9: =IF(CS9="","",IF(DC9>0,DC9*0.5*CT9,0)) | DJ9: =IF(CS9="","",IF(DE9<0,DE9*CT9*AI9*1%,0)) | DK9: =IF(CS9="","",SUM(DF9:DJ9)) | DN9: =IF(CS9="","",SUM(DK9:DL9)) | DO9: =IF(CS9="","",BJ9*AI9-DN9) | DP9: =IF(CS9="","",AZ9+CQ9) | DQ9: =IF(CS9="","",IF((DP9-DO9)>0,DP9-DO9,"")) | DR9: =IF(CS9="","",IF((DO9-DP9)>0,(DO9-DP9),"")) | DS9: =IF(CS9="","",IF(DQ9="",H9,"VALENCY")) | DT9: =IF(DN9="","",IF(DN9>0,"CN", "DN")) | DY9: NO VINA/RBS REPORT | EA9: =IF(CS9="","", MIN(0,(IF(DA9>2,2,1)*DA9*CT9*CY9)) ) | EH9: Valency Nigeria | EN9: =EK9*EJ9 -> 0 | EV9: =IF(CR9<>0,"Final Pmt Recd",IF(CM9<>0,"Export Loan",IF(BZ9<>0,"Nego Pending",IF(Z9<>0,"Yet to load","Yet to load")))) -> Yet to load | EX9: =EW9/BJ9 -> 0 | EY9: Freight paid by origin | FD9: =FC9*BJ9 -> 0 | FL9: =IFERROR(EZ9-BY9,"") -> 0 | FM9: =IFERROR(BM9-FB9,"") -> 46158 | FS9: =Y9 -> 20009815 | FT9: =AA9 -> 32015806-2
A10: =IF(DZ10="CLOSE","Trade closed",IF(DZ10="PMT Pending","FNF Settlement is Due",IF(CS10<>0,"FNF Reconcillation Onging",IF(CR10<>0," Final Pmt Recd , FNF Pending",IF(CM10<>0,"Exp Dox Presented to Bank, Pmt Pending",IF(BZ10<>0,"OBL Scan Recd, Nego Pending",IF(BM10<>0,"Sailed, OBL & Certs Pending",IF(BJ10<>0,"Stuffed, Yet to Sail",IF(BB10<>0,"SI Sent, Shipment Awaited",IF(BA10<>0,"Advance Rcvd, SI Pending",IF(Z10<>0,"SC Raised, Advance Pending",IF(X10<>0,"Deal Ticket Rcvd SC Pending", "Entry Pending")))))))))))) -> Exp Dox Presented to Bank, Pmt Pending | B10: 47 | C10: 185 | D10: RCN | E10: =IF(AND(LEFT(TRIM(AA10&""),1)="3",BI10<>""),"CLOSE POSITION", IF(AND(LEFT(TRIM(AA10&""),1)="3",BI10=""),"SHORT POSITION", IF(AND(LEFT(TRIM(AA10&""),1)<>"3",BI10<>""),"LONG POSITION","ENTRY PENDING"))) -> CLOSE POSITION | F10: =AA10 -> 32015281-4 | H10: =AB10 -> Valency Agro (Processing) | I10: GHANA | J10: INDIA | K10: =IF(BQ10<>0,BQ10,"") -> MUNDRA, INDIA | L10: =IF(BI10<>0,BI10,"") -> ONEYTEMG00306400 | M10: =IF(BJ10<>0,BJ10,"") -> 103.59 | N10: =IF(BM10<>0,BM10,"") -> 46103 | O10: =IF(BO10<>0,BO10,"") -> 46146 | P10: =CE10 -> OBL In Destination - INDIA | R10: =CK10 -> CERTS in Destination - INDIA | S10: =CP10 -> Docs in Buyer's Nego Bank | T10: =IFERROR(_xlfn.XLOOKUP(F10, '[2]Data 2026'!$H$12:$H$111, '[2]Data 2026'!$CL$12:$CL$111),"") | U10: Payment by Valency Agro will be done, 120 days after BL date- CARGO CLEARED. | X10: 46093 | Y10: 20009747 | Z10: =X10 -> 46093 | AA10: 32015281-4 | AB10: Valency Agro (Processing) | AC10: March - 26 | AD10: 46112 | AE10: 0.1 | AF10: 100 | AG10: =AF10*(1-AE10) -> 90 | AH10: MT | AI10: 1585 | AJ10: =AI10*AF10 -> 158500 | AK10: CIF | AL10: 120 DAYS FROM BL DATE | AM10: 0 | AN10: 1 | AO10: 0 | AP10: 180 DAYS | AQ10: Mr. Naveen | AR10: Direct | AT10: - | AU10: - | AV10: - | AZ10: =AF10*AI10*AM10 -> 0 | BA10: =Z10 -> 46093 | BB10: 46078 | BF10: 46078 | BI10: ONEYTEMG00306400 | BJ10: 103.59 | BK10: 40' | BL10: 4 | BM10: 46103 | BO10: 46146 | BP10: GHANA | BQ10: MUNDRA, INDIA | BR10: ONE LINE | BT10: GIALOVA | BU10: 2607E | BV10: 90082920 | BX10: =BJ10*AI10 -> 164190.15 | BZ10: 46122 | CB10: 46125 | CC10: 9016936213 | CD10: 46128 | CE10: =IF(J10="VIETNAM", IF(CG10<>"","OBL in Vietnam Office", IF(CF10<>"","OBL in Transit from Vietnam Office", IF(CD10<>0,"OBL In Destination - "&J10, IF(CC10<>0,"OBL in Transit to Destination - "&J10, IF(CB10<>0,"OBL in SIG Office", IF(CA10<>0,"OBL in Transit from Origin to SIG", IF(BZ10<>0,"OBL in Origin - "&I10, IF(BY10<>0,"Draft Rcvd","No OBL Yet")))))))), IF(CO10<>0,"OBL In Destination - "&J10, IF(CM10<>0,"OBL in Transit with Nego Docs - "&J10, IF(CB10<>0,"OBL in SIG Office", IF(CA10<>0,"OBL in Transit from Origin to SIG", IF(BZ10<>0,"OBL in Origin - "&I10, IF(BY10<>0,"Draft Rcvd","No OBL Yet"))))))) -> OBL In Destination - INDIA | CI10: 9016936213 | CJ10: 46128 | CK10: =IF(CJ10<>0,"CERTS in Destination - "&J10,IF(CI10<>0,"CERT in Transit to -"&J10,IF(CH10<>0,"CERT in Origin - "&I10,IF(CH10="","No CERTS Yet")))) -> CERTS in Destination - INDIA | CL10: ICICI BANK | CM10: 46125 | CN10: 9016936213 | CO10: 46128 | CP10: =IF(CO10<>0,"Docs in Buyer's Nego Bank",IF(CN10<>0,"Docs in Transit to Buyer's Nego Bank",IF(CM10<>0,"Docs in Our Nego Bank",IF(CL10="TT PAYMENT","Not Applicable","")))) -> Docs in Buyer's Nego Bank | CQ10: =(AN10*AI10*BJ10)-AZ10 -> 164190.15 | CU10: =IF(CS10="","",BJ10-CT10) | CV10: =IF(CS10="","",CU10/BJ10) | CW10: =IF(CS10="","",AZ10+CQ10) | CX10: =IF(CS10="","",BX10*2%) | CY10: =IF(CS10="","",AI10/B10) | DA10: =IF(CS10="","",B10-CZ10) | DC10: =IF(CS10="","",IF(CS10="","",DB10-C10)) | DE10: =IF(CS10="","",10%-DD10) | DF10: =IF(CS10="","",CU10*AI10) | DG10: =IF(CS10="","",IF(DA10>2,2*DA10*CT10*CY10,DA10*CT10*CY10)) | DH10: =IF(CS10="","",IF(DA10>2,2*(DA10-2*CT10*CY10),0)) | DI10: =IF(CS10="","",IF(DC10>0,DC10*0.5*CT10,0)) | DJ10: =IF(CS10="","",IF(DE10<0,DE10*CT10*AI10*1%,0)) | DK10: =IF(CS10="","",SUM(DF10:DJ10)) | DN10: =IF(CS10="","",SUM(DK10:DL10)) | DO10: =IF(CS10="","",BJ10*AI10-DN10) | DP10: =IF(CS10="","",AZ10+CQ10) | DQ10: =IF(CS10="","",IF((DP10-DO10)>0,DP10-DO10,"")) | DR10: =IF(CS10="","",IF((DO10-DP10)>0,(DO10-DP10),"")) | DS10: =IF(CS10="","",IF(DQ10="",H10,"VALENCY")) | DT10: =IF(DN10="","",IF(DN10>0,"CN", "DN")) | DY10: NO VINA/RBS REPORT | EA10: =IF(CS10="","", MIN(0,(IF(DA10>2,2,1)*DA10*CT10*CY10)) ) | EH10: Valora Exim | EI10: FOB | EN10: =EK10*EJ10 -> 0 | EV10: =IF(CR10<>0,"Final Pmt Recd",IF(CM10<>0,"Export Loan",IF(BZ10<>0,"Nego Pending",IF(Z10<>0,"Yet to load","Yet to load")))) -> Export Loan | EX10: =EW10/BJ10 -> 0 | EY10: Freight paid by origin | FD10: =FC10*BJ10 -> 0 | FL10: =IFERROR(EZ10-BY10,"") -> 0 | FM10: =IFERROR(BM10-FB10,"") -> 46103 | FS10: =Y10 -> 20009747 | FT10: =AA10 -> 32015281-4 | GD10: 90082920 | GF10: done
A11: =IF(DZ11="CLOSE","Trade closed",IF(DZ11="PMT Pending","FNF Settlement is Due",IF(CS11<>0,"FNF Reconcillation Onging",IF(CR11<>0," Final Pmt Recd , FNF Pending",IF(CM11<>0,"Exp Dox Presented to Bank, Pmt Pending",IF(BZ11<>0,"OBL Scan Recd, Nego Pending",IF(BM11<>0,"Sailed, OBL & Certs Pending",IF(BJ11<>0,"Stuffed, Yet to Sail",IF(BB11<>0,"SI Sent, Shipment Awaited",IF(BA11<>0,"Advance Rcvd, SI Pending",IF(Z11<>0,"SC Raised, Advance Pending",IF(X11<>0,"Deal Ticket Rcvd SC Pending", "Entry Pending")))))))))))) -> Final Pmt Recd , FNF Pending | B11: 47 | C11: 205 | D11: RCN | E11: =IF(AND(LEFT(TRIM(AA11&""),1)="3",BI11<>""),"CLOSE POSITION", IF(AND(LEFT(TRIM(AA11&""),1)="3",BI11=""),"SHORT POSITION", IF(AND(LEFT(TRIM(AA11&""),1)<>"3",BI11<>""),"LONG POSITION","ENTRY PENDING"))) -> CLOSE POSITION | F11: =AA11 -> 32015286 | H11: =AB11 -> MOI COMMODITIES INDIA PVT LTD | I11: BURKINA FASO | J11: INDIA | K11: =IF(BQ11<>0,BQ11,"") -> MUNDRA, INDIA | L11: =IF(BI11<>0,BI11,"") -> ONEYTEMG00307500 | M11: =IF(BJ11<>0,BJ11,"") -> 182.57 | N11: =IF(BM11<>0,BM11,"") -> 46125 | O11: =IF(BO11<>0,BO11,"") -> 46163 | P11: =CE11 -> OBL In Destination - INDIA | R11: =CK11 -> CERT in Transit to -INDIA | S11: =CP11 -> Docs in Buyer's Nego Bank | U11: PAYMENT RCVD 27/05 | W11: PAYMENT PENDING-CERTS WILL REACH 2ND JUNE | X11: 46134 | Y11: 20009765 | Z11: 46098 | AA11: 32015286 | AB11: MOI COMMODITIES INDIA PVT LTD | AC11: March /15th April | AD11: 46127 | AE11: 0.1 | AF11: 200 | AG11: =AF11*(1-AE11) -> 180 | AH11: MT | AI11: 1485 | AJ11: =AI11*AF11 -> 297000 | AK11: CIF | AL11: 10% ADVANCE 90%DP AT SIGHT | AM11: 0.1 | AN11: 0.9 | AO11: 0 | AP11: 180 DAYS | AQ11: Mr. George | AR11: Direct | AT11: - | AU11: - | AV11: - | AZ11: =AF11*AI11*AM11 -> 29700 | BA11: 46105 | BB11: 46099 | BF11: 46099 | BI11: ONEYTEMG00307500 | BJ11: 182.57 | BK11: 40' | BL11: 7 | BM11: 46125 | BO11: 46163 | BP11: TEMA, GHANA | BQ11: MUNDRA, INDIA | BR11: ONE LINE | BT11: SPIL KARTIKA | BU11: 2609E | BV11: 90085007 | BW11: 46125 | BX11: =BJ11*AI11 -> 271116.45 | BZ11: 46137 | CA11: 5182275906 | CB11: 46146 | CE11: =IF(J11="VIETNAM", IF(CG11<>"","OBL in Vietnam Office", IF(CF11<>"","OBL in Transit from Vietnam Office", IF(CD11<>0,"OBL In Destination - "&J11, IF(CC11<>0,"OBL in Transit to Destination - "&J11, IF(CB11<>0,"OBL in SIG Office", IF(CA11<>0,"OBL in Transit from Origin to SIG", IF(BZ11<>0,"OBL in Origin - "&I11, IF(BY11<>0,"Draft Rcvd","No OBL Yet")))))))), IF(CO11<>0,"OBL In Destination - "&J11, IF(CM11<>0,"OBL in Transit with Nego Docs - "&J11, IF(CB11<>0,"OBL in SIG Office", IF(CA11<>0,"OBL in Transit from Origin to SIG", IF(BZ11<>0,"OBL in Origin - "&I11, IF(BY11<>0,"Draft Rcvd","No OBL Yet"))))))) -> OBL In Destination - INDIA | CH11: 46164 | CI11: 6696514112 FUMI / 1377954734 LDC/PHYTO | CK11: =IF(CJ11<>0,"CERTS in Destination - "&J11,IF(CI11<>0,"CERT in Transit to -"&J11,IF(CH11<>0,"CERT in Origin - "&I11,IF(CH11="","No CERTS Yet")))) -> CERT in Transit to -INDIA | CL11: HABIB BANK | CM11: 46146 | CN11: 6065372143 | CO11: 46148 | CP11: =IF(CO11<>0,"Docs in Buyer's Nego Bank",IF(CN11<>0,"Docs in Transit to Buyer's Nego Bank",IF(CM11<>0,"Docs in Our Nego Bank",IF(CL11="TT PAYMENT","Not Applicable","")))) -> Docs in Buyer's Nego Bank | CQ11: 241416.45 | CR11: 46169 | CU11: =IF(CS11="","",BJ11-CT11) | CV11: =IF(CS11="","",CU11/BJ11) | CW11: =IF(CS11="","",AZ11+CQ11) | CX11: =IF(CS11="","",BX11*2%) | CY11: =IF(CS11="","",AI11/B11) | DA11: =IF(CS11="","",B11-CZ11) | DC11: =IF(CS11="","",IF(CS11="","",DB11-C11)) | DE11: =IF(CS11="","",10%-DD11) | DF11: =IF(CS11="","",CU11*AI11) | DG11: =IF(CS11="","",IF(DA11>2,2*DA11*CT11*CY11,DA11*CT11*CY11)) | DH11: =IF(CS11="","",IF(DA11>2,2*(DA11-2*CT11*CY11),0)) | DI11: =IF(CS11="","",IF(DC11>0,DC11*0.5*CT11,0)) | DJ11: =IF(CS11="","",IF(DE11<0,DE11*CT11*AI11*1%,0)) | DK11: =IF(CS11="","",SUM(DF11:DJ11)) | DN11: =IF(CS11="","",SUM(DK11:DL11)) | DO11: =IF(CS11="","",BJ11*AI11-DN11) | DP11: =IF(CS11="","",AZ11+CQ11) | DQ11: =IF(CS11="","",IF((DP11-DO11)>0,DP11-DO11,"")) | DR11: =IF(CS11="","",IF((DO11-DP11)>0,(DO11-DP11),"")) | DS11: =IF(CS11="","",IF(DQ11="",H11,"VALENCY")) | DT11: =IF(DN11="","",IF(DN11>0,"CN", "DN")) | DY11: NO VINA/RBS REPORT | EA11: =IF(CS11="","", MIN(0,(IF(DA11>2,2,1)*DA11*CT11*CY11)) ) | EE11: 4900009632 | EH11: VALORA BURKINA EXIM SARL | EJ11: =BJ11 -> 182.57 | EK11: 1200 | EN11: =EK11*EJ11 -> 219084 | EV11: =IF(CR11<>0,"Final Pmt Recd",IF(CM11<>0,"Export Loan",IF(BZ11<>0,"Nego Pending",IF(Z11<>0,"Yet to load","Yet to load")))) -> Final Pmt Recd | EX11: =EW11/BJ11 -> 0 | EY11: Freight paid by origin | FA11: 22141468 | FD11: =FC11*BJ11 -> 0 | FL11: =IFERROR(EZ11-BY11,"") -> 0 | FM11: =IFERROR(BM11-FB11,"") -> 46125 | FS11: =Y11 -> 20009765 | FT11: =AA11 -> 32015286
A12: =IF(DZ12="CLOSE","Trade closed",IF(DZ12="PMT Pending","FNF Settlement is Due",IF(CS12<>0,"FNF Reconcillation Onging",IF(CR12<>0," Final Pmt Recd , FNF Pending",IF(CM12<>0,"Exp Dox Presented to Bank, Pmt Pending",IF(BZ12<>0,"OBL Scan Recd, Nego Pending",IF(BM12<>0,"Sailed, OBL & Certs Pending",IF(BJ12<>0,"Stuffed, Yet to Sail",IF(BB12<>0,"SI Sent, Shipment Awaited",IF(BA12<>0,"Advance Rcvd, SI Pending",IF(Z12<>0,"SC Raised, Advance Pending",IF(X12<>0,"Deal Ticket Rcvd SC Pending", "Entry Pending")))))))))))) -> Exp Dox Presented to Bank, Pmt Pending | B12: 50 | C12: 185 | D12: RCN | E12: =IF(AND(LEFT(TRIM(AA12&""),1)="3",BI12<>""),"CLOSE POSITION", IF(AND(LEFT(TRIM(AA12&""),1)="3",BI12=""),"SHORT POSITION", IF(AND(LEFT(TRIM(AA12&""),1)<>"3",BI12<>""),"LONG POSITION","ENTRY PENDING"))) -> CLOSE POSITION | F12: =AA12 -> 32014448-3 | H12: =AB12 -> Valency Agro (Processing) | I12: NIGERIA(OGB) | J12: INDIA | K12: =IF(BQ12<>0,BQ12,"") -> MANGALORE, INDIA | L12: =IF(BI12<>0,BI12,"") -> MEDULG626012 | M12: =IF(BJ12<>0,BJ12,"") -> 105.235 | N12: =IF(BM12<>0,BM12,"") -> 46110 | O12: =IF(BO12<>0,BO12,"") -> 46157 | P12: =CE12 -> OBL In Destination - INDIA | R12: =CK12 -> CERTS in Destination - INDIA | S12: =CP12 -> Docs in Buyer's Nego Bank | T12: =IFERROR(_xlfn.XLOOKUP(F12, '[2]Data 2026'!$H$12:$H$111, '[2]Data 2026'!$CL$12:$CL$111),"") | U12: Payment by Valency Agro will be done, 90 days after BL date- CARGO CLEARED. | X12: 46066 | Y12: 20009485 | Z12: 46066 | AA12: 32014448-3 | AB12: Valency Agro (Processing) | AC12: 46082 | AD12: 46112 | AE12: 0.1 | AF12: =BJ12 -> 105.235 | AG12: =AF12*(1-AE12) -> 94.7115 | AH12: MT | AI12: 1683 | AJ12: 1700000 | AK12: CIF | AL12: 90 DAYS FROM BL DATE | AM12: 0 | AN12: 1 | AO12: 0 | AP12: 180 DAYS | AQ12: Mr. Naveen | AR12: Direct | AT12: - | AU12: - | AV12: - | AZ12: =AF12*AI12*AM12 -> 0 | BA12: 46069 | BB12: 46073 | BF12: 46073 | BI12: MEDULG626012 | BJ12: 105.235 | BK12: 40' | BL12: 4 | BM12: 46110 | BN12: Vizhinjam international 10-05 | BO12: 46157 | BP12: NIGERIA | BQ12: MANGALORE, INDIA | BR12: MSC | BS12: LASTBORN | BV12: 90084574 | BX12: =BJ12*AI12 -> 177110.51 | BZ12: 46129 | CA12: 4567280594 | CB12: 46132 | CE12: =IF(J12="VIETNAM", IF(CG12<>"","OBL in Vietnam Office", IF(CF12<>"","OBL in Transit from Vietnam Office", IF(CD12<>0,"OBL In Destination - "&J12, IF(CC12<>0,"OBL in Transit to Destination - "&J12, IF(CB12<>0,"OBL in SIG Office", IF(CA12<>0,"OBL in Transit from Origin to SIG", IF(BZ12<>0,"OBL in Origin - "&I12, IF(BY12<>0,"Draft Rcvd","No OBL Yet")))))))), IF(CO12<>0,"OBL In Destination - "&J12, IF(CM12<>0,"OBL in Transit with Nego Docs - "&J12, IF(CB12<>0,"OBL in SIG Office", IF(CA12<>0,"OBL in Transit from Origin to SIG", IF(BZ12<>0,"OBL in Origin - "&I12, IF(BY12<>0,"Draft Rcvd","No OBL Yet"))))))) -> OBL In Destination - INDIA | CH12: 46141 | CI12: 1335828874 | CJ12: 46157 | CK12: =IF(CJ12<>0,"CERTS in Destination - "&J12,IF(CI12<>0,"CERT in Transit to -"&J12,IF(CH12<>0,"CERT in Origin - "&I12,IF(CH12="","No CERTS Yet")))) -> CERTS in Destination - INDIA | CL12: ICICI BANK | CM12: 46139 | CN12: 8585994476 | CO12: 46147 | CP12: =IF(CO12<>0,"Docs in Buyer's Nego Bank",IF(CN12<>0,"Docs in Transit to Buyer's Nego Bank",IF(CM12<>0,"Docs in Our Nego Bank",IF(CL12="TT PAYMENT","Not Applicable","")))) -> Docs in Buyer's Nego Bank | CQ12: =(AN12*AI12*BJ12)-AZ12 -> 177110.51 | CU12: =IF(CS12="","",BJ12-CT12) | CV12: =IF(CS12="","",CU12/BJ12) | CW12: =IF(CS12="","",AZ12+CQ12) | CX12: =IF(CS12="","",BX12*2%) | CY12: =IF(CS12="","",AI12/B12) | DA12: =IF(CS12="","",B12-CZ12) | DC12: =IF(CS12="","",IF(CS12="","",DB12-C12)) | DE12: =IF(CS12="","",10%-DD12) | DF12: =IF(CS12="","",CU12*AI12) | DG12: =IF(CS12="","",IF(DA12>2,2*DA12*CT12*CY12,DA12*CT12*CY12)) | DH12: =IF(CS12="","",IF(DA12>2,2*(DA12-2*CT12*CY12),0)) | DI12: =IF(CS12="","",IF(DC12>0,DC12*0.5*CT12,0)) | DJ12: =IF(CS12="","",IF(DE12<0,DE12*CT12*AI12*1%,0)) | DK12: =IF(CS12="","",SUM(DF12:DJ12)) | DN12: =IF(CS12="","",SUM(DK12:DL12)) | DO12: =IF(CS12="","",BJ12*AI12-DN12) | DP12: =IF(CS12="","",AZ12+CQ12) | DQ12: =IF(CS12="","",IF((DP12-DO12)>0,DP12-DO12,"")) | DR12: =IF(CS12="","",IF((DO12-DP12)>0,(DO12-DP12),"")) | DS12: =IF(CS12="","",IF(DQ12="",H12,"VALENCY")) | DT12: =IF(DN12="","",IF(DN12>0,"CN", "DN")) | DY12: NO VINA/RBS REPORT | EA12: =IF(CS12="","", MIN(0,(IF(DA12>2,2,1)*DA12*CT12*CY12)) ) | EB12: 47.38 | EC12: 191 | ED12: 8.95 | EE12: 4900009113 | EH12: LASTBORN GENERAL MERCHANT LTD | EI12: FOB | EJ12: =BJ12 -> 105.235 | EK12: 1600 | EN12: =EK12*EJ12 -> 168376 | EO12: FOB | ER12: 165008.48 | EV12: =IF(CR12<>0,"Final Pmt Recd",IF(CM12<>0,"Export Loan",IF(BZ12<>0,"Nego Pending",IF(Z12<>0,"Yet to load","Yet to load")))) -> Export Loan | EX12: =EW12/BJ12 -> 0 | EY12: Freight paid by origin | FD12: =FC12*BJ12 -> 0 | FL12: =IFERROR(EZ12-BY12,"") -> 0 | FM12: =IFERROR(BM12-FB12,"") -> 46110 | FS12: =Y12 -> 20009485 | FT12: =AA12 -> 32014448-3
A13: =IF(DZ13="CLOSE","Trade closed",IF(DZ13="PMT Pending","FNF Settlement is Due",IF(CS13<>0,"FNF Reconcillation Onging",IF(CR13<>0," Final Pmt Recd , FNF Pending",IF(CM13<>0,"Exp Dox Presented to Bank, Pmt Pending",IF(BZ13<>0,"OBL Scan Recd, Nego Pending",IF(BM13<>0,"Sailed, OBL & Certs Pending",IF(BJ13<>0,"Stuffed, Yet to Sail",IF(BB13<>0,"SI Sent, Shipment Awaited",IF(BA13<>0,"Advance Rcvd, SI Pending",IF(Z13<>0,"SC Raised, Advance Pending",IF(X13<>0,"Deal Ticket Rcvd SC Pending", "Entry Pending")))))))))))) -> SI Sent, Shipment Awaited | B13: 49 | C13: 200 | D13: RCN | E13: =IF(AND(LEFT(TRIM(AA13&""),1)="3",BI13<>""),"CLOSE POSITION", IF(AND(LEFT(TRIM(AA13&""),1)="3",BI13=""),"SHORT POSITION", IF(AND(LEFT(TRIM(AA13&""),1)<>"3",BI13<>""),"LONG POSITION","ENTRY PENDING"))) -> SHORT POSITION | F13: =AA13 -> 32014482 | H13: =AB13 -> MADHAVARAYA PRABHU | I13: IVC | J13: INDIA | K13: =IF(BQ13<>0,BQ13,"") -> MANGALORE, INDIA | L13: =IF(BI13<>0,BI13,"") | M13: =IF(BJ13<>0,BJ13,"") | N13: =IF(BM13<>0,BM13,"") | O13: =IF(BO13<>0,BO13,"") | P13: =CE13 -> No OBL Yet | R13: =CK13 -> No CERTS Yet | S13: =CP13 | T13: CLARIFICATION ON LATEST SOB | U13: RCVD COUNTERSIGNED-267489781 267489781-1 | X13: 46073 | Y13: 20009534 | Z13: 46073 | AA13: 32014482 | AB13: MADHAVARAYA PRABHU | AC13: April - 26 | AD13: 46142 | AE13: 0.1 | AF13: 200 | AG13: =AF13*(1-AE13) -> 180 | AH13: MT | AI13: 1545 | AJ13: =AI13*AF13 -> 309000 | AK13: CIF | AL13: DP SIGHT | AM13: 0 | AN13: 1 | AO13: 0 | AP13: 180 DAYS | AQ13: Mr. George | AR13: Mr. Rao | AS13: 5 | AT13: - | AU13: - | AV13: - | AZ13: =AF13*AI13*AM13 -> 0 | BA13: 46076 | BB13: 46083 | BF13: 46083 | BK13: 40' | BP13: IVC | BQ13: MANGALORE, INDIA | BX13: =BJ13*AI13 -> 0 | CE13: =IF(J13="VIETNAM", IF(CG13<>"","OBL in Vietnam Office", IF(CF13<>"","OBL in Transit from Vietnam Office", IF(CD13<>0,"OBL In Destination - "&J13, IF(CC13<>0,"OBL in Transit to Destination - "&J13, IF(CB13<>0,"OBL in SIG Office", IF(CA13<>0,"OBL in Transit from Origin to SIG", IF(BZ13<>0,"OBL in Origin - "&I13, IF(BY13<>0,"Draft Rcvd","No OBL Yet")))))))), IF(CO13<>0,"OBL In Destination - "&J13, IF(CM13<>0,"OBL in Transit with Nego Docs - "&J13, IF(CB13<>0,"OBL in SIG Office", IF(CA13<>0,"OBL in Transit from Origin to SIG", IF(BZ13<>0,"OBL in Origin - "&I13, IF(BY13<>0,"Draft Rcvd","No OBL Yet"))))))) -> No OBL Yet | CK13: =IF(CJ13<>0,"CERTS in Destination - "&J13,IF(CI13<>0,"CERT in Transit to -"&J13,IF(CH13<>0,"CERT in Origin - "&I13,IF(CH13="","No CERTS Yet")))) -> No CERTS Yet | CP13: =IF(CO13<>0,"Docs in Buyer's Nego Bank",IF(CN13<>0,"Docs in Transit to Buyer's Nego Bank",IF(CM13<>0,"Docs in Our Nego Bank",IF(CL13="TT PAYMENT","Not Applicable","")))) | CQ13: =(AN13*AI13*BJ13)-AZ13 -> 0 | CU13: =IF(CS13="","",BJ13-CT13) | CV13: =IF(CS13="","",CU13/BJ13) | CW13: =IF(CS13="","",AZ13+CQ13) | CX13: =IF(CS13="","",BX13*2%) | CY13: =IF(CS13="","",AI13/B13) | DA13: =IF(CS13="","",B13-CZ13) | DC13: =IF(CS13="","",IF(CS13="","",DB13-C13)) | DE13: =IF(CS13="","",10%-DD13) | DF13: =IF(CS13="","",CU13*AI13) | DG13: =IF(CS13="","",IF(DA13>2,2*DA13*CT13*CY13,DA13*CT13*CY13)) | DH13: =IF(CS13="","",IF(DA13>2,2*(DA13-2*CT13*CY13),0)) | DI13: =IF(CS13="","",IF(DC13>0,DC13*0.5*CT13,0)) | DJ13: =IF(CS13="","",IF(DE13<0,DE13*CT13*AI13*1%,0)) | DK13: =IF(CS13="","",SUM(DF13:DJ13)) | DN13: =IF(CS13="","",SUM(DK13:DL13)) | DO13: =IF(CS13="","",BJ13*AI13-DN13) | DP13: =IF(CS13="","",AZ13+CQ13) | DQ13: =IF(CS13="","",IF((DP13-DO13)>0,DP13-DO13,"")) | DR13: =IF(CS13="","",IF((DO13-DP13)>0,(DO13-DP13),"")) | DS13: =IF(CS13="","",IF(DQ13="",H13,"VALENCY")) | DT13: =IF(DN13="","",IF(DN13>0,"CN", "DN")) | DY13: NO VINA/RBS REPORT | EA13: =IF(CS13="","", MIN(0,(IF(DA13>2,2,1)*DA13*CT13*CY13)) ) | EH13: VALENCY IVC | EN13: =EK13*EJ13 -> 0 | EV13: =IF(CR13<>0,"Final Pmt Recd",IF(CM13<>0,"Export Loan",IF(BZ13<>0,"Nego Pending",IF(Z13<>0,"Yet to load","Yet to load")))) -> Yet to load | EX13: =EW13/BJ13 -> #DIV/0! | EY13: Freight paid by origin | FD13: =FC13*BJ13 -> 0 | FL13: =IFERROR(EZ13-BY13,"") -> 0 | FM13: =IFERROR(BM13-FB13,"") -> 0 | FS13: =Y13 -> 20009534 | FT13: =AA13 -> 32014482
A14: =IF(DZ14="CLOSE","Trade closed",IF(DZ14="PMT Pending","FNF Settlement is Due",IF(CS14<>0,"FNF Reconcillation Onging",IF(CR14<>0," Final Pmt Recd , FNF Pending",IF(CM14<>0,"Exp Dox Presented to Bank, Pmt Pending",IF(BZ14<>0,"OBL Scan Recd, Nego Pending",IF(BM14<>0,"Sailed, OBL & Certs Pending",IF(BJ14<>0,"Stuffed, Yet to Sail",IF(BB14<>0,"SI Sent, Shipment Awaited",IF(BA14<>0,"Advance Rcvd, SI Pending",IF(Z14<>0,"SC Raised, Advance Pending",IF(X14<>0,"Deal Ticket Rcvd SC Pending", "Entry Pending")))))))))))) -> Exp Dox Presented to Bank, Pmt Pending | B14: 50 | C14: 185 | D14: RCN | E14: =IF(AND(LEFT(TRIM(AA14&""),1)="3",BI14<>""),"CLOSE POSITION", IF(AND(LEFT(TRIM(AA14&""),1)="3",BI14=""),"SHORT POSITION", IF(AND(LEFT(TRIM(AA14&""),1)<>"3",BI14<>""),"LONG POSITION","ENTRY PENDING"))) -> CLOSE POSITION | F14: =AA14 -> 32014448-5 | H14: =AB14 -> Valency Agro (Processing) | I14: NIGERIA(OGB) | J14: INDIA | K14: =IF(BQ14<>0,BQ14,"") -> MANGALORE, INDIA | L14: =IF(BI14<>0,BI14,"") -> MEDULG625659 | M14: =IF(BJ14<>0,BJ14,"") -> 104.27 | N14: =IF(BM14<>0,BM14,"") -> 46108 | O14: =IF(BO14<>0,BO14,"") -> 46157 | P14: =CE14 -> OBL In Destination - INDIA | R14: =CK14 -> CERTS in Destination - INDIA | S14: =CP14 -> Docs in Buyer's Nego Bank | T14: =IFERROR(_xlfn.XLOOKUP(F14, '[2]Data 2026'!$H$12:$H$111, '[2]Data 2026'!$CL$12:$CL$111),"") | U14: Payment by Valency Agro will be done, 90 days after BL date- CARGO CLEARED. | X14: 46066 | Y14: 20009485 | Z14: 46066 | AA14: 32014448-5 | AB14: Valency Agro (Processing) | AC14: 46082 | AD14: 46112 | AE14: 0.1 | AF14: =BJ14 -> 104.27 | AG14: =AF14*(1-AE14) -> 93.843 | AH14: MT | AI14: 1683 | AJ14: 1700000 | AK14: CIF | AL14: 90 DAYS FROM BL DATE | AM14: 0 | AN14: 1 | AO14: 0 | AP14: 180 DAYS | AQ14: Mr. Naveen | AR14: Direct | AT14: - | AU14: - | AV14: - | AZ14: =AF14*AI14*AM14 -> 0 | BA14: 46069 | BB14: 46073 | BF14: 46073 | BI14: MEDULG625659 | BJ14: 104.27 | BK14: 40' | BL14: 4 | BM14: 46108 | BN14: Vizhinjam internation 04-05 | BO14: 46157 | BP14: NIGERIA | BQ14: MANGALORE, INDIA | BR14: MSC | BS14: LASTBORN | BV14: 90084573 | BX14: =BJ14*AI14 -> 175486.41 | BZ14: 46129 | CA14: 4567280594 | CB14: 46134 | CE14: =IF(J14="VIETNAM", IF(CG14<>"","OBL in Vietnam Office", IF(CF14<>"","OBL in Transit from Vietnam Office", IF(CD14<>0,"OBL In Destination - "&J14, IF(CC14<>0,"OBL in Transit to Destination - "&J14, IF(CB14<>0,"OBL in SIG Office", IF(CA14<>0,"OBL in Transit from Origin to SIG", IF(BZ14<>0,"OBL in Origin - "&I14, IF(BY14<>0,"Draft Rcvd","No OBL Yet")))))))), IF(CO14<>0,"OBL In Destination - "&J14, IF(CM14<>0,"OBL in Transit with Nego Docs - "&J14, IF(CB14<>0,"OBL in SIG Office", IF(CA14<>0,"OBL in Transit from Origin to SIG", IF(BZ14<>0,"OBL in Origin - "&I14, IF(BY14<>0,"Draft Rcvd","No OBL Yet"))))))) -> OBL In Destination - INDIA | CH14: 46141 | CI14: 1335828874 | CJ14: 46157 | CK14: =IF(CJ14<>0,"CERTS in Destination - "&J14,IF(CI14<>0,"CERT in Transit to -"&J14,IF(CH14<>0,"CERT in Origin - "&I14,IF(CH14="","No CERTS Yet")))) -> CERTS in Destination - INDIA | CL14: ICICI BANK | CM14: 46139 | CN14: 8585994476 | CO14: 46147 | CP14: =IF(CO14<>0,"Docs in Buyer's Nego Bank",IF(CN14<>0,"Docs in Transit to Buyer's Nego Bank",IF(CM14<>0,"Docs in Our Nego Bank",IF(CL14="TT PAYMENT","Not Applicable","")))) -> Docs in Buyer's Nego Bank | CQ14: =(AN14*AI14*BJ14)-AZ14 -> 175486.41 | CU14: =IF(CS14="","",BJ14-CT14) | CV14: =IF(CS14="","",CU14/BJ14) | CW14: =IF(CS14="","",AZ14+CQ14) | CX14: =IF(CS14="","",BX14*2%) | CY14: =IF(CS14="","",AI14/B14) | DA14: =IF(CS14="","",B14-CZ14) | DC14: =IF(CS14="","",IF(CS14="","",DB14-C14)) | DE14: =IF(CS14="","",10%-DD14) | DF14: =IF(CS14="","",CU14*AI14) | DG14: =IF(CS14="","",IF(DA14>2,2*DA14*CT14*CY14,DA14*CT14*CY14)) | DH14: =IF(CS14="","",IF(DA14>2,2*(DA14-2*CT14*CY14),0)) | DI14: =IF(CS14="","",IF(DC14>0,DC14*0.5*CT14,0)) | DJ14: =IF(CS14="","",IF(DE14<0,DE14*CT14*AI14*1%,0)) | DK14: =IF(CS14="","",SUM(DF14:DJ14)) | DN14: =IF(CS14="","",SUM(DK14:DL14)) | DO14: =IF(CS14="","",BJ14*AI14-DN14) | DP14: =IF(CS14="","",AZ14+CQ14) | DQ14: =IF(CS14="","",IF((DP14-DO14)>0,DP14-DO14,"")) | DR14: =IF(CS14="","",IF((DO14-DP14)>0,(DO14-DP14),"")) | DS14: =IF(CS14="","",IF(DQ14="",H14,"VALENCY")) | DT14: =IF(DN14="","",IF(DN14>0,"CN", "DN")) | DY14: NO VINA/RBS REPORT | EA14: =IF(CS14="","", MIN(0,(IF(DA14>2,2,1)*DA14*CT14*CY14)) ) | EB14: 47.95 | EC14: 192 | ED14: 8.58 | EE14: 4900009113 | EH14: LASTBORN GENERAL MERCHANT LTD | EI14: FOB | EJ14: =BJ14 -> 104.27 | EK14: 1600 | EN14: =EK14*EJ14 -> 166832 | EO14: FOB | ER14: 163495.36 | EV14: =IF(CR14<>0,"Final Pmt Recd",IF(CM14<>0,"Export Loan",IF(BZ14<>0,"Nego Pending",IF(Z14<>0,"Yet to load","Yet to load")))) -> Export Loan | EX14: =EW14/BJ14 -> 0 | EY14: Freight paid by origin | FD14: =FC14*BJ14 -> 0 | FL14: =IFERROR(EZ14-BY14,"") -> 0 | FM14: =IFERROR(BM14-FB14,"") -> 46108 | FS14: =Y14 -> 20009485 | FT14: =AA14 -> 32014448-5
A15: =IF(DZ15="CLOSE","Trade closed",IF(DZ15="PMT Pending","FNF Settlement is Due",IF(CS15<>0,"FNF Reconcillation Onging",IF(CR15<>0," Final Pmt Recd , FNF Pending",IF(CM15<>0,"Exp Dox Presented to Bank, Pmt Pending",IF(BZ15<>0,"OBL Scan Recd, Nego Pending",IF(BM15<>0,"Sailed, OBL & Certs Pending",IF(BJ15<>0,"Stuffed, Yet to Sail",IF(BB15<>0,"SI Sent, Shipment Awaited",IF(BA15<>0,"Advance Rcvd, SI Pending",IF(Z15<>0,"SC Raised, Advance Pending",IF(X15<>0,"Deal Ticket Rcvd SC Pending", "Entry Pending")))))))))))) -> Final Pmt Recd , FNF Pending | B15: 51 | C15: 190 | D15: RCN | E15: =IF(AND(LEFT(TRIM(AA15&""),1)="3",BI15<>""),"CLOSE POSITION", IF(AND(LEFT(TRIM(AA15&""),1)="3",BI15=""),"SHORT POSITION", IF(AND(LEFT(TRIM(AA15&""),1)<>"3",BI15<>""),"LONG POSITION","ENTRY PENDING"))) -> CLOSE POSITION | F15: =AA15 -> 32013748 | H15: =AB15 -> ST. PAULS CASHEW FACTORY | I15: NIGERIA(OGB) | J15: INDIA | K15: =IF(BQ15<>0,BQ15,"") -> TUTICORIN, INDIA | L15: MEDULG628059 | M15: =IF(BJ15<>0,BJ15,"") -> 50.635 | N15: =IF(BM15<>0,BM15,"") -> 46105 | O15: =IF(BO15<>0,BO15,"") -> 46161 | P15: =CE15 -> OBL In Destination - INDIA | R15: =CK15 -> CERTS in Destination - INDIA | S15: =CP15 -> Docs in Buyer's Nego Bank | T15: =IFERROR(_xlfn.XLOOKUP(F15, '[2]Data 2026'!$H$12:$H$111, '[2]Data 2026'!$CL$12:$CL$111),"") | U15: CERT YET TO REACH DESTINATION, PAYMENT RCVD 14/5 | V15: ADDENDUM 11/02-COUNTER SIGNED RCVD | X15: 46380 | Y15: 20009014 | Z15: 46017 | AA15: 32013748 | AB15: ST. PAULS CASHEW FACTORY | AC15: BY 15TH MARCH | AD15: 46096 | AE15: 0.1 | AF15: 50 | AG15: =AF15*(1-AE15) -> 45 | AH15: MT | AI15: 1610 | AJ15: =AI15*AF15 -> 80500 | AK15: CFR | AL15: DP SIGHT | AM15: 0 | AN15: 1 | AO15: 0 | AP15: 180 DAYS | AQ15: Mr. George | AT15: - | AU15: - | AV15: - | AZ15: =AF15*AI15*AM15 -> 0 | BA15: 46382 | BB15: 46030 | BF15: 46030 | BI15: MEDULG628059 | BJ15: 50.635 | BK15: 40' | BL15: 2 | BM15: 46105 | BN15: Hambantota, LK | BO15: 46161 | BP15: Ogbomosho | BQ15: TUTICORIN, INDIA | BR15: MSC | BT15: KOWLOON / FN610R | BU15: WP609R | BV15: 90083900 | BW15: 46120 | BX15: =BJ15*AI15 -> 81522.35 | BZ15: 46129 | CA15: 46130 | CB15: 46134 | CE15: =IF(J15="VIETNAM", IF(CG15<>"","OBL in Vietnam Office", IF(CF15<>"","OBL in Transit from Vietnam Office", IF(CD15<>0,"OBL In Destination - "&J15, IF(CC15<>0,"OBL in Transit to Destination - "&J15, IF(CB15<>0,"OBL in SIG Office", IF(CA15<>0,"OBL in Transit from Origin to SIG", IF(BZ15<>0,"OBL in Origin - "&I15, IF(BY15<>0,"Draft Rcvd","No OBL Yet")))))))), IF(CO15<>0,"OBL In Destination - "&J15, IF(CM15<>0,"OBL in Transit with Nego Docs - "&J15, IF(CB15<>0,"OBL in SIG Office", IF(CA15<>0,"OBL in Transit from Origin to SIG", IF(BZ15<>0,"OBL in Origin - "&I15, IF(BY15<>0,"Draft Rcvd","No OBL Yet"))))))) -> OBL In Destination - INDIA | CH15: 46139 | CI15: 5775433856 | CJ15: 46157 | CK15: =IF(CJ15<>0,"CERTS in Destination - "&J15,IF(CI15<>0,"CERT in Transit to -"&J15,IF(CH15<>0,"CERT in Origin - "&I15,IF(CH15="","No CERTS Yet")))) -> CERTS in Destination - INDIA | CL15: HABIB BANK | CM15: 46140 | CN15: 47 0504 1283 | CO15: 46142 | CP15: =IF(CO15<>0,"Docs in Buyer's Nego Bank",IF(CN15<>0,"Docs in Transit to Buyer's Nego Bank",IF(CM15<>0,"Docs in Our Nego Bank",IF(CL15="TT PAYMENT","Not Applicable","")))) -> Docs in Buyer's Nego Bank | CQ15: =(AN15*AI15*BJ15)-AZ15 -> 81522.35 | CR15: 46156 | CU15: =IF(CS15="","",BJ15-CT15) | CV15: =IF(CS15="","",CU15/BJ15) | CW15: =IF(CS15="","",AZ15+CQ15) | CX15: =IF(CS15="","",BX15*2%) | CY15: =IF(CS15="","",AI15/B15) | DA15: =IF(CS15="","",B15-CZ15) | DC15: =IF(CS15="","",IF(CS15="","",DB15-C15)) | DE15: =IF(CS15="","",10%-DD15) | DF15: =IF(CS15="","",CU15*AI15) | DG15: =IF(CS15="","",IF(DA15>2,2*DA15*CT15*CY15,DA15*CT15*CY15)) | DH15: =IF(CS15="","",IF(DA15>2,2*(DA15-2*CT15*CY15),0)) | DI15: =IF(CS15="","",IF(DC15>0,DC15*0.5*CT15,0)) | DJ15: =IF(CS15="","",IF(DE15<0,DE15*CT15*AI15*1%,0)) | DK15: =IF(CS15="","",SUM(DF15:DJ15)) | DN15: =IF(CS15="","",SUM(DK15:DL15)) | DO15: =IF(CS15="","",BJ15*AI15-DN15) | DP15: =IF(CS15="","",AZ15+CQ15) | DQ15: =IF(CS15="","",IF((DP15-DO15)>0,DP15-DO15,"")) | DR15: =IF(CS15="","",IF((DO15-DP15)>0,(DO15-DP15),"")) | DS15: =IF(CS15="","",IF(DQ15="",H15,"VALENCY")) | DT15: =IF(DN15="","",IF(DN15>0,"CN", "DN")) | DY15: NO VINA/RBS REPORT | EA15: =IF(CS15="","", MIN(0,(IF(DA15>2,2,1)*DA15*CT15*CY15)) ) | EB15: 47.91 | EC15: 196 | ED15: 7.85 | EE15: 4900009486 | EH15: VALENCY NIGERIA | EL15: - | EN15: =EK15*EJ15 -> 0 | EV15: =IF(CR15<>0,"Final Pmt Recd",IF(CM15<>0,"Export Loan",IF(BZ15<>0,"Nego Pending",IF(Z15<>0,"Yet to load","Yet to load")))) -> Final Pmt Recd | EX15: =EW15/BJ15 -> 0 | EY15: Freight paid by origin | FD15: =FC15*BJ15 -> 0 | FL15: =IFERROR(EZ15-BY15,"") -> 0 | FM15: =IFERROR(BM15-FB15,"") -> 46105 | FS15: 20009014 | FT15: 32013748 | FU15: 0
A16: =IF(DZ16="CLOSE","Trade closed",IF(DZ16="PMT Pending","FNF Settlement is Due",IF(CS16<>0,"FNF Reconcillation Onging",IF(CR16<>0," Final Pmt Recd , FNF Pending",IF(CM16<>0,"Exp Dox Presented to Bank, Pmt Pending",IF(BZ16<>0,"OBL Scan Recd, Nego Pending",IF(BM16<>0,"Sailed, OBL & Certs Pending",IF(BJ16<>0,"Stuffed, Yet to Sail",IF(BB16<>0,"SI Sent, Shipment Awaited",IF(BA16<>0,"Advance Rcvd, SI Pending",IF(Z16<>0,"SC Raised, Advance Pending",IF(X16<>0,"Deal Ticket Rcvd SC Pending", "Entry Pending")))))))))))) -> Final Pmt Recd , FNF Pending | B16: 51 | C16: 185 | D16: RCN | E16: =IF(AND(LEFT(TRIM(AA16&""),1)="3",BI16<>""),"CLOSE POSITION", IF(AND(LEFT(TRIM(AA16&""),1)="3",BI16=""),"SHORT POSITION", IF(AND(LEFT(TRIM(AA16&""),1)<>"3",BI16<>""),"LONG POSITION","ENTRY PENDING"))) -> CLOSE POSITION | F16: =AA16 -> 32014391 | H16: =AB16 -> SRI VIJAYALAXMI CASHEW INDUSTRIES | I16: NIGERIA(OGB) | J16: INDIA | K16: =IF(BQ16<>0,BQ16,"") -> MANGALORE, INDIA | L16: =IF(BI16<>0,BI16,"") -> MEDULG626988 | M16: =IF(BJ16<>0,BJ16,"") -> 104.563 | N16: =IF(BM16<>0,BM16,"") -> 46110 | O16: =IF(BO16<>0,BO16,"") -> 46160 | P16: =CE16 -> OBL In Destination - INDIA | R16: =CK16 -> CERTS in Destination - INDIA | S16: =CP16 -> Docs in Buyer's Nego Bank | T16: =IFERROR(_xlfn.XLOOKUP(F16, '[2]Data 2026'!$H$12:$H$111, '[2]Data 2026'!$CL$12:$CL$111),"") | U16: PAYMENT RCVD 21/5 | W16: PAYMENT PENDING-EXPECTED THIS WEEK - NEED TO TALK WITH TRADER | X16: 46052 | Y16: 20009356 | Z16: 46052 | AA16: 32014391 | AB16: SRI VIJAYALAXMI CASHEW INDUSTRIES | AC16: 46082 | AD16: 46112 | AE16: 0.1 | AF16: =EJ16 -> 104.563 | AG16: =AF16*(1-AE16) -> 94.1067 | AH16: MT | AI16: 1635 | AJ16: 163500 | AK16: CIF | AL16: DP SIGHT | AM16: 0 | AN16: 1 | AO16: 0 | AP16: 180 DAYS | AQ16: Mr. George | AR16: Direct | AT16: - | AU16: - | AV16: - | AZ16: =AF16*AI16*AM16 -> 0 | BA16: 46056 | BB16: 46062 | BF16: 46062 | BI16: MEDULG626988 | BJ16: 104.563 | BK16: 40' | BL16: 4 | BM16: 46110 | BN16: Vizhinjam international 10-05,FCIU7360800 | BO16: 46160 | BP16: NIGERIA | BQ16: MANGALORE, INDIA | BR16: MSC | BT16: MSC KERRY VII | BU16: FN611R | BV16: 90084810 | BW16: 46141 | BX16: =BJ16*AI16 -> 170960.51 | BY16: 46128 | BZ16: 46128 | CA16: 9763609273 | CB16: 46134 | CE16: =IF(J16="VIETNAM", IF(CG16<>"","OBL in Vietnam Office", IF(CF16<>"","OBL in Transit from Vietnam Office", IF(CD16<>0,"OBL In Destination - "&J16, IF(CC16<>0,"OBL in Transit to Destination - "&J16, IF(CB16<>0,"OBL in SIG Office", IF(CA16<>0,"OBL in Transit from Origin to SIG", IF(BZ16<>0,"OBL in Origin - "&I16, IF(BY16<>0,"Draft Rcvd","No OBL Yet")))))))), IF(CO16<>0,"OBL In Destination - "&J16, IF(CM16<>0,"OBL in Transit with Nego Docs - "&J16, IF(CB16<>0,"OBL in SIG Office", IF(CA16<>0,"OBL in Transit from Origin to SIG", IF(BZ16<>0,"OBL in Origin - "&I16, IF(BY16<>0,"Draft Rcvd","No OBL Yet"))))))) -> OBL In Destination - INDIA | CH16: 46141 | CI16: 1335828874 | CJ16: 46157 | CK16: =IF(CJ16<>0,"CERTS in Destination - "&J16,IF(CI16<>0,"CERT in Transit to -"&J16,IF(CH16<>0,"CERT in Origin - "&I16,IF(CH16="","No CERTS Yet")))) -> CERTS in Destination - INDIA | CL16: HABIB BANK | CM16: 46141 | CN16: 9672115106 | CO16: 46149 | CP16: =IF(CO16<>0,"Docs in Buyer's Nego Bank",IF(CN16<>0,"Docs in Transit to Buyer's Nego Bank",IF(CM16<>0,"Docs in Our Nego Bank",IF(CL16="TT PAYMENT","Not Applicable","")))) -> Docs in Buyer's Nego Bank | CQ16: =(AN16*AI16*BJ16)-AZ16 -> 170960.51 | CR16: 46163 | CU16: =IF(CS16="","",BJ16-CT16) | CV16: =IF(CS16="","",CU16/BJ16) | CW16: =IF(CS16="","",AZ16+CQ16) | CX16: =IF(CS16="","",BX16*2%) | CY16: =IF(CS16="","",AI16/B16) | DA16: =IF(CS16="","",B16-CZ16) | DC16: =IF(CS16="","",IF(CS16="","",DB16-C16)) | DE16: =IF(CS16="","",10%-DD16) | DF16: =IF(CS16="","",CU16*AI16) | DG16: =IF(CS16="","",IF(DA16>2,2*DA16*CT16*CY16,DA16*CT16*CY16)) | DH16: =IF(CS16="","",IF(DA16>2,2*(DA16-2*CT16*CY16),0)) | DI16: =IF(CS16="","",IF(DC16>0,DC16*0.5*CT16,0)) | DJ16: =IF(CS16="","",IF(DE16<0,DE16*CT16*AI16*1%,0)) | DK16: =IF(CS16="","",SUM(DF16:DJ16)) | DN16: =IF(CS16="","",SUM(DK16:DL16)) | DO16: =IF(CS16="","",BJ16*AI16-DN16) | DP16: =IF(CS16="","",AZ16+CQ16) | DQ16: =IF(CS16="","",IF((DP16-DO16)>0,DP16-DO16,"")) | DR16: =IF(CS16="","",IF((DO16-DP16)>0,(DO16-DP16),"")) | DS16: =IF(CS16="","",IF(DQ16="",H16,"VALENCY")) | DT16: =IF(DN16="","",IF(DN16>0,"CN", "DN")) | DY16: NO VINA/RBS REPORT | EA16: =IF(CS16="","", MIN(0,(IF(DA16>2,2,1)*DA16*CT16*CY16)) ) | EB16: 49.81 | EC16: 178 | ED16: 8.78 | EE16: 4900008912 | EH16: WAKMAN HERITAGE | EI16: FOB | EJ16: 104.563 | EK16: 1500 | EN16: =EK16*EJ16 -> 156844.5 | EO16: FOB | ER16: 141160.05 | EV16: =IF(CR16<>0,"Final Pmt Recd",IF(CM16<>0,"Export Loan",IF(BZ16<>0,"Nego Pending",IF(Z16<>0,"Yet to load","Yet to load")))) -> Final Pmt Recd | EX16: =EW16/BJ16 -> 0 | EY16: Freight paid by origin | FA16: 22138870 | FD16: =FC16*BJ16 -> 0 | FL16: =IFERROR(EZ16-BY16,"") -> -46128 | FM16: =IFERROR(BM16-FB16,"") -> 46110 | FS16: =Y16 -> 20009356 | FT16: =AA16 -> 32014391
A17: =IF(DZ17="CLOSE","Trade closed",IF(DZ17="PMT Pending","FNF Settlement is Due",IF(CS17<>0,"FNF Reconcillation Onging",IF(CR17<>0," Final Pmt Recd , FNF Pending",IF(CM17<>0,"Exp Dox Presented to Bank, Pmt Pending",IF(BZ17<>0,"OBL Scan Recd, Nego Pending",IF(BM17<>0,"Sailed, OBL & Certs Pending",IF(BJ17<>0,"Stuffed, Yet to Sail",IF(BB17<>0,"SI Sent, Shipment Awaited",IF(BA17<>0,"Advance Rcvd, SI Pending",IF(Z17<>0,"SC Raised, Advance Pending",IF(X17<>0,"Deal Ticket Rcvd SC Pending", "Entry Pending")))))))))))) -> Final Pmt Recd , FNF Pending | B17: 51 | C17: 190 | D17: RCN | E17: =IF(AND(LEFT(TRIM(AA17&""),1)="3",BI17<>""),"CLOSE POSITION", IF(AND(LEFT(TRIM(AA17&""),1)="3",BI17=""),"SHORT POSITION", IF(AND(LEFT(TRIM(AA17&""),1)<>"3",BI17<>""),"LONG POSITION","ENTRY PENDING"))) -> CLOSE POSITION | F17: =AA17 -> 32013750-1 | H17: =AB17 -> MAA TARA TARINI CASHEW INDUSTRIES | I17: NIGERIA(OGB) | J17: INDIA | K17: =IF(BQ17<>0,BQ17,"") -> GANGAVARAM, INDIA | L17: =IF(BI17<>0,BI17,"") -> MEDULG617839 | M17: =IF(BJ17<>0,BJ17,"") -> 103.6 | N17: =IF(BM17<>0,BM17,"") -> 46099 | O17: =IF(BO17<>0,BO17,"") -> 46161 | P17: =CE17 -> OBL In Destination - INDIA | R17: =CK17 -> CERTS in Destination - INDIA | S17: =CP17 -> Docs in Buyer's Nego Bank | T17: =IFERROR(_xlfn.XLOOKUP(F17, '[2]Data 2026'!$H$12:$H$111, '[2]Data 2026'!$CL$12:$CL$111),"") | U17: ORIGINAL CERTS COURIERED TO BUYER CHA DHL: 4288510505-NEGO BANK DONE 8TH APRIL- PAYMENT PENDING | V17: ADDENDUM 11/02-COUNTER SIGNED RCVD | X17: 46014 | Y17: 20009016-1 | Z17: 46017 | AA17: 32013750-1 | AB17: MAA TARA TARINI CASHEW INDUSTRIES | AC17: BY 15TH MARCH | AD17: 46096 | AE17: 0.1 | AF17: 100 | AG17: =AF17*(1-AE17) -> 90 | AH17: MT | AI17: 1610 | AJ17: 161000 | AK17: CFR | AL17: DP SIGHT | AM17: 0.1 | AN17: 0.9 | AO17: 0 | AP17: 180 DAYS | AQ17: Mr. Chirag | AT17: - | AU17: - | AV17: - | AZ17: =AF17*AI17*AM17 -> 16100 | BA17: 46024 | BB17: 46030 | BF17: 46030 | BI17: MEDULG617839 | BJ17: 103.6 | BK17: 40' | BL17: 4 | BM17: 46099 | BN17: Colombo, LK 29-04 | BO17: 46161 | BP17: Ogbomosho | BQ17: GANGAVARAM, INDIA | BR17: MSC | BT17: MSC TASMANIA - | BU17: WP609R | BV17: 90083332 | BX17: =BJ17*AI17 -> 166796 | BZ17: 46120 | CA17: 6876239156 | CB17: 46120 | CC17: 1564805443 | CD17: 46127 | CE17: =IF(J17="VIETNAM", IF(CG17<>"","OBL in Vietnam Office", IF(CF17<>"","OBL in Transit from Vietnam Office", IF(CD17<>0,"OBL In Destination - "&J17, IF(CC17<>0,"OBL in Transit to Destination - "&J17, IF(CB17<>0,"OBL in SIG Office", IF(CA17<>0,"OBL in Transit from Origin to SIG", IF(BZ17<>0,"OBL in Origin - "&I17, IF(BY17<>0,"Draft Rcvd","No OBL Yet")))))))), IF(CO17<>0,"OBL In Destination - "&J17, IF(CM17<>0,"OBL in Transit with Nego Docs - "&J17, IF(CB17<>0,"OBL in SIG Office", IF(CA17<>0,"OBL in Transit from Origin to SIG", IF(BZ17<>0,"OBL in Origin - "&I17, IF(BY17<>0,"Draft Rcvd","No OBL Yet"))))))) -> OBL In Destination - INDIA | CH17: 46120 | CI17: 7144679555 | CJ17: 46125 | CK17: =IF(CJ17<>0,"CERTS in Destination - "&J17,IF(CI17<>0,"CERT in Transit to -"&J17,IF(CH17<>0,"CERT in Origin - "&I17,IF(CH17="","No CERTS Yet")))) -> CERTS in Destination - INDIA | CL17: HABIB BANK | CM17: 46120 | CN17: 1564805443 | CO17: 46127 | CP17: =IF(CO17<>0,"Docs in Buyer's Nego Bank",IF(CN17<>0,"Docs in Transit to Buyer's Nego Bank",IF(CM17<>0,"Docs in Our Nego Bank",IF(CL17="TT PAYMENT","Not Applicable","")))) -> Docs in Buyer's Nego Bank | CQ17: =(AN17*AI17*BJ17)-AZ17 -> 134016.4 | CR17: 46154 | CU17: =IF(CS17="","",BJ17-CT17) | CV17: =IF(CS17="","",CU17/BJ17) | CW17: =IF(CS17="","",AZ17+CQ17) | CX17: =IF(CS17="","",BX17*2%) | CY17: =IF(CS17="","",AI17/B17) | DA17: =IF(CS17="","",B17-CZ17) | DC17: =IF(CS17="","",IF(CS17="","",DB17-C17)) | DE17: =IF(CS17="","",10%-DD17) | DF17: =IF(CS17="","",CU17*AI17) | DG17: =IF(CS17="","",IF(DA17>2,2*DA17*CT17*CY17,DA17*CT17*CY17)) | DH17: =IF(CS17="","",IF(DA17>2,2*(DA17-2*CT17*CY17),0)) | DI17: =IF(CS17="","",IF(DC17>0,DC17*0.5*CT17,0)) | DJ17: =IF(CS17="","",IF(DE17<0,DE17*CT17*AI17*1%,0)) | DK17: =IF(CS17="","",SUM(DF17:DJ17)) | DN17: =IF(CS17="","",SUM(DK17:DL17)) | DO17: =IF(CS17="","",BJ17*AI17-DN17) | DP17: =IF(CS17="","",AZ17+CQ17) | DQ17: =IF(CS17="","",IF((DP17-DO17)>0,DP17-DO17,"")) | DR17: =IF(CS17="","",IF((DO17-DP17)>0,(DO17-DP17),"")) | DS17: =IF(CS17="","",IF(DQ17="",H17,"VALENCY")) | DT17: =IF(DN17="","",IF(DN17>0,"CN", "DN")) | DY17: NO VINA/RBS REPORT | EA17: =IF(CS17="","", MIN(0,(IF(DA17>2,2,1)*DA17*CT17*CY17)) ) | EE17: 4900009471 | EH17: Valency Nigeria | EL17: - | EN17: =EK17*EJ17 -> 0 | EV17: =IF(CR17<>0,"Final Pmt Recd",IF(CM17<>0,"Export Loan",IF(BZ17<>0,"Nego Pending",IF(Z17<>0,"Yet to load","Yet to load")))) -> Final Pmt Recd | EX17: =EW17/BJ17 -> 0 | EY17: Freight paid by origin | FD17: =FC17*BJ17 -> 0 | FL17: =IFERROR(EZ17-BY17,"") -> 0 | FM17: =IFERROR(BM17-FB17,"") -> 46099 | FS17: 20009016-1 | FT17: 32013750-1 | FU17: 4900009471 | FV17: 5000271818 | FW17: 0000093683 | FX17: 5105710577 | GC17: 40081770 | GD17: 90083332 | GF17: done
A18: =IF(DZ18="CLOSE","Trade closed",IF(DZ18="PMT Pending","FNF Settlement is Due",IF(CS18<>0,"FNF Reconcillation Onging",IF(CR18<>0," Final Pmt Recd , FNF Pending",IF(CM18<>0,"Exp Dox Presented to Bank, Pmt Pending",IF(BZ18<>0,"OBL Scan Recd, Nego Pending",IF(BM18<>0,"Sailed, OBL & Certs Pending",IF(BJ18<>0,"Stuffed, Yet to Sail",IF(BB18<>0,"SI Sent, Shipment Awaited",IF(BA18<>0,"Advance Rcvd, SI Pending",IF(Z18<>0,"SC Raised, Advance Pending",IF(X18<>0,"Deal Ticket Rcvd SC Pending", "Entry Pending")))))))))))) -> Final Pmt Recd , FNF Pending | B18: 51 | C18: 190 | D18: RCN | E18: =IF(AND(LEFT(TRIM(AA18&""),1)="3",BI18<>""),"CLOSE POSITION", IF(AND(LEFT(TRIM(AA18&""),1)="3",BI18=""),"SHORT POSITION", IF(AND(LEFT(TRIM(AA18&""),1)<>"3",BI18<>""),"LONG POSITION","ENTRY PENDING"))) -> CLOSE POSITION | F18: =AA18 -> 32013750-2 | H18: =AB18 -> MAA TARA TARINI CASHEW INDUSTRIES | I18: NIGERIA(OGB) | J18: INDIA | K18: =IF(BQ18<>0,BQ18,"") -> GANGAVARAM, INDIA | L18: =IF(BI18<>0,BI18,"") -> MEDULG618159 | M18: =IF(BJ18<>0,BJ18,"") -> 50.65 | N18: =IF(BM18<>0,BM18,"") -> 46098 | O18: =IF(BO18<>0,BO18,"") -> 46156 | P18: =CE18 -> OBL In Destination - INDIA | R18: =CK18 -> CERTS in Destination - INDIA | S18: =CP18 -> Docs in Buyer's Nego Bank | T18: =IFERROR(_xlfn.XLOOKUP(F18, '[2]Data 2026'!$H$12:$H$111, '[2]Data 2026'!$CL$12:$CL$111),"") | U18: OBL SENT SG OFC:6876239156(SHORTSHIPPED 2FCL)-CERTS COURIERED TO BUYER ADDRESS;7144679555-PAYMENT PENDING | V18: ADDENDUM 11/02-COUNTER SIGNED RCVD | X18: 46014 | Y18: 20009016-2 | Z18: 46017 | AA18: 32013750-2 | AB18: MAA TARA TARINI CASHEW INDUSTRIES | AC18: BY 15TH MARCH | AD18: 46096 | AE18: 0.1 | AF18: 50 | AG18: =AF18*(1-AE18) -> 45 | AH18: MT | AI18: 1610 | AJ18: 161000 | AK18: CFR | AL18: DP SIGHT | AM18: 0.1 | AN18: 0.9 | AO18: 0 | AP18: 180 DAYS | AQ18: Mr. Chirag | AT18: - | AU18: - | AV18: - | AZ18: =AF18*AI18*AM18 -> 8050 | BA18: 46024 | BB18: 46030 | BF18: 46030 | BI18: MEDULG618159 | BJ18: 50.65 | BK18: 40' | BL18: 2 | BM18: 46098 | BN18: Colombo, LK 22-04 | BO18: 46156 | BP18: Ogbomosho | BQ18: GANGAVARAM, INDIA | BR18: MSC | BT18: MSC TASMANIA - | BU18: WP609R | BV18: 90083412 | BW18: 46115 | BX18: =BJ18*AI18 -> 81546.5 | BZ18: 46120 | CA18: 6876239156 | CB18: 46120 | CC18: 1564805443 | CD18: 46127 | CE18: =IF(J18="VIETNAM", IF(CG18<>"","OBL in Vietnam Office", IF(CF18<>"","OBL in Transit from Vietnam Office", IF(CD18<>0,"OBL In Destination - "&J18, IF(CC18<>0,"OBL in Transit to Destination - "&J18, IF(CB18<>0,"OBL in SIG Office", IF(CA18<>0,"OBL in Transit from Origin to SIG", IF(BZ18<>0,"OBL in Origin - "&I18, IF(BY18<>0,"Draft Rcvd","No OBL Yet")))))))), IF(CO18<>0,"OBL In Destination - "&J18, IF(CM18<>0,"OBL in Transit with Nego Docs - "&J18, IF(CB18<>0,"OBL in SIG Office", IF(CA18<>0,"OBL in Transit from Origin to SIG", IF(BZ18<>0,"OBL in Origin - "&I18, IF(BY18<>0,"Draft Rcvd","No OBL Yet"))))))) -> OBL In Destination - INDIA | CH18: 46120 | CI18: 7144679555 | CJ18: 46125 | CK18: =IF(CJ18<>0,"CERTS in Destination - "&J18,IF(CI18<>0,"CERT in Transit to -"&J18,IF(CH18<>0,"CERT in Origin - "&I18,IF(CH18="","No CERTS Yet")))) -> CERTS in Destination - INDIA | CL18: HABIB BANK | CM18: 46120 | CN18: 1564805443 | CO18: 46127 | CP18: =IF(CO18<>0,"Docs in Buyer's Nego Bank",IF(CN18<>0,"Docs in Transit to Buyer's Nego Bank",IF(CM18<>0,"Docs in Our Nego Bank",IF(CL18="TT PAYMENT","Not Applicable","")))) -> Docs in Buyer's Nego Bank | CQ18: =(AN18*AI18*BJ18)-AZ18 -> 65341.85 | CR18: 46154 | CU18: =IF(CS18="","",BJ18-CT18) | CV18: =IF(CS18="","",CU18/BJ18) | CW18: =IF(CS18="","",AZ18+CQ18) | CX18: =IF(CS18="","",BX18*2%) | CY18: =IF(CS18="","",AI18/B18) | DA18: =IF(CS18="","",B18-CZ18) | DC18: =IF(CS18="","",IF(CS18="","",DB18-C18)) | DE18: =IF(CS18="","",10%-DD18) | DF18: =IF(CS18="","",CU18*AI18) | DG18: =IF(CS18="","",IF(DA18>2,2*DA18*CT18*CY18,DA18*CT18*CY18)) | DH18: =IF(CS18="","",IF(DA18>2,2*(DA18-2*CT18*CY18),0)) | DI18: =IF(CS18="","",IF(DC18>0,DC18*0.5*CT18,0)) | DJ18: =IF(CS18="","",IF(DE18<0,DE18*CT18*AI18*1%,0)) | DK18: =IF(CS18="","",SUM(DF18:DJ18)) | DN18: =IF(CS18="","",SUM(DK18:DL18)) | DO18: =IF(CS18="","",BJ18*AI18-DN18) | DP18: =IF(CS18="","",AZ18+CQ18) | DQ18: =IF(CS18="","",IF((DP18-DO18)>0,DP18-DO18,"")) | DR18: =IF(CS18="","",IF((DO18-DP18)>0,(DO18-DP18),"")) | DS18: =IF(CS18="","",IF(DQ18="",H18,"VALENCY")) | DT18: =IF(DN18="","",IF(DN18>0,"CN", "DN")) | DY18: NO VINA/RBS REPORT | EA18: =IF(CS18="","", MIN(0,(IF(DA18>2,2,1)*DA18*CT18*CY18)) ) | EH18: Valency Nigeria | EL18: - | EN18: =EK18*EJ18 -> 0 | EV18: =IF(CR18<>0,"Final Pmt Recd",IF(CM18<>0,"Export Loan",IF(BZ18<>0,"Nego Pending",IF(Z18<>0,"Yet to load","Yet to load")))) -> Final Pmt Recd | EX18: =EW18/BJ18 -> 0 | EY18: Freight paid by origin | FD18: =FC18*BJ18 -> 0 | FL18: =IFERROR(EZ18-BY18,"") -> 0 | FM18: =IFERROR(BM18-FB18,"") -> 46098 | FS18: 20009016-2 | FT18: 32013750-2 | FU18: 0 | GD18: 90083412 | GF18: done
A19: =IF(DZ19="CLOSE","Trade closed",IF(DZ19="PMT Pending","FNF Settlement is Due",IF(CS19<>0,"FNF Reconcillation Onging",IF(CR19<>0," Final Pmt Recd , FNF Pending",IF(CM19<>0,"Exp Dox Presented to Bank, Pmt Pending",IF(BZ19<>0,"OBL Scan Recd, Nego Pending",IF(BM19<>0,"Sailed, OBL & Certs Pending",IF(BJ19<>0,"Stuffed, Yet to Sail",IF(BB19<>0,"SI Sent, Shipment Awaited",IF(BA19<>0,"Advance Rcvd, SI Pending",IF(Z19<>0,"SC Raised, Advance Pending",IF(X19<>0,"Deal Ticket Rcvd SC Pending", "Entry Pending")))))))))))) -> Exp Dox Presented to Bank, Pmt Pending | B19: 50 | C19: 190 | D19: RCN | E19: =IF(AND(LEFT(TRIM(AA19&""),1)="3",BI19<>""),"CLOSE POSITION", IF(AND(LEFT(TRIM(AA19&""),1)="3",BI19=""),"SHORT POSITION", IF(AND(LEFT(TRIM(AA19&""),1)<>"3",BI19<>""),"LONG POSITION","ENTRY PENDING"))) -> CLOSE POSITION | F19: =AA19 -> 32014578 | H19: =AB19 -> VALENCY AGRO //HSS//SABAH ENTERPRISES | I19: NIGERIA(OGB) | J19: INDIA | K19: =IF(BQ19<>0,BQ19,"") -> TUTICORIN, INDIA | L19: =IF(BI19<>0,BI19,"") -> ONEYLOSG01235800 | M19: =IF(BJ19<>0,BJ19,"") -> 101.915 | N19: =IF(BM19<>0,BM19,"") -> 46108 | O19: =IF(BO19<>0,BO19,"") -> 46157 | P19: =CE19 -> OBL In Destination - INDIA | R19: =CK19 -> CERTS in Destination - INDIA | S19: =CP19 -> Docs in Buyer's Nego Bank | T19: =IFERROR(_xlfn.XLOOKUP(F19, '[2]Data 2026'!$H$12:$H$111, '[2]Data 2026'!$CL$12:$CL$111),"") | U19: Payment by Valency Agro will be done, 90 days after BL date- HSS Formalities are done | W19: CARGO YET TO CLEAR-HSS PAYMENT PENDING | X19: 46077 | Y19: 20009587 | Z19: 46077 | AA19: 32014578 | AB19: VALENCY AGRO //HSS//SABAH ENTERPRISES | AC19: 46082 | AD19: 46112 | AE19: 0.1 | AF19: 100 | AG19: =AF19*(1-AE19) -> 90 | AH19: MT | AI19: 1610 | AJ19: 161000 | AK19: CIF | AL19: 90 DAYS FROM BL DATE | AM19: 0 | AN19: 1 | AO19: 0 | AP19: 180 DAYS | AQ19: Mr. George | AR19: Direct | AT19: - | AU19: - | AV19: - | AZ19: =AF19*AI19*AM19 -> 0 | BA19: 46077 | BB19: 46078 | BF19: 46078 | BI19: ONEYLOSG01235800 | BJ19: 101.915 | BK19: 40' | BL19: 4 | BM19: 46108 | BO19: 46157 | BP19: NIGERIA | BQ19: TUTICORIN, INDIA | BR19: ONE LINE | BV19: 90083899 | BW19: 46120 | BX19: =BJ19*AI19 -> 164083.15 | BZ19: 46127 | CA19: 9617295796 | CB19: 46132 | CE19: =IF(J19="VIETNAM", IF(CG19<>"","OBL in Vietnam Office", IF(CF19<>"","OBL in Transit from Vietnam Office", IF(CD19<>0,"OBL In Destination - "&J19, IF(CC19<>0,"OBL in Transit to Destination - "&J19, IF(CB19<>0,"OBL in SIG Office", IF(CA19<>0,"OBL in Transit from Origin to SIG", IF(BZ19<>0,"OBL in Origin - "&I19, IF(BY19<>0,"Draft Rcvd","No OBL Yet")))))))), IF(CO19<>0,"OBL In Destination - "&J19, IF(CM19<>0,"OBL in Transit with Nego Docs - "&J19, IF(CB19<>0,"OBL in SIG Office", IF(CA19<>0,"OBL in Transit from Origin to SIG", IF(BZ19<>0,"OBL in Origin - "&I19, IF(BY19<>0,"Draft Rcvd","No OBL Yet"))))))) -> OBL In Destination - INDIA | CH19: 46133 | CI19: 2185630370 | CJ19: 46151 | CK19: =IF(CJ19<>0,"CERTS in Destination - "&J19,IF(CI19<>0,"CERT in Transit to -"&J19,IF(CH19<>0,"CERT in Origin - "&I19,IF(CH19="","No CERTS Yet")))) -> CERTS in Destination - INDIA | CL19: ICICI BANK | CM19: 46134 | CN19: 3686961994 | CO19: 46141 | CP19: =IF(CO19<>0,"Docs in Buyer's Nego Bank",IF(CN19<>0,"Docs in Transit to Buyer's Nego Bank",IF(CM19<>0,"Docs in Our Nego Bank",IF(CL19="TT PAYMENT","Not Applicable","")))) -> Docs in Buyer's Nego Bank | CQ19: =(AN19*AI19*BJ19)-AZ19 -> 164083.15 | CU19: =IF(CS19="","",BJ19-CT19) | CV19: =IF(CS19="","",CU19/BJ19) | CW19: =IF(CS19="","",AZ19+CQ19) | CX19: =IF(CS19="","",BX19*2%) | CY19: =IF(CS19="","",AI19/B19) | DA19: =IF(CS19="","",B19-CZ19) | DC19: =IF(CS19="","",IF(CS19="","",DB19-C19)) | DE19: =IF(CS19="","",10%-DD19) | DF19: =IF(CS19="","",CU19*AI19) | DG19: =IF(CS19="","",IF(DA19>2,2*DA19*CT19*CY19,DA19*CT19*CY19)) | DH19: =IF(CS19="","",IF(DA19>2,2*(DA19-2*CT19*CY19),0)) | DI19: =IF(CS19="","",IF(DC19>0,DC19*0.5*CT19,0)) | DJ19: =IF(CS19="","",IF(DE19<0,DE19*CT19*AI19*1%,0)) | DK19: =IF(CS19="","",SUM(DF19:DJ19)) | DN19: =IF(CS19="","",SUM(DK19:DL19)) | DO19: =IF(CS19="","",BJ19*AI19-DN19) | DP19: =IF(CS19="","",AZ19+CQ19) | DQ19: =IF(CS19="","",IF((DP19-DO19)>0,DP19-DO19,"")) | DR19: =IF(CS19="","",IF((DO19-DP19)>0,(DO19-DP19),"")) | DS19: =IF(CS19="","",IF(DQ19="",H19,"VALENCY")) | DT19: =IF(DN19="","",IF(DN19>0,"CN", "DN")) | DY19: NO VINA/RBS REPORT | EA19: =IF(CS19="","", MIN(0,(IF(DA19>2,2,1)*DA19*CT19*CY19)) ) | EB19: 49.275 | EC19: 181 | ED19: 8.6 | EE19: 4900009485 | EH19: VALENCY NIGERIA | EN19: =EK19*EJ19 -> 0 | EV19: =IF(CR19<>0,"Final Pmt Recd",IF(CM19<>0,"Export Loan",IF(BZ19<>0,"Nego Pending",IF(Z19<>0,"Yet to load","Yet to load")))) -> Export Loan | EX19: =EW19/BJ19 -> 0 | EY19: Freight paid by origin | FA19: 22138889 | FD19: =FC19*BJ19 -> 0 | FL19: =IFERROR(EZ19-BY19,"") -> 0 | FM19: =IFERROR(BM19-FB19,"") -> 46108 | FS19: =Y19 -> 20009587 | FT19: =AA19 -> 32014578 | GD19: 90083899
A20: =IF(DZ20="CLOSE","Trade closed",IF(DZ20="PMT Pending","FNF Settlement is Due",IF(CS20<>0,"FNF Reconcillation Onging",IF(CR20<>0," Final Pmt Recd , FNF Pending",IF(CM20<>0,"Exp Dox Presented to Bank, Pmt Pending",IF(BZ20<>0,"OBL Scan Recd, Nego Pending",IF(BM20<>0,"Sailed, OBL & Certs Pending",IF(BJ20<>0,"Stuffed, Yet to Sail",IF(BB20<>0,"SI Sent, Shipment Awaited",IF(BA20<>0,"Advance Rcvd, SI Pending",IF(Z20<>0,"SC Raised, Advance Pending",IF(X20<>0,"Deal Ticket Rcvd SC Pending", "Entry Pending")))))))))))) -> Sailed, OBL & Certs Pending | B20: 48 | C20: 200 | D20: RCN | E20: =IF(AND(LEFT(TRIM(AA20&""),1)="3",BI20<>""),"CLOSE POSITION", IF(AND(LEFT(TRIM(AA20&""),1)="3",BI20=""),"SHORT POSITION", IF(AND(LEFT(TRIM(AA20&""),1)<>"3",BI20<>""),"LONG POSITION","ENTRY PENDING"))) -> CLOSE POSITION | F20: =AA20 -> 32015058 | H20: =AB20 -> THAO NGUYEN COMPANY LIMITED | I20: IVC | J20: VIETNAM | K20: =IF(BQ20<>0,BQ20,"") -> CAT LAI HCMC, Vietnam | L20: =IF(BI20<>0,BI20,"") -> ONEYABJG00281500 | M20: =IF(BJ20<>0,BJ20,"") -> 250 | N20: =IF(BM20<>0,BM20,"") -> 46159 | O20: =IF(BO20<>0,BO20,"") -> 46178 | P20: =CE20 -> No OBL Yet | Q20: TPSCR26010450 | R20: =CK20 -> No CERTS Yet | S20: =CP20 | T20: PENDING OBL-SAILED 17/5 | U20: DRAFT HBL CONFIRMED 20/5- OBL PENDING | W20: NTT - OBL PRINTING ISSUE IN SIG, ETA ERROR | X20: 46086 | Y20: 20009669 | Z20: 46086 | AA20: 32015058 | AB20: THAO NGUYEN COMPANY LIMITED | AC20: April/May - 26 | AD20: 46173 | AE20: 0.1 | AF20: 250 | AG20: =AF20*(1-AE20) -> 225 | AH20: MT | AI20: 1520 | AJ20: =AI20*AF20 -> 380000 | AK20: CFR | AL20: DP SIGHT | AM20: 0.1 | AN20: 0.88 | AO20: 0.02 | AP20: 180 DAYS | AQ20: Mr. Prashant | AR20: THUAN THIEN AGENCY | AS20: 5 | AT20: - | AU20: - | AV20: - | AY20: 46097 | AZ20: =AF20*AI20*AM20 -> 38000 | BA20: 46097 | BI20: ONEYABJG00281500 | BJ20: 250 | BK20: 40' | BL20: 10 | BM20: 46159 | BO20: 46178 | BP20: IVC | BQ20: CAT LAI HCMC, Vietnam | BR20: ONE LINE | BX20: =BJ20*AI20 -> 380000 | CE20: =IF(J20="VIETNAM", IF(CG20<>"","OBL in Vietnam Office", IF(CF20<>"","OBL in Transit from Vietnam Office", IF(CD20<>0,"OBL In Destination - "&J20, IF(CC20<>0,"OBL in Transit to Destination - "&J20, IF(CB20<>0,"OBL in SIG Office", IF(CA20<>0,"OBL in Transit from Origin to SIG", IF(BZ20<>0,"OBL in Origin - "&I20, IF(BY20<>0,"Draft Rcvd","No OBL Yet")))))))), IF(CO20<>0,"OBL In Destination - "&J20, IF(CM20<>0,"OBL in Transit with Nego Docs - "&J20, IF(CB20<>0,"OBL in SIG Office", IF(CA20<>0,"OBL in Transit from Origin to SIG", IF(BZ20<>0,"OBL in Origin - "&I20, IF(BY20<>0,"Draft Rcvd","No OBL Yet"))))))) -> No OBL Yet | CK20: =IF(CJ20<>0,"CERTS in Destination - "&J20,IF(CI20<>0,"CERT in Transit to -"&J20,IF(CH20<>0,"CERT in Origin - "&I20,IF(CH20="","No CERTS Yet")))) -> No CERTS Yet | CP20: =IF(CO20<>0,"Docs in Buyer's Nego Bank",IF(CN20<>0,"Docs in Transit to Buyer's Nego Bank",IF(CM20<>0,"Docs in Our Nego Bank",IF(CL20="TT PAYMENT","Not Applicable","")))) | CQ20: =(AN20*AI20*BJ20)-AZ20 -> 296400 | CU20: =IF(CS20="","",BJ20-CT20) | CV20: =IF(CS20="","",CU20/BJ20) | CW20: =IF(CS20="","",AZ20+CQ20) | CX20: =IF(CS20="","",BX20*2%) | CY20: =IF(CS20="","",AI20/B20) | DA20: =IF(CS20="","",B20-CZ20) | DC20: =IF(CS20="","",IF(CS20="","",DB20-C20)) | DE20: =IF(CS20="","",10%-DD20) | DF20: =IF(CS20="","",CU20*AI20) | DG20: =IF(CS20="","",IF(DA20>2,2*DA20*CT20*CY20,DA20*CT20*CY20)) | DH20: =IF(CS20="","",IF(DA20>2,2*(DA20-2*CT20*CY20),0)) | DI20: =IF(CS20="","",IF(DC20>0,DC20*0.5*CT20,0)) | DJ20: =IF(CS20="","",IF(DE20<0,DE20*CT20*AI20*1%,0)) | DK20: =IF(CS20="","",SUM(DF20:DJ20)) | DN20: =IF(CS20="","",SUM(DK20:DL20)) | DO20: =IF(CS20="","",BJ20*AI20-DN20) | DP20: =IF(CS20="","",AZ20+CQ20) | DQ20: =IF(CS20="","",IF((DP20-DO20)>0,DP20-DO20,"")) | DR20: =IF(CS20="","",IF((DO20-DP20)>0,(DO20-DP20),"")) | DS20: =IF(CS20="","",IF(DQ20="",H20,"VALENCY")) | DT20: =IF(DN20="","",IF(DN20>0,"CN", "DN")) | DY20: NO VINA/RBS REPORT | EA20: =IF(CS20="","", MIN(0,(IF(DA20>2,2,1)*DA20*CT20*CY20)) ) | EH20: VALENCY IVC | EN20: =EK20*EJ20 -> 0 | EV20: =IF(CR20<>0,"Final Pmt Recd",IF(CM20<>0,"Export Loan",IF(BZ20<>0,"Nego Pending",IF(Z20<>0,"Yet to load","Yet to load")))) -> Yet to load | EX20: =EW20/BJ20 -> 0 | EY20: Freight paid by origin | FD20: =FC20*BJ20 -> 0 | FL20: =IFERROR(EZ20-BY20,"") -> 0 | FM20: =IFERROR(BM20-FB20,"") -> 46159 | FS20: =Y20 -> 20009669 | FT20: =AA20 -> 32015058
A21: =IF(DZ21="CLOSE","Trade closed",IF(DZ21="PMT Pending","FNF Settlement is Due",IF(CS21<>0,"FNF Reconcillation Onging",IF(CR21<>0," Final Pmt Recd , FNF Pending",IF(CM21<>0,"Exp Dox Presented to Bank, Pmt Pending",IF(BZ21<>0,"OBL Scan Recd, Nego Pending",IF(BM21<>0,"Sailed, OBL & Certs Pending",IF(BJ21<>0,"Stuffed, Yet to Sail",IF(BB21<>0,"SI Sent, Shipment Awaited",IF(BA21<>0,"Advance Rcvd, SI Pending",IF(Z21<>0,"SC Raised, Advance Pending",IF(X21<>0,"Deal Ticket Rcvd SC Pending", "Entry Pending")))))))))))) -> Stuffed, Yet to Sail | B21: 48 | C21: 200 | D21: RCN | E21: =IF(AND(LEFT(TRIM(AA21&""),1)="3",BI21<>""),"CLOSE POSITION", IF(AND(LEFT(TRIM(AA21&""),1)="3",BI21=""),"SHORT POSITION", IF(AND(LEFT(TRIM(AA21&""),1)<>"3",BI21<>""),"LONG POSITION","ENTRY PENDING"))) -> CLOSE POSITION | F21: =AA21 -> 32014495 | H21: =AB21 -> MAHALASA EXPORTS | I21: IVC | J21: INDIA | K21: =IF(BQ21<>0,BQ21,"") -> MANGALORE, INDIA | L21: =IF(BI21<>0,BI21,"") -> 267489886 | M21: =IF(BJ21<>0,BJ21,"") -> 95.4 | N21: =IF(BM21<>0,BM21,"") | O21: =IF(BO21<>0,BO21,"") -> 46202 | P21: =CE21 -> No OBL Yet | R21: =CK21 -> No CERTS Yet | S21: =CP21 | T21: CLARIFICATION ON LATEST SOB | U21: RCVD COUNTERSIGNED-267489886 | X21: 46076 | Y21: 20009553 | Z21: 46074 | AA21: 32014495 | AB21: MAHALASA EXPORTS | AC21: April - 26 | AD21: 46142 | AE21: 0.1 | AF21: 100 | AG21: =AF21*(1-AE21) -> 90 | AH21: MT | AI21: 1510 | AJ21: =AI21*AF21 -> 151000 | AK21: CIF | AL21: DP SIGHT | AM21: 0 | AN21: 1 | AO21: 0 | AP21: 180 DAYS | AQ21: Mr. George | AR21: Mr. Rao | AS21: 5 | AT21: - | AU21: - | AV21: - | AZ21: =AF21*AI21*AM21 -> 0 | BB21: 46083 | BF21: 46083 | BI21: 267489886 | BJ21: 95.4 | BK21: 40' | BL21: 4 | BO21: 46202 | BP21: IVC | BQ21: MANGALORE, INDIA | BX21: =BJ21*AI21 -> 144054 | CE21: =IF(J21="VIETNAM", IF(CG21<>"","OBL in Vietnam Office", IF(CF21<>"","OBL in Transit from Vietnam Office", IF(CD21<>0,"OBL In Destination - "&J21, IF(CC21<>0,"OBL in Transit to Destination - "&J21, IF(CB21<>0,"OBL in SIG Office", IF(CA21<>0,"OBL in Transit from Origin to SIG", IF(BZ21<>0,"OBL in Origin - "&I21, IF(BY21<>0,"Draft Rcvd","No OBL Yet")))))))), IF(CO21<>0,"OBL In Destination - "&J21, IF(CM21<>0,"OBL in Transit with Nego Docs - "&J21, IF(CB21<>0,"OBL in SIG Office", IF(CA21<>0,"OBL in Transit from Origin to SIG", IF(BZ21<>0,"OBL in Origin - "&I21, IF(BY21<>0,"Draft Rcvd","No OBL Yet"))))))) -> No OBL Yet | CK21: =IF(CJ21<>0,"CERTS in Destination - "&J21,IF(CI21<>0,"CERT in Transit to -"&J21,IF(CH21<>0,"CERT in Origin - "&I21,IF(CH21="","No CERTS Yet")))) -> No CERTS Yet | CP21: =IF(CO21<>0,"Docs in Buyer's Nego Bank",IF(CN21<>0,"Docs in Transit to Buyer's Nego Bank",IF(CM21<>0,"Docs in Our Nego Bank",IF(CL21="TT PAYMENT","Not Applicable","")))) | CQ21: =(AN21*AI21*BJ21)-AZ21 -> 144054 | CU21: =IF(CS21="","",BJ21-CT21) | CV21: =IF(CS21="","",CU21/BJ21) | CW21: =IF(CS21="","",AZ21+CQ21) | CX21: =IF(CS21="","",BX21*2%) | CY21: =IF(CS21="","",AI21/B21) | DA21: =IF(CS21="","",B21-CZ21) | DC21: =IF(CS21="","",IF(CS21="","",DB21-C21)) | DE21: =IF(CS21="","",10%-DD21) | DF21: =IF(CS21="","",CU21*AI21) | DG21: =IF(CS21="","",IF(DA21>2,2*DA21*CT21*CY21,DA21*CT21*CY21)) | DH21: =IF(CS21="","",IF(DA21>2,2*(DA21-2*CT21*CY21),0)) | DI21: =IF(CS21="","",IF(DC21>0,DC21*0.5*CT21,0)) | DJ21: =IF(CS21="","",IF(DE21<0,DE21*CT21*AI21*1%,0)) | DK21: =IF(CS21="","",SUM(DF21:DJ21)) | DN21: =IF(CS21="","",SUM(DK21:DL21)) | DO21: =IF(CS21="","",BJ21*AI21-DN21) | DP21: =IF(CS21="","",AZ21+CQ21) | DQ21: =IF(CS21="","",IF((DP21-DO21)>0,DP21-DO21,"")) | DR21: =IF(CS21="","",IF((DO21-DP21)>0,(DO21-DP21),"")) | DS21: =IF(CS21="","",IF(DQ21="",H21,"VALENCY")) | DT21: =IF(DN21="","",IF(DN21>0,"CN", "DN")) | DY21: NO VINA/RBS REPORT | EA21: =IF(CS21="","", MIN(0,(IF(DA21>2,2,1)*DA21*CT21*CY21)) ) | EH21: VALENCY IVC | EN21: =EK21*EJ21 -> 0 | EV21: =IF(CR21<>0,"Final Pmt Recd",IF(CM21<>0,"Export Loan",IF(BZ21<>0,"Nego Pending",IF(Z21<>0,"Yet to load","Yet to load")))) -> Yet to load | EX21: =EW21/BJ21 -> 0 | EY21: Freight paid by origin | FD21: =FC21*BJ21 -> 0 | FL21: =IFERROR(EZ21-BY21,"") -> 0 | FM21: =IFERROR(BM21-FB21,"") -> 0 | FS21: =Y21 -> 20009553 | FT21: =AA21 -> 32014495
A22: =IF(DZ22="CLOSE","Trade closed",IF(DZ22="PMT Pending","FNF Settlement is Due",IF(CS22<>0,"FNF Reconcillation Onging",IF(CR22<>0," Final Pmt Recd , FNF Pending",IF(CM22<>0,"Exp Dox Presented to Bank, Pmt Pending",IF(BZ22<>0,"OBL Scan Recd, Nego Pending",IF(BM22<>0,"Sailed, OBL & Certs Pending",IF(BJ22<>0,"Stuffed, Yet to Sail",IF(BB22<>0,"SI Sent, Shipment Awaited",IF(BA22<>0,"Advance Rcvd, SI Pending",IF(Z22<>0,"SC Raised, Advance Pending",IF(X22<>0,"Deal Ticket Rcvd SC Pending", "Entry Pending")))))))))))) -> Exp Dox Presented to Bank, Pmt Pending | B22: 50 | C22: 185 | D22: RCN | E22: =IF(AND(LEFT(TRIM(AA22&""),1)="3",BI22<>""),"CLOSE POSITION", IF(AND(LEFT(TRIM(AA22&""),1)="3",BI22=""),"SHORT POSITION", IF(AND(LEFT(TRIM(AA22&""),1)<>"3",BI22<>""),"LONG POSITION","ENTRY PENDING"))) -> CLOSE POSITION | F22: =AA22 -> 32014448-6 | H22: =AB22 -> Valency Agro (Processing) | I22: NIGERIA(OGB) | J22: INDIA | K22: =IF(BQ22<>0,BQ22,"") -> MANGALORE INDIA | L22: =IF(BI22<>0,BI22,"") -> MEDULG622805 | M22: =IF(BJ22<>0,BJ22,"") -> 102.96 | N22: =IF(BM22<>0,BM22,"") -> 46110 | O22: =IF(BO22<>0,BO22,"") -> 46158 | P22: =CE22 -> OBL In Destination - INDIA | R22: =CK22 -> CERTS in Destination - INDIA | S22: =CP22 -> Docs in Buyer's Nego Bank | T22: =IFERROR(_xlfn.XLOOKUP(F22, '[2]Data 2026'!$H$12:$H$111, '[2]Data 2026'!$CL$12:$CL$111),"") | U22: Payment by Valency Agro will be done, 90 days after BL date- CARGO CLEARED. | X22: 46066 | Y22: 20009485 | Z22: 46066 | AA22: 32014448-6 | AB22: Valency Agro (Processing) | AC22: 46082 | AD22: 46112 | AE22: 0.1 | AF22: =BJ22 -> 102.96 | AG22: =AF22*(1-AE22) -> 92.664 | AH22: MT | AI22: 1683 | AJ22: 1700000 | AK22: CIF | AL22: 90 DAYS FROM BL DATE | AM22: 0 | AN22: 1 | AO22: 0 | AP22: 180 DAYS | AQ22: Mr. Naveen | AR22: Direct | AT22: - | AU22: - | AV22: - | AZ22: =AF22*AI22*AM22 -> 0 | BA22: 46069 | BB22: 46073 | BF22: 46073 | BI22: MEDULG622805 | BJ22: 102.96 | BK22: 40' | BL22: 4 | BM22: 46110 | BN22: Vizhinjam internation 06-05 | BO22: 46158 | BP22: NIGERIA | BQ22: MANGALORE INDIA | BR22: MSC | BS22: LASTBORN | BV22: 90084572 | BX22: =BJ22*AI22 -> 173281.68 | BZ22: 46129 | CA22: 4567280594 | CB22: 46134 | CE22: =IF(J22="VIETNAM", IF(CG22<>"","OBL in Vietnam Office", IF(CF22<>"","OBL in Transit from Vietnam Office", IF(CD22<>0,"OBL In Destination - "&J22, IF(CC22<>0,"OBL in Transit to Destination - "&J22, IF(CB22<>0,"OBL in SIG Office", IF(CA22<>0,"OBL in Transit from Origin to SIG", IF(BZ22<>0,"OBL in Origin - "&I22, IF(BY22<>0,"Draft Rcvd","No OBL Yet")))))))), IF(CO22<>0,"OBL In Destination - "&J22, IF(CM22<>0,"OBL in Transit with Nego Docs - "&J22, IF(CB22<>0,"OBL in SIG Office", IF(CA22<>0,"OBL in Transit from Origin to SIG", IF(BZ22<>0,"OBL in Origin - "&I22, IF(BY22<>0,"Draft Rcvd","No OBL Yet"))))))) -> OBL In Destination - INDIA | CH22: 46141 | CI22: 1335828874 | CJ22: 46157 | CK22: =IF(CJ22<>0,"CERTS in Destination - "&J22,IF(CI22<>0,"CERT in Transit to -"&J22,IF(CH22<>0,"CERT in Origin - "&I22,IF(CH22="","No CERTS Yet")))) -> CERTS in Destination - INDIA | CL22: ICICI BANK | CM22: 46139 | CN22: 8585994476 | CO22: 46147 | CP22: =IF(CO22<>0,"Docs in Buyer's Nego Bank",IF(CN22<>0,"Docs in Transit to Buyer's Nego Bank",IF(CM22<>0,"Docs in Our Nego Bank",IF(CL22="TT PAYMENT","Not Applicable","")))) -> Docs in Buyer's Nego Bank | CQ22: =(AN22*AI22*BJ22)-AZ22 -> 173281.68 | CU22: =IF(CS22="","",BJ22-CT22) | CV22: =IF(CS22="","",CU22/BJ22) | CW22: =IF(CS22="","",AZ22+CQ22) | CX22: =IF(CS22="","",BX22*2%) | CY22: =IF(CS22="","",AI22/B22) | DA22: =IF(CS22="","",B22-CZ22) | DC22: =IF(CS22="","",IF(CS22="","",DB22-C22)) | DE22: =IF(CS22="","",10%-DD22) | DF22: =IF(CS22="","",CU22*AI22) | DG22: =IF(CS22="","",IF(DA22>2,2*DA22*CT22*CY22,DA22*CT22*CY22)) | DH22: =IF(CS22="","",IF(DA22>2,2*(DA22-2*CT22*CY22),0)) | DI22: =IF(CS22="","",IF(DC22>0,DC22*0.5*CT22,0)) | DJ22: =IF(CS22="","",IF(DE22<0,DE22*CT22*AI22*1%,0)) | DK22: =IF(CS22="","",SUM(DF22:DJ22)) | DN22: =IF(CS22="","",SUM(DK22:DL22)) | DO22: =IF(CS22="","",BJ22*AI22-DN22) | DP22: =IF(CS22="","",AZ22+CQ22) | DQ22: =IF(CS22="","",IF((DP22-DO22)>0,DP22-DO22,"")) | DR22: =IF(CS22="","",IF((DO22-DP22)>0,(DO22-DP22),"")) | DS22: =IF(CS22="","",IF(DQ22="",H22,"VALENCY")) | DT22: =IF(DN22="","",IF(DN22>0,"CN", "DN")) | DY22: NO VINA/RBS REPORT | EA22: =IF(CS22="","", MIN(0,(IF(DA22>2,2,1)*DA22*CT22*CY22)) ) | EB22: 48.16 | EC22: 182 | ED22: 7.95 | EE22: 4900009113 | EH22: LASTBORN GENERAL MERCHANT LTD | EI22: FOB | EJ22: =BJ22 -> 102.96 | EK22: 1600 | EN22: =EK22*EJ22 -> 164736 | EO22: FOB | ER22: 161441.28 | EV22: =IF(CR22<>0,"Final Pmt Recd",IF(CM22<>0,"Export Loan",IF(BZ22<>0,"Nego Pending",IF(Z22<>0,"Yet to load","Yet to load")))) -> Export Loan | EX22: =EW22/BJ22 -> 0 | EY22: Freight paid by origin | FD22: =FC22*BJ22 -> 0 | FL22: =IFERROR(EZ22-BY22,"") -> 0 | FM22: =IFERROR(BM22-FB22,"") -> 46110 | FS22: =Y22 -> 20009485 | FT22: =AA22 -> 32014448-6
A23: =IF(DZ23="CLOSE","Trade closed",IF(DZ23="PMT Pending","FNF Settlement is Due",IF(CS23<>0,"FNF Reconcillation Onging",IF(CR23<>0," Final Pmt Recd , FNF Pending",IF(CM23<>0,"Exp Dox Presented to Bank, Pmt Pending",IF(BZ23<>0,"OBL Scan Recd, Nego Pending",IF(BM23<>0,"Sailed, OBL & Certs Pending",IF(BJ23<>0,"Stuffed, Yet to Sail",IF(BB23<>0,"SI Sent, Shipment Awaited",IF(BA23<>0,"Advance Rcvd, SI Pending",IF(Z23<>0,"SC Raised, Advance Pending",IF(X23<>0,"Deal Ticket Rcvd SC Pending", "Entry Pending")))))))))))) -> SI Sent, Shipment Awaited | B23: 48 | C23: 200 | D23: RCN | E23: =IF(AND(LEFT(TRIM(AA23&""),1)="3",BI23<>""),"CLOSE POSITION", IF(AND(LEFT(TRIM(AA23&""),1)="3",BI23=""),"SHORT POSITION", IF(AND(LEFT(TRIM(AA23&""),1)<>"3",BI23<>""),"LONG POSITION","ENTRY PENDING"))) -> CLOSE POSITION | F23: =AA23 -> 32014496 | H23: =AB23 -> MALNAD CASHEWS | I23: IVC | J23: INDIA | K23: =IF(BQ23<>0,BQ23,"") -> MANGALORE, INDIA | L23: =IF(BI23<>0,BI23,"") -> 267490071 | M23: =IF(BJ23<>0,BJ23,"") | N23: =IF(BM23<>0,BM23,"") | O23: =IF(BO23<>0,BO23,"") -> 46202 | P23: =CE23 -> No OBL Yet | R23: =CK23 -> No CERTS Yet | S23: =CP23 | T23: CLARIFICATION ON LATEST SOB | U23: ADVANCE RCVD 27/02-267490071 | X23: 46134 | Y23: 20009552 | Z23: 46074 | AA23: 32014496 | AB23: MALNAD CASHEWS | AC23: April - 26 | AD23: 46142 | AE23: 0.1 | AF23: 100 | AG23: =AF23*(1-AE23) -> 90 | AH23: MT | AI23: 1510 | AJ23: =AI23*AF23 -> 151000 | AK23: CIF | AL23: DP SIGHT | AM23: 0.1 | AN23: 0.9 | AO23: 0 | AP23: 180 DAYS | AQ23: Mr. George | AR23: Mr. Rao | AS23: 5 | AT23: - | AU23: - | AV23: - | AZ23: =AF23*AI23*AM23 -> 15100 | BA23: 46079 | BB23: 46083 | BF23: 46083 | BI23: 267490071 | BK23: 40' | BO23: 46202 | BP23: IVC | BQ23: MANGALORE, INDIA | BX23: =BJ23*AI23 -> 0 | CE23: =IF(J23="VIETNAM", IF(CG23<>"","OBL in Vietnam Office", IF(CF23<>"","OBL in Transit from Vietnam Office", IF(CD23<>0,"OBL In Destination - "&J23, IF(CC23<>0,"OBL in Transit to Destination - "&J23, IF(CB23<>0,"OBL in SIG Office", IF(CA23<>0,"OBL in Transit from Origin to SIG", IF(BZ23<>0,"OBL in Origin - "&I23, IF(BY23<>0,"Draft Rcvd","No OBL Yet")))))))), IF(CO23<>0,"OBL In Destination - "&J23, IF(CM23<>0,"OBL in Transit with Nego Docs - "&J23, IF(CB23<>0,"OBL in SIG Office", IF(CA23<>0,"OBL in Transit from Origin to SIG", IF(BZ23<>0,"OBL in Origin - "&I23, IF(BY23<>0,"Draft Rcvd","No OBL Yet"))))))) -> No OBL Yet | CK23: =IF(CJ23<>0,"CERTS in Destination - "&J23,IF(CI23<>0,"CERT in Transit to -"&J23,IF(CH23<>0,"CERT in Origin - "&I23,IF(CH23="","No CERTS Yet")))) -> No CERTS Yet | CP23: =IF(CO23<>0,"Docs in Buyer's Nego Bank",IF(CN23<>0,"Docs in Transit to Buyer's Nego Bank",IF(CM23<>0,"Docs in Our Nego Bank",IF(CL23="TT PAYMENT","Not Applicable","")))) | CQ23: =(AN23*AI23*BJ23)-AZ23 -> -15100 | CU23: =IF(CS23="","",BJ23-CT23) | CV23: =IF(CS23="","",CU23/BJ23) | CW23: =IF(CS23="","",AZ23+CQ23) | CX23: =IF(CS23="","",BX23*2%) | CY23: =IF(CS23="","",AI23/B23) | DA23: =IF(CS23="","",B23-CZ23) | DC23: =IF(CS23="","",IF(CS23="","",DB23-C23)) | DE23: =IF(CS23="","",10%-DD23) | DF23: =IF(CS23="","",CU23*AI23) | DG23: =IF(CS23="","",IF(DA23>2,2*DA23*CT23*CY23,DA23*CT23*CY23)) | DH23: =IF(CS23="","",IF(DA23>2,2*(DA23-2*CT23*CY23),0)) | DI23: =IF(CS23="","",IF(DC23>0,DC23*0.5*CT23,0)) | DJ23: =IF(CS23="","",IF(DE23<0,DE23*CT23*AI23*1%,0)) | DK23: =IF(CS23="","",SUM(DF23:DJ23)) | DN23: =IF(CS23="","",SUM(DK23:DL23)) | DO23: =IF(CS23="","",BJ23*AI23-DN23) | DP23: =IF(CS23="","",AZ23+CQ23) | DQ23: =IF(CS23="","",IF((DP23-DO23)>0,DP23-DO23,"")) | DR23: =IF(CS23="","",IF((DO23-DP23)>0,(DO23-DP23),"")) | DS23: =IF(CS23="","",IF(DQ23="",H23,"VALENCY")) | DT23: =IF(DN23="","",IF(DN23>0,"CN", "DN")) | DY23: NO VINA/RBS REPORT | EA23: =IF(CS23="","", MIN(0,(IF(DA23>2,2,1)*DA23*CT23*CY23)) ) | EH23: VALENCY IVC | EN23: =EK23*EJ23 -> 0 | EV23: =IF(CR23<>0,"Final Pmt Recd",IF(CM23<>0,"Export Loan",IF(BZ23<>0,"Nego Pending",IF(Z23<>0,"Yet to load","Yet to load")))) -> Yet to load | EX23: =EW23/BJ23 -> #DIV/0! | EY23: Freight paid by origin | FD23: =FC23*BJ23 -> 0 | FL23: =IFERROR(EZ23-BY23,"") -> 0 | FM23: =IFERROR(BM23-FB23,"") -> 0 | FS23: =Y23 -> 20009552 | FT23: =AA23 -> 32014496
A24: =IF(DZ24="CLOSE","Trade closed",IF(DZ24="PMT Pending","FNF Settlement is Due",IF(CS24<>0,"FNF Reconcillation Onging",IF(CR24<>0," Final Pmt Recd , FNF Pending",IF(CM24<>0,"Exp Dox Presented to Bank, Pmt Pending",IF(BZ24<>0,"OBL Scan Recd, Nego Pending",IF(BM24<>0,"Sailed, OBL & Certs Pending",IF(BJ24<>0,"Stuffed, Yet to Sail",IF(BB24<>0,"SI Sent, Shipment Awaited",IF(BA24<>0,"Advance Rcvd, SI Pending",IF(Z24<>0,"SC Raised, Advance Pending",IF(X24<>0,"Deal Ticket Rcvd SC Pending", "Entry Pending")))))))))))) -> Stuffed, Yet to Sail | B24: 48 | C24: 185 | D24: RCN | E24: =IF(AND(LEFT(TRIM(AA24&""),1)="3",BI24<>""),"CLOSE POSITION", IF(AND(LEFT(TRIM(AA24&""),1)="3",BI24=""),"SHORT POSITION", IF(AND(LEFT(TRIM(AA24&""),1)<>"3",BI24<>""),"LONG POSITION","ENTRY PENDING"))) -> CLOSE POSITION | F24: =AA24 -> 32016180 | H24: =AB24 -> QUOC DUY IMPORT EXPORT TRADING PRODUCTION CO., LTD | I24: NIGERIA(SAKI) | J24: VIETNAM | K24: =IF(BQ24<>0,BQ24,"") -> CAT LAI PORT HCMC, VIETNAM | L24: =IF(BI24<>0,BI24,"") -> MEDULG637035 | M24: =IF(BJ24<>0,BJ24,"") -> 251.768 | N24: =IF(BM24<>0,BM24,"") | O24: =IF(BO24<>0,BO24,"") -> 46198 | P24: =CE24 -> No OBL Yet | Q24: TPSCR26010549 | R24: =CK24 -> No CERTS Yet | S24: =CP24 | T24: ETD: 22/5: MSC ANTONIA - CONFIRMATION AWAITED | U24: SOB EXPECTED 21/5-OBL PENDING-VESSEL IS UNDER OPERTAION | Y24: 20010002 | Z24: 46112 | AA24: 32016180 | AB24: QUOC DUY IMPORT EXPORT TRADING PRODUCTION CO., LTD | AC24: April - 26 | AD24: 46142 | AE24: 0.1 | AF24: 250 | AG24: =AF24*(1-AE24) -> 225 | AH24: MT | AI24: 1590 | AJ24: =AI24*AF24 -> 397500 | AK24: CIF | AL24: DP SIGHT | AM24: 0.1 | AN24: 0.9 | AO24: 0 | AP24: 180 DAYS | AQ24: Ms. Tuyet | AR24: Direct | AT24: - | AU24: - | AV24: - | AY24: 46116 | AZ24: =AF24*AI24*AM24 -> 39750 | BA24: 46120 | BB24: 46116 | BF24: 46116 | BI24: MEDULG637035 | BJ24: 251.768 | BK24: 40' | BL24: 10 | BN24: MSNU9022124 | BO24: 46198 | BP24: NIGERIA | BQ24: CAT LAI PORT HCMC, VIETNAM | BR24: MSC | BT24: MSC BARBARA - FN617R | BX24: =BJ24*AI24 -> 400311.12 | CE24: =IF(J24="VIETNAM", IF(CG24<>"","OBL in Vietnam Office", IF(CF24<>"","OBL in Transit from Vietnam Office", IF(CD24<>0,"OBL In Destination - "&J24, IF(CC24<>0,"OBL in Transit to Destination - "&J24, IF(CB24<>0,"OBL in SIG Office", IF(CA24<>0,"OBL in Transit from Origin to SIG", IF(BZ24<>0,"OBL in Origin - "&I24, IF(BY24<>0,"Draft Rcvd","No OBL Yet")))))))), IF(CO24<>0,"OBL In Destination - "&J24, IF(CM24<>0,"OBL in Transit with Nego Docs - "&J24, IF(CB24<>0,"OBL in SIG Office", IF(CA24<>0,"OBL in Transit from Origin to SIG", IF(BZ24<>0,"OBL in Origin - "&I24, IF(BY24<>0,"Draft Rcvd","No OBL Yet"))))))) -> No OBL Yet | CK24: =IF(CJ24<>0,"CERTS in Destination - "&J24,IF(CI24<>0,"CERT in Transit to -"&J24,IF(CH24<>0,"CERT in Origin - "&I24,IF(CH24="","No CERTS Yet")))) -> No CERTS Yet | CP24: =IF(CO24<>0,"Docs in Buyer's Nego Bank",IF(CN24<>0,"Docs in Transit to Buyer's Nego Bank",IF(CM24<>0,"Docs in Our Nego Bank",IF(CL24="TT PAYMENT","Not Applicable","")))) | CQ24: =(AN24*AI24*BJ24)-AZ24 -> 320530.01 | CU24: =IF(CS24="","",BJ24-CT24) | CV24: =IF(CS24="","",CU24/BJ24) | CW24: =IF(CS24="","",AZ24+CQ24) | CX24: =IF(CS24="","",BX24*2%) | CY24: =IF(CS24="","",AI24/B24) | DA24: =IF(CS24="","",B24-CZ24) | DC24: =IF(CS24="","",IF(CS24="","",DB24-C24)) | DE24: =IF(CS24="","",10%-DD24) | DF24: =IF(CS24="","",CU24*AI24) | DG24: =IF(CS24="","",IF(DA24>2,2*DA24*CT24*CY24,DA24*CT24*CY24)) | DH24: =IF(CS24="","",IF(DA24>2,2*(DA24-2*CT24*CY24),0)) | DI24: =IF(CS24="","",IF(DC24>0,DC24*0.5*CT24,0)) | DJ24: =IF(CS24="","",IF(DE24<0,DE24*CT24*AI24*1%,0)) | DK24: =IF(CS24="","",SUM(DF24:DJ24)) | DN24: =IF(CS24="","",SUM(DK24:DL24)) | DO24: =IF(CS24="","",BJ24*AI24-DN24) | DP24: =IF(CS24="","",AZ24+CQ24) | DQ24: =IF(CS24="","",IF((DP24-DO24)>0,DP24-DO24,"")) | DR24: =IF(CS24="","",IF((DO24-DP24)>0,(DO24-DP24),"")) | DS24: =IF(CS24="","",IF(DQ24="",H24,"VALENCY")) | DT24: =IF(DN24="","",IF(DN24>0,"CN", "DN")) | DY24: NO VINA/RBS REPORT | EA24: =IF(CS24="","", MIN(0,(IF(DA24>2,2,1)*DA24*CT24*CY24)) ) | EH24: Valency Nigeria | EN24: =EK24*EJ24 -> 0 | EV24: =IF(CR24<>0,"Final Pmt Recd",IF(CM24<>0,"Export Loan",IF(BZ24<>0,"Nego Pending",IF(Z24<>0,"Yet to load","Yet to load")))) -> Yet to load | EX24: =EW24/BJ24 -> 0 | EY24: Freight paid by origin | FD24: =FC24*BJ24 -> 0 | FL24: =IFERROR(EZ24-BY24,"") -> 0 | FM24: =IFERROR(BM24-FB24,"") -> 0 | FS24: =Y24 -> 20010002 | FT24: =AA24 -> 32016180
A25: =IF(DZ25="CLOSE","Trade closed",IF(DZ25="PMT Pending","FNF Settlement is Due",IF(CS25<>0,"FNF Reconcillation Onging",IF(CR25<>0," Final Pmt Recd , FNF Pending",IF(CM25<>0,"Exp Dox Presented to Bank, Pmt Pending",IF(BZ25<>0,"OBL Scan Recd, Nego Pending",IF(BM25<>0,"Sailed, OBL & Certs Pending",IF(BJ25<>0,"Stuffed, Yet to Sail",IF(BB25<>0,"SI Sent, Shipment Awaited",IF(BA25<>0,"Advance Rcvd, SI Pending",IF(Z25<>0,"SC Raised, Advance Pending",IF(X25<>0,"Deal Ticket Rcvd SC Pending", "Entry Pending")))))))))))) -> SI Sent, Shipment Awaited | B25: 46 | C25: 205 | D25: RCN | E25: =IF(AND(LEFT(TRIM(AA25&""),1)="3",BI25<>""),"CLOSE POSITION", IF(AND(LEFT(TRIM(AA25&""),1)="3",BI25=""),"SHORT POSITION", IF(AND(LEFT(TRIM(AA25&""),1)<>"3",BI25<>""),"LONG POSITION","ENTRY PENDING"))) -> SHORT POSITION | F25: =AA25 -> 32016123 | H25: =AB25 -> RED RIVER FOODS | I25: GAMBIA | J25: VIETNAM | K25: =IF(BQ25<>0,BQ25,"") -> Qui Nhon, Vietnam | L25: =IF(BI25<>0,BI25,"") | M25: =IF(BJ25<>0,BJ25,"") | N25: =IF(BM25<>0,BM25,"") | O25: =IF(BO25<>0,BO25,"") | P25: =CE25 -> No OBL Yet | R25: =CK25 -> No CERTS Yet | S25: =CP25 | T25: Loaded, Update is due from supplier(LS EXIM) due to EID Holiday, | U25: BOOKING NO: 269388817, ETD 5/6 | V25: PENDING SIGNED ADDENDUM | W25: NTT - NEED TO TAKE ADDENDUM, LDS IS DELAYED | X25: 46108 | Y25: 20009869 | Z25: 46108 | AA25: 32016123 | AB25: RED RIVER FOODS | AC25: April - 26 | AD25: 46142 | AE25: 0.05 | AF25: 100 | AG25: =AF25*(1-AE25) -> 95 | AH25: MT | AI25: 1535 | AJ25: =AI25*AF25 -> 153500 | AK25: CIF | AL25: DP SIGHT | AM25: 0.1 | AN25: 0.88 | AO25: 0.02 | AP25: 180 DAYS | AQ25: Mr. Prashant | AR25: Direct | AT25: - | AU25: - | AV25: - | AY25: 46120 | AZ25: =AF25*AI25*AM25 -> 15350 | BA25: 46120 | BB25: 46113 | BF25: 46113 | BK25: 40' | BP25: IVC | BQ25: Qui Nhon, Vietnam | BX25: =BJ25*AI25 -> 0 | CE25: =IF(J25="VIETNAM", IF(CG25<>"","OBL in Vietnam Office", IF(CF25<>"","OBL in Transit from Vietnam Office", IF(CD25<>0,"OBL In Destination - "&J25, IF(CC25<>0,"OBL in Transit to Destination - "&J25, IF(CB25<>0,"OBL in SIG Office", IF(CA25<>0,"OBL in Transit from Origin to SIG", IF(BZ25<>0,"OBL in Origin - "&I25, IF(BY25<>0,"Draft Rcvd","No OBL Yet")))))))), IF(CO25<>0,"OBL In Destination - "&J25, IF(CM25<>0,"OBL in Transit with Nego Docs - "&J25, IF(CB25<>0,"OBL in SIG Office", IF(CA25<>0,"OBL in Transit from Origin to SIG", IF(BZ25<>0,"OBL in Origin - "&I25, IF(BY25<>0,"Draft Rcvd","No OBL Yet"))))))) -> No OBL Yet | CK25: =IF(CJ25<>0,"CERTS in Destination - "&J25,IF(CI25<>0,"CERT in Transit to -"&J25,IF(CH25<>0,"CERT in Origin - "&I25,IF(CH25="","No CERTS Yet")))) -> No CERTS Yet | CP25: =IF(CO25<>0,"Docs in Buyer's Nego Bank",IF(CN25<>0,"Docs in Transit to Buyer's Nego Bank",IF(CM25<>0,"Docs in Our Nego Bank",IF(CL25="TT PAYMENT","Not Applicable","")))) | CQ25: =(AN25*AI25*BJ25)-AZ25 -> -15350 | CU25: =IF(CS25="","",BJ25-CT25) | CV25: =IF(CS25="","",CU25/BJ25) | CW25: =IF(CS25="","",AZ25+CQ25) | CX25: =IF(CS25="","",BX25*2%) | CY25: =IF(CS25="","",AI25/B25) | DA25: =IF(CS25="","",B25-CZ25) | DC25: =IF(CS25="","",IF(CS25="","",DB25-C25)) | DE25: =IF(CS25="","",10%-DD25) | DF25: =IF(CS25="","",CU25*AI25) | DG25: =IF(CS25="","",IF(DA25>2,2*DA25*CT25*CY25,DA25*CT25*CY25)) | DH25: =IF(CS25="","",IF(DA25>2,2*(DA25-2*CT25*CY25),0)) | DI25: =IF(CS25="","",IF(DC25>0,DC25*0.5*CT25,0)) | DJ25: =IF(CS25="","",IF(DE25<0,DE25*CT25*AI25*1%,0)) | DK25: =IF(CS25="","",SUM(DF25:DJ25)) | DN25: =IF(CS25="","",SUM(DK25:DL25)) | DO25: =IF(CS25="","",BJ25*AI25-DN25) | DP25: =IF(CS25="","",AZ25+CQ25) | DQ25: =IF(CS25="","",IF((DP25-DO25)>0,DP25-DO25,"")) | DR25: =IF(CS25="","",IF((DO25-DP25)>0,(DO25-DP25),"")) | DS25: =IF(CS25="","",IF(DQ25="",H25,"VALENCY")) | DT25: =IF(DN25="","",IF(DN25>0,"CN", "DN")) | DY25: NO VINA/RBS REPORT | EA25: =IF(CS25="","", MIN(0,(IF(DA25>2,2,1)*DA25*CT25*CY25)) ) | EE25: 4900009476 | EH25: LS EXIM ENTERPRISE | EJ25: 100 | EK25: 1435 | EN25: =EK25*EJ25 -> 143500 | EV25: =IF(CR25<>0,"Final Pmt Recd",IF(CM25<>0,"Export Loan",IF(BZ25<>0,"Nego Pending",IF(Z25<>0,"Yet to load","Yet to load")))) -> Yet to load | EX25: =EW25/BJ25 -> #DIV/0! | EY25: Freight paid by origin | FD25: =FC25*BJ25 -> 0 | FL25: =IFERROR(EZ25-BY25,"") -> 0 | FM25: =IFERROR(BM25-FB25,"") -> 0 | FS25: =Y25 -> 20009869 | FT25: =AA25 -> 32016123
A26: =IF(DZ26="CLOSE","Trade closed",IF(DZ26="PMT Pending","FNF Settlement is Due",IF(CS26<>0,"FNF Reconcillation Onging",IF(CR26<>0," Final Pmt Recd , FNF Pending",IF(CM26<>0,"Exp Dox Presented to Bank, Pmt Pending",IF(BZ26<>0,"OBL Scan Recd, Nego Pending",IF(BM26<>0,"Sailed, OBL & Certs Pending",IF(BJ26<>0,"Stuffed, Yet to Sail",IF(BB26<>0,"SI Sent, Shipment Awaited",IF(BA26<>0,"Advance Rcvd, SI Pending",IF(Z26<>0,"SC Raised, Advance Pending",IF(X26<>0,"Deal Ticket Rcvd SC Pending", "Entry Pending")))))))))))) -> Exp Dox Presented to Bank, Pmt Pending | B26: 48 | C26: 200 | D26: RCN | E26: =IF(AND(LEFT(TRIM(AA26&""),1)="3",BI26<>""),"CLOSE POSITION", IF(AND(LEFT(TRIM(AA26&""),1)="3",BI26=""),"SHORT POSITION", IF(AND(LEFT(TRIM(AA26&""),1)<>"3",BI26<>""),"LONG POSITION","ENTRY PENDING"))) -> CLOSE POSITION | F26: =AA26 -> 32016283 | H26: =AB26 -> VALENCY AGRO //HSS//Jain Cashew Nuts | I26: GHANA | J26: INDIA | K26: =IF(BQ26<>0,BQ26,"") -> TUTICORIN, INDIA | L26: =IF(BI26<>0,BI26,"") -> MEDUTM434741 | M26: =IF(BJ26<>0,BJ26,"") -> 103.365 | N26: =IF(BM26<>0,BM26,"") -> 46107 | O26: =IF(BO26<>0,BO26,"") -> 46158 | P26: =CE26 -> OBL In Destination - INDIA | R26: =CK26 -> CERTS in Destination - INDIA | S26: =CP26 -> Docs in Buyer's Nego Bank | T26: =IFERROR(_xlfn.XLOOKUP(F26, '[2]Data 2026'!$H$12:$H$111, '[2]Data 2026'!$CL$12:$CL$111),"") | U26: Payment by Valency Agro will be done, 90 days after BL date- HSS Formalities are done(HSS SETTLED) | X26: 46125 | Y26: 20010107 | Z26: 46126 | AA26: 32016283 | AB26: VALENCY AGRO //HSS//Jain Cashew Nuts | AC26: March /April | AD26: 46142 | AE26: 0.05 | AF26: 100 | AG26: =AF26*(1-AE26) -> 95 | AH26: MT | AI26: 1600 | AJ26: =AI26*AF26 -> 160000 | AK26: CIF | AL26: 90 DAYS FROM BL DATE | AM26: 0 | AN26: 1 | AO26: 0 | AP26: 180 DAYS | AQ26: Mr. Chirag | AR26: Direct | AT26: - | AU26: - | AV26: - | AZ26: =AF26*AI26*AM26 -> 0 | BA26: 46107 | BB26: 46105 | BF26: 46105 | BI26: MEDUTM434741 | BJ26: 103.365 | BK26: 40' | BL26: 4 | BM26: 46107 | BN26: TEMU8261109 | BO26: 46158 | BP26: GHANA | BQ26: TUTICORIN, INDIA | BR26: MSC | BT26: MSC MIRJAM - | BU26: FY613R | BV26: 90084338 | BW26: 46136 | BX26: =BJ26*AI26 -> 165384 | BZ26: 46121 | CA26: 5548360370 | CB26: 46126 | CE26: =IF(J26="VIETNAM", IF(CG26<>"","OBL in Vietnam Office", IF(CF26<>"","OBL in Transit from Vietnam Office", IF(CD26<>0,"OBL In Destination - "&J26, IF(CC26<>0,"OBL in Transit to Destination - "&J26, IF(CB26<>0,"OBL in SIG Office", IF(CA26<>0,"OBL in Transit from Origin to SIG", IF(BZ26<>0,"OBL in Origin - "&I26, IF(BY26<>0,"Draft Rcvd","No OBL Yet")))))))), IF(CO26<>0,"OBL In Destination - "&J26, IF(CM26<>0,"OBL in Transit with Nego Docs - "&J26, IF(CB26<>0,"OBL in SIG Office", IF(CA26<>0,"OBL in Transit from Origin to SIG", IF(BZ26<>0,"OBL in Origin - "&I26, IF(BY26<>0,"Draft Rcvd","No OBL Yet"))))))) -> OBL In Destination - INDIA | CH26: 46146 | CI26: 2243727452 | CJ26: 46153 | CK26: =IF(CJ26<>0,"CERTS in Destination - "&J26,IF(CI26<>0,"CERT in Transit to -"&J26,IF(CH26<>0,"CERT in Origin - "&I26,IF(CH26="","No CERTS Yet")))) -> CERTS in Destination - INDIA | CL26: ICICI BANK | CM26: 46136 | CN26: 1012283075 | CO26: 46142 | CP26: =IF(CO26<>0,"Docs in Buyer's Nego Bank",IF(CN26<>0,"Docs in Transit to Buyer's Nego Bank",IF(CM26<>0,"Docs in Our Nego Bank",IF(CL26="TT PAYMENT","Not Applicable","")))) -> Docs in Buyer's Nego Bank | CQ26: =(AN26*AI26*BJ26)-AZ26 -> 165384 | CU26: =IF(CS26="","",BJ26-CT26) | CV26: =IF(CS26="","",CU26/BJ26) | CW26: =IF(CS26="","",AZ26+CQ26) | CX26: =IF(CS26="","",BX26*2%) | CY26: =IF(CS26="","",AI26/B26) | DA26: =IF(CS26="","",B26-CZ26) | DC26: =IF(CS26="","",IF(CS26="","",DB26-C26)) | DE26: =IF(CS26="","",10%-DD26) | DF26: =IF(CS26="","",CU26*AI26) | DG26: =IF(CS26="","",IF(DA26>2,2*DA26*CT26*CY26,DA26*CT26*CY26)) | DH26: =IF(CS26="","",IF(DA26>2,2*(DA26-2*CT26*CY26),0)) | DI26: =IF(CS26="","",IF(DC26>0,DC26*0.5*CT26,0)) | DJ26: =IF(CS26="","",IF(DE26<0,DE26*CT26*AI26*1%,0)) | DK26: =IF(CS26="","",SUM(DF26:DJ26)) | DN26: =IF(CS26="","",SUM(DK26:DL26)) | DO26: =IF(CS26="","",BJ26*AI26-DN26) | DP26: =IF(CS26="","",AZ26+CQ26) | DQ26: =IF(CS26="","",IF((DP26-DO26)>0,DP26-DO26,"")) | DR26: =IF(CS26="","",IF((DO26-DP26)>0,(DO26-DP26),"")) | DS26: =IF(CS26="","",IF(DQ26="",H26,"VALENCY")) | DT26: =IF(DN26="","",IF(DN26>0,"CN", "DN")) | DY26: NO VINA/RBS REPORT | EA26: =IF(CS26="","", MIN(0,(IF(DA26>2,2,1)*DA26*CT26*CY26)) ) | EH26: Valora Exim | EN26: =EK26*EJ26 -> 0 | EV26: =IF(CR26<>0,"Final Pmt Recd",IF(CM26<>0,"Export Loan",IF(BZ26<>0,"Nego Pending",IF(Z26<>0,"Yet to load","Yet to load")))) -> Export Loan | EX26: =EW26/BJ26 -> 0 | EY26: Freight paid by origin | FA26: 22138897 | FD26: =FC26*BJ26 -> 0 | FL26: =IFERROR(EZ26-BY26,"") -> 0 | FM26: =IFERROR(BM26-FB26,"") -> 46107 | FS26: =Y26 -> 20010107 | FT26: =AA26 -> 32016283 | GD26: 90084338
A27: =IF(DZ27="CLOSE","Trade closed",IF(DZ27="PMT Pending","FNF Settlement is Due",IF(CS27<>0,"FNF Reconcillation Onging",IF(CR27<>0," Final Pmt Recd , FNF Pending",IF(CM27<>0,"Exp Dox Presented to Bank, Pmt Pending",IF(BZ27<>0,"OBL Scan Recd, Nego Pending",IF(BM27<>0,"Sailed, OBL & Certs Pending",IF(BJ27<>0,"Stuffed, Yet to Sail",IF(BB27<>0,"SI Sent, Shipment Awaited",IF(BA27<>0,"Advance Rcvd, SI Pending",IF(Z27<>0,"SC Raised, Advance Pending",IF(X27<>0,"Deal Ticket Rcvd SC Pending", "Entry Pending")))))))))))) -> Exp Dox Presented to Bank, Pmt Pending | B27: 48 | C27: 200 | D27: RCN | E27: =IF(AND(LEFT(TRIM(AA27&""),1)="3",BI27<>""),"CLOSE POSITION", IF(AND(LEFT(TRIM(AA27&""),1)="3",BI27=""),"SHORT POSITION", IF(AND(LEFT(TRIM(AA27&""),1)<>"3",BI27<>""),"LONG POSITION","ENTRY PENDING"))) -> CLOSE POSITION | F27: =AA27 -> 32016346 | H27: =AB27 -> Valency Agro (Processing) | I27: GHANA | J27: INDIA | K27: =IF(BQ27<>0,BQ27,"") -> TUTICORIN, INDIA | L27: =IF(BI27<>0,BI27,"") -> MEDUTM435789 | M27: =IF(BJ27<>0,BJ27,"") -> 104.2 | N27: =IF(BM27<>0,BM27,"") -> 46107 | O27: =IF(BO27<>0,BO27,"") -> 46160 | P27: =CE27 -> OBL In Destination - INDIA | R27: =CK27 -> CERTS in Destination - INDIA | S27: =CP27 -> Docs in Buyer's Nego Bank | T27: =IFERROR(_xlfn.XLOOKUP(F27, '[2]Data 2026'!$H$12:$H$111, '[2]Data 2026'!$CL$12:$CL$111),"") | U27: Payment by Valency Agro will be done, 90 days after BL date- Clearance under process | W27: CARGO CLEARANCE UNDER PROCESS | X27: 46142 | Y27: 20010240 | Z27: 46142 | AA27: 32016346 | AB27: Valency Agro (Processing) | AC27: March /April | AD27: 46142 | AE27: 0.1 | AF27: 100 | AG27: =AF27*(1-AE27) -> 90 | AH27: MT | AI27: 1526 | AJ27: =AI27*AF27 -> 152600 | AK27: CIF | AL27: 90 DAYS FROM BL DATE | AM27: 0 | AN27: 1 | AO27: 0 | AP27: 180 DAYS | AR27: Direct | AT27: - | AU27: - | AV27: - | AZ27: =AF27*AI27*AM27 -> 0 | BA27: 46107 | BB27: 46105 | BF27: 46105 | BI27: MEDUTM435789 | BJ27: 104.2 | BK27: 40' | BL27: 4 | BM27: 46107 | BN27: FFAU3886533 | BO27: 46160 | BP27: GHANA | BQ27: TUTICORIN, INDIA | BR27: MSC | BT27: MSC MIRJAM | BU27: FY613R | BV27: 90085095 | BW27: 46142 | BX27: =BJ27*AI27 -> 159009.2 | BZ27: 46121 | CA27: 5548360370 | CB27: 46126 | CE27: =IF(J27="VIETNAM", IF(CG27<>"","OBL in Vietnam Office", IF(CF27<>"","OBL in Transit from Vietnam Office", IF(CD27<>0,"OBL In Destination - "&J27, IF(CC27<>0,"OBL in Transit to Destination - "&J27, IF(CB27<>0,"OBL in SIG Office", IF(CA27<>0,"OBL in Transit from Origin to SIG", IF(BZ27<>0,"OBL in Origin - "&I27, IF(BY27<>0,"Draft Rcvd","No OBL Yet")))))))), IF(CO27<>0,"OBL In Destination - "&J27, IF(CM27<>0,"OBL in Transit with Nego Docs - "&J27, IF(CB27<>0,"OBL in SIG Office", IF(CA27<>0,"OBL in Transit from Origin to SIG", IF(BZ27<>0,"OBL in Origin - "&I27, IF(BY27<>0,"Draft Rcvd","No OBL Yet"))))))) -> OBL In Destination - INDIA | CH27: 46150 | CI27: 1978639121 | CJ27: 46156 | CK27: =IF(CJ27<>0,"CERTS in Destination - "&J27,IF(CI27<>0,"CERT in Transit to -"&J27,IF(CH27<>0,"CERT in Origin - "&I27,IF(CH27="","No CERTS Yet")))) -> CERTS in Destination - INDIA | CL27: ICICI BANK | CM27: 46148 | CN27: 1534736851 | CO27: 46155 | CP27: =IF(CO27<>0,"Docs in Buyer's Nego Bank",IF(CN27<>0,"Docs in Transit to Buyer's Nego Bank",IF(CM27<>0,"Docs in Our Nego Bank",IF(CL27="TT PAYMENT","Not Applicable","")))) -> Docs in Buyer's Nego Bank | CQ27: =(AN27*AI27*BJ27)-AZ27 -> 159009.2 | CU27: =IF(CS27="","",BJ27-CT27) | CV27: =IF(CS27="","",CU27/BJ27) | CW27: =IF(CS27="","",AZ27+CQ27) | CX27: =IF(CS27="","",BX27*2%) | CY27: =IF(CS27="","",AI27/B27) | DA27: =IF(CS27="","",B27-CZ27) | DC27: =IF(CS27="","",IF(CS27="","",DB27-C27)) | DE27: =IF(CS27="","",10%-DD27) | DF27: =IF(CS27="","",CU27*AI27) | DG27: =IF(CS27="","",IF(DA27>2,2*DA27*CT27*CY27,DA27*CT27*CY27)) | DH27: =IF(CS27="","",IF(DA27>2,2*(DA27-2*CT27*CY27),0)) | DI27: =IF(CS27="","",IF(DC27>0,DC27*0.5*CT27,0)) | DJ27: =IF(CS27="","",IF(DE27<0,DE27*CT27*AI27*1%,0)) | DK27: =IF(CS27="","",SUM(DF27:DJ27)) | DN27: =IF(CS27="","",SUM(DK27:DL27)) | DO27: =IF(CS27="","",BJ27*AI27-DN27) | DP27: =IF(CS27="","",AZ27+CQ27) | DQ27: =IF(CS27="","",IF((DP27-DO27)>0,DP27-DO27,"")) | DR27: =IF(CS27="","",IF((DO27-DP27)>0,(DO27-DP27),"")) | DS27: =IF(CS27="","",IF(DQ27="",H27,"VALENCY")) | DT27: =IF(DN27="","",IF(DN27>0,"CN", "DN")) | DY27: NO VINA/RBS REPORT | EA27: =IF(CS27="","", MIN(0,(IF(DA27>2,2,1)*DA27*CT27*CY27)) ) | EH27: Valora Exim | EN27: =EK27*EJ27 -> 0 | EV27: =IF(CR27<>0,"Final Pmt Recd",IF(CM27<>0,"Export Loan",IF(BZ27<>0,"Nego Pending",IF(Z27<>0,"Yet to load","Yet to load")))) -> Export Loan | EX27: =EW27/BJ27 -> 0 | EY27: Freight paid by origin | FD27: =FC27*BJ27 -> 0 | FL27: =IFERROR(EZ27-BY27,"") -> 0 | FM27: =IFERROR(BM27-FB27,"") -> 46107 | FS27: =Y27 -> 20010240 | FT27: =AA27 -> 32016346
A28: =IF(DZ28="CLOSE","Trade closed",IF(DZ28="PMT Pending","FNF Settlement is Due",IF(CS28<>0,"FNF Reconcillation Onging",IF(CR28<>0," Final Pmt Recd , FNF Pending",IF(CM28<>0,"Exp Dox Presented to Bank, Pmt Pending",IF(BZ28<>0,"OBL Scan Recd, Nego Pending",IF(BM28<>0,"Sailed, OBL & Certs Pending",IF(BJ28<>0,"Stuffed, Yet to Sail",IF(BB28<>0,"SI Sent, Shipment Awaited",IF(BA28<>0,"Advance Rcvd, SI Pending",IF(Z28<>0,"SC Raised, Advance Pending",IF(X28<>0,"Deal Ticket Rcvd SC Pending", "Entry Pending")))))))))))) -> Sailed, OBL & Certs Pending | B28: 48 | C28: 200 | D28: RCN | E28: =IF(AND(LEFT(TRIM(AA28&""),1)="3",BI28<>""),"CLOSE POSITION", IF(AND(LEFT(TRIM(AA28&""),1)="3",BI28=""),"SHORT POSITION", IF(AND(LEFT(TRIM(AA28&""),1)<>"3",BI28<>""),"LONG POSITION","ENTRY PENDING"))) -> CLOSE POSITION | F28: =AA28 -> 32014998 | H28: =AB28 -> THAO NGUYEN COMPANY LIMITED | I28: IVC | J28: VIETNAM | K28: =IF(BQ28<>0,BQ28,"") -> CAT LAI HCMC, Vietnam | L28: =IF(BI28<>0,BI28,"") -> ONEYABJG00282600 | M28: =IF(BJ28<>0,BJ28,"") -> 250 | N28: =IF(BM28<>0,BM28,"") -> 46159 | O28: =IF(BO28<>0,BO28,"") -> 46178 | P28: =CE28 -> No OBL Yet | Q28: TPSCR26010451 | R28: =CK28 -> No CERTS Yet | S28: =CP28 | T28: PENDING OBL-SAILED 17/5 | U28: DRAFT HBL CONFIRMED 20/5- OBL PENDING | W28: NTT - OBL PRINTING ISSUE IN SIG, ETA ERROR | X28: 46086 | Y28: 20009663 | Z28: 46086 | AA28: 32014998 | AB28: THAO NGUYEN COMPANY LIMITED | AC28: April/May - 26 | AD28: 46173 | AE28: 0.1 | AF28: 250 | AG28: =AF28*(1-AE28) -> 225 | AH28: MT | AI28: 1515 | AJ28: 378750 | AK28: CFR | AL28: DP SIGHT | AM28: 0.1 | AN28: 0.88 | AO28: 0.02 | AP28: 180 DAYS | AQ28: Ms. Tuyet | AR28: Ms. Tuyet | AT28: - | AU28: - | AV28: - | AY28: 46094 | AZ28: =AF28*AI28*AM28 -> 37875 | BA28: 46097 | BI28: ONEYABJG00282600 | BJ28: 250 | BK28: 40' | BL28: 10 | BM28: 46159 | BO28: 46178 | BP28: IVC | BQ28: CAT LAI HCMC, Vietnam | BR28: ONE LINE | BX28: =BJ28*AI28 -> 378750 | CE28: =IF(J28="VIETNAM", IF(CG28<>"","OBL in Vietnam Office", IF(CF28<>"","OBL in Transit from Vietnam Office", IF(CD28<>0,"OBL In Destination - "&J28, IF(CC28<>0,"OBL in Transit to Destination - "&J28, IF(CB28<>0,"OBL in SIG Office", IF(CA28<>0,"OBL in Transit from Origin to SIG", IF(BZ28<>0,"OBL in Origin - "&I28, IF(BY28<>0,"Draft Rcvd","No OBL Yet")))))))), IF(CO28<>0,"OBL In Destination - "&J28, IF(CM28<>0,"OBL in Transit with Nego Docs - "&J28, IF(CB28<>0,"OBL in SIG Office", IF(CA28<>0,"OBL in Transit from Origin to SIG", IF(BZ28<>0,"OBL in Origin - "&I28, IF(BY28<>0,"Draft Rcvd","No OBL Yet"))))))) -> No OBL Yet | CK28: =IF(CJ28<>0,"CERTS in Destination - "&J28,IF(CI28<>0,"CERT in Transit to -"&J28,IF(CH28<>0,"CERT in Origin - "&I28,IF(CH28="","No CERTS Yet")))) -> No CERTS Yet | CP28: =IF(CO28<>0,"Docs in Buyer's Nego Bank",IF(CN28<>0,"Docs in Transit to Buyer's Nego Bank",IF(CM28<>0,"Docs in Our Nego Bank",IF(CL28="TT PAYMENT","Not Applicable","")))) | CQ28: =(AN28*AI28*BJ28)-AZ28 -> 295425 | CU28: =IF(CS28="","",BJ28-CT28) | CV28: =IF(CS28="","",CU28/BJ28) | CW28: =IF(CS28="","",AZ28+CQ28) | CX28: =IF(CS28="","",BX28*2%) | CY28: =IF(CS28="","",AI28/B28) | DA28: =IF(CS28="","",B28-CZ28) | DC28: =IF(CS28="","",IF(CS28="","",DB28-C28)) | DE28: =IF(CS28="","",10%-DD28) | DF28: =IF(CS28="","",CU28*AI28) | DG28: =IF(CS28="","",IF(DA28>2,2*DA28*CT28*CY28,DA28*CT28*CY28)) | DH28: =IF(CS28="","",IF(DA28>2,2*(DA28-2*CT28*CY28),0)) | DI28: =IF(CS28="","",IF(DC28>0,DC28*0.5*CT28,0)) | DJ28: =IF(CS28="","",IF(DE28<0,DE28*CT28*AI28*1%,0)) | DK28: =IF(CS28="","",SUM(DF28:DJ28)) | DN28: =IF(CS28="","",SUM(DK28:DL28)) | DO28: =IF(CS28="","",BJ28*AI28-DN28) | DP28: =IF(CS28="","",AZ28+CQ28) | DQ28: =IF(CS28="","",IF((DP28-DO28)>0,DP28-DO28,"")) | DR28: =IF(CS28="","",IF((DO28-DP28)>0,(DO28-DP28),"")) | DS28: =IF(CS28="","",IF(DQ28="",H28,"VALENCY")) | DT28: =IF(DN28="","",IF(DN28>0,"CN", "DN")) | DY28: NO VINA/RBS REPORT | EA28: =IF(CS28="","", MIN(0,(IF(DA28>2,2,1)*DA28*CT28*CY28)) ) | EH28: VALENCY IVC | EN28: =EK28*EJ28 -> 0 | EV28: =IF(CR28<>0,"Final Pmt Recd",IF(CM28<>0,"Export Loan",IF(BZ28<>0,"Nego Pending",IF(Z28<>0,"Yet to load","Yet to load")))) -> Yet to load | EX28: =EW28/BJ28 -> 0 | EY28: Freight paid by origin | FD28: =FC28*BJ28 -> 0 | FL28: =IFERROR(EZ28-BY28,"") -> 0 | FM28: =IFERROR(BM28-FB28,"") -> 46159 | FS28: =Y28 -> 20009663 | FT28: =AA28 -> 32014998
A29: =IF(DZ29="CLOSE","Trade closed",IF(DZ29="PMT Pending","FNF Settlement is Due",IF(CS29<>0,"FNF Reconcillation Onging",IF(CR29<>0," Final Pmt Recd , FNF Pending",IF(CM29<>0,"Exp Dox Presented to Bank, Pmt Pending",IF(BZ29<>0,"OBL Scan Recd, Nego Pending",IF(BM29<>0,"Sailed, OBL & Certs Pending",IF(BJ29<>0,"Stuffed, Yet to Sail",IF(BB29<>0,"SI Sent, Shipment Awaited",IF(BA29<>0,"Advance Rcvd, SI Pending",IF(Z29<>0,"SC Raised, Advance Pending",IF(X29<>0,"Deal Ticket Rcvd SC Pending", "Entry Pending")))))))))))) -> SI Sent, Shipment Awaited | B29: 47 | C29: 210 | D29: RCN | E29: =IF(AND(LEFT(TRIM(AA29&""),1)="3",BI29<>""),"CLOSE POSITION", IF(AND(LEFT(TRIM(AA29&""),1)="3",BI29=""),"SHORT POSITION", IF(AND(LEFT(TRIM(AA29&""),1)<>"3",BI29<>""),"LONG POSITION","ENTRY PENDING"))) -> SHORT POSITION | F29: =AA29 -> 32016244 | H29: =AB29 -> INDIA ENTERPRISES | I29: BURKINA FASO | J29: INDIA | K29: =IF(BQ29<>0,BQ29,"") -> MANGALORE, INDIA | L29: =IF(BI29<>0,BI29,"") | M29: =IF(BJ29<>0,BJ29,"") | N29: =IF(BM29<>0,BM29,"") | O29: =IF(BO29<>0,BO29,"") | P29: =CE29 -> No OBL Yet | R29: =CK29 -> No CERTS Yet | S29: =CP29 | T29: Gated IN, SOB Awaited( ETD 1 / 2 WEEK OF JUNE) - | U29: ADVANCE RECVD 16/4-EBKG16643471- STUFFING THIS WEEK | V29: ADDENDUM TO TAKE | W29: NTT - NEED TO TAKE ADDENDUM, LDS IS DELAYED | Y29: 20010003 | Z29: 46113 | AA29: 32016244 | AB29: INDIA ENTERPRISES | AC29: April - 26 | AD29: 46142 | AE29: 0.1 | AF29: 100 | AG29: =AF29*(1-AE29) -> 90 | AH29: MT | AI29: 1510 | AJ29: =AI29*AF29 -> 151000 | AK29: CIF | AL29: DP SIGHT | AM29: 0.1 | AN29: 0.9 | AO29: 0 | AP29: 180 DAYS | AQ29: Mr. George | AT29: - | AU29: - | AV29: - | AY29: 46116 | AZ29: =AF29*AI29*AM29 -> 15100 | BA29: 46128 | BB29: 46130 | BK29: 40' | BP29: LOME, TOGO | BQ29: MANGALORE, INDIA | BX29: =BJ29*AI29 -> 0 | CE29: =IF(J29="VIETNAM", IF(CG29<>"","OBL in Vietnam Office", IF(CF29<>"","OBL in Transit from Vietnam Office", IF(CD29<>0,"OBL In Destination - "&J29, IF(CC29<>0,"OBL in Transit to Destination - "&J29, IF(CB29<>0,"OBL in SIG Office", IF(CA29<>0,"OBL in Transit from Origin to SIG", IF(BZ29<>0,"OBL in Origin - "&I29, IF(BY29<>0,"Draft Rcvd","No OBL Yet")))))))), IF(CO29<>0,"OBL In Destination - "&J29, IF(CM29<>0,"OBL in Transit with Nego Docs - "&J29, IF(CB29<>0,"OBL in SIG Office", IF(CA29<>0,"OBL in Transit from Origin to SIG", IF(BZ29<>0,"OBL in Origin - "&I29, IF(BY29<>0,"Draft Rcvd","No OBL Yet"))))))) -> No OBL Yet | CK29: =IF(CJ29<>0,"CERTS in Destination - "&J29,IF(CI29<>0,"CERT in Transit to -"&J29,IF(CH29<>0,"CERT in Origin - "&I29,IF(CH29="","No CERTS Yet")))) -> No CERTS Yet | CP29: =IF(CO29<>0,"Docs in Buyer's Nego Bank",IF(CN29<>0,"Docs in Transit to Buyer's Nego Bank",IF(CM29<>0,"Docs in Our Nego Bank",IF(CL29="TT PAYMENT","Not Applicable","")))) | CQ29: =(AN29*AI29*BJ29)-AZ29 -> -15100 | CU29: =IF(CS29="","",BJ29-CT29) | CV29: =IF(CS29="","",CU29/BJ29) | CW29: =IF(CS29="","",AZ29+CQ29) | CX29: =IF(CS29="","",BX29*2%) | CY29: =IF(CS29="","",AI29/B29) | DA29: =IF(CS29="","",B29-CZ29) | DC29: =IF(CS29="","",IF(CS29="","",DB29-C29)) | DE29: =IF(CS29="","",10%-DD29) | DF29: =IF(CS29="","",CU29*AI29) | DG29: =IF(CS29="","",IF(DA29>2,2*DA29*CT29*CY29,DA29*CT29*CY29)) | DH29: =IF(CS29="","",IF(DA29>2,2*(DA29-2*CT29*CY29),0)) | DI29: =IF(CS29="","",IF(DC29>0,DC29*0.5*CT29,0)) | DJ29: =IF(CS29="","",IF(DE29<0,DE29*CT29*AI29*1%,0)) | DK29: =IF(CS29="","",SUM(DF29:DJ29)) | DN29: =IF(CS29="","",SUM(DK29:DL29)) | DO29: =IF(CS29="","",BJ29*AI29-DN29) | DP29: =IF(CS29="","",AZ29+CQ29) | DQ29: =IF(CS29="","",IF((DP29-DO29)>0,DP29-DO29,"")) | DR29: =IF(CS29="","",IF((DO29-DP29)>0,(DO29-DP29),"")) | DS29: =IF(CS29="","",IF(DQ29="",H29,"VALENCY")) | DT29: =IF(DN29="","",IF(DN29>0,"CN", "DN")) | DY29: NO VINA/RBS REPORT | EA29: =IF(CS29="","", MIN(0,(IF(DA29>2,2,1)*DA29*CT29*CY29)) ) | EH29: VALORA BURKINA EXIM SARL | EN29: =EK29*EJ29 -> 0 | EV29: =IF(CR29<>0,"Final Pmt Recd",IF(CM29<>0,"Export Loan",IF(BZ29<>0,"Nego Pending",IF(Z29<>0,"Yet to load","Yet to load")))) -> Yet to load | EX29: =EW29/BJ29 -> #DIV/0! | EY29: Freight paid by origin | FD29: =FC29*BJ29 -> 0 | FL29: =IFERROR(EZ29-BY29,"") -> 0 | FM29: =IFERROR(BM29-FB29,"") -> 0 | FS29: =Y29 -> 20010003 | FT29: =AA29 -> 32016244
A30: =IF(DZ30="CLOSE","Trade closed",IF(DZ30="PMT Pending","FNF Settlement is Due",IF(CS30<>0,"FNF Reconcillation Onging",IF(CR30<>0," Final Pmt Recd , FNF Pending",IF(CM30<>0,"Exp Dox Presented to Bank, Pmt Pending",IF(BZ30<>0,"OBL Scan Recd, Nego Pending",IF(BM30<>0,"Sailed, OBL & Certs Pending",IF(BJ30<>0,"Stuffed, Yet to Sail",IF(BB30<>0,"SI Sent, Shipment Awaited",IF(BA30<>0,"Advance Rcvd, SI Pending",IF(Z30<>0,"SC Raised, Advance Pending",IF(X30<>0,"Deal Ticket Rcvd SC Pending", "Entry Pending")))))))))))) -> Final Pmt Recd , FNF Pending | B30: 48 | C30: 185 | D30: RCN | E30: =IF(AND(LEFT(TRIM(AA30&""),1)="3",BI30<>""),"CLOSE POSITION", IF(AND(LEFT(TRIM(AA30&""),1)="3",BI30=""),"SHORT POSITION", IF(AND(LEFT(TRIM(AA30&""),1)<>"3",BI30<>""),"LONG POSITION","ENTRY PENDING"))) -> CLOSE POSITION | F30: =AA30 -> 32016264 | H30: =AB30 -> LIEN VIET TRADING | I30: NIGERIA(OGB) | J30: VIETNAM | K30: =IF(BQ30<>0,BQ30,"") -> HCMC, VIETNAM | L30: =IF(BI30<>0,BI30,"") -> MEDULG618936 | M30: =IF(BJ30<>0,BJ30,"") -> 264.197 | N30: =IF(BM30<>0,BM30,"") -> 46099 | O30: =IF(BO30<>0,BO30,"") -> 46161 | P30: =CE30 -> OBL In Destination - VIETNAM | Q30: TPSCR26010490 | R30: =CK30 -> CERTS in Destination - VIETNAM | S30: =CP30 -> Docs in Buyer's Nego Bank | T30: =IFERROR(_xlfn.XLOOKUP(F30, '[2]Data 2026'!$H$12:$H$111, '[2]Data 2026'!$CL$12:$CL$111),"") | U30: PAYMENT RCVD 26/05 | X30: 46120 | Y30: 20010050 | Z30: 46120 | AA30: 32016264 | AB30: LIEN VIET TRADING | AC30: April - 26 | AD30: 46142 | AE30: 0.1 | AF30: 250 | AG30: =AF30*(1-AE30) -> 225 | AH30: MT | AI30: 1570 | AJ30: =AI30*AF30 -> 392500 | AK30: CFR | AL30: 10% ADVANCE 88% DP AT SIGHT 2% after vina | AM30: 0.1 | AN30: 0.88 | AO30: 0.02 | AP30: 180 DAYS | AQ30: PRASHANT | AR30: Global Link | AS30: 5 | AT30: - | AU30: - | AV30: - | AY30: 46122 | AZ30: =AF30*AI30*AM30 -> 39250 | BA30: 46125 | BI30: MEDULG618936 | BJ30: 264.197 | BM30: 46099 | BN30: Nansha, CN 05-05 | BO30: 46161 | BP30: NIGERIA | BQ30: HCMC, VIETNAM | BR30: MSC | BT30: MSC TASMANIA | BU30: WP609R | BV30: 90085131 | BW30: 46142 | BX30: =BJ30*AI30 -> 414789.29 | BZ30: 46135 | CC30: 25 2898 9820 | CD30: 46150 | CE30: =IF(J30="VIETNAM", IF(CG30<>"","OBL in Vietnam Office", IF(CF30<>"","OBL in Transit from Vietnam Office", IF(CD30<>0,"OBL In Destination - "&J30, IF(CC30<>0,"OBL in Transit to Destination - "&J30, IF(CB30<>0,"OBL in SIG Office", IF(CA30<>0,"OBL in Transit from Origin to SIG", IF(BZ30<>0,"OBL in Origin - "&I30, IF(BY30<>0,"Draft Rcvd","No OBL Yet")))))))), IF(CO30<>0,"OBL In Destination - "&J30, IF(CM30<>0,"OBL in Transit with Nego Docs - "&J30, IF(CB30<>0,"OBL in SIG Office", IF(CA30<>0,"OBL in Transit from Origin to SIG", IF(BZ30<>0,"OBL in Origin - "&I30, IF(BY30<>0,"Draft Rcvd","No OBL Yet"))))))) -> OBL In Destination - VIETNAM | CH30: 46135 | CI30: 25 2898 9820 | CJ30: 46150 | CK30: =IF(CJ30<>0,"CERTS in Destination - "&J30,IF(CI30<>0,"CERT in Transit to -"&J30,IF(CH30<>0,"CERT in Origin - "&I30,IF(CH30="","No CERTS Yet")))) -> CERTS in Destination - VIETNAM | CL30: Habib Bank | CM30: 46149 | CN30: 7291530002 | CO30: 46154 | CP30: =IF(CO30<>0,"Docs in Buyer's Nego Bank",IF(CN30<>0,"Docs in Transit to Buyer's Nego Bank",IF(CM30<>0,"Docs in Our Nego Bank",IF(CL30="TT PAYMENT","Not Applicable","")))) -> Docs in Buyer's Nego Bank | CQ30: 367243.5 | CR30: 46168 | CU30: =IF(CS30="","",BJ30-CT30) | CV30: =IF(CS30="","",CU30/BJ30) | CW30: =IF(CS30="","",AZ30+CQ30) | CX30: =IF(CS30="","",BX30*2%) | CY30: =IF(CS30="","",AI30/B30) | DA30: =IF(CS30="","",B30-CZ30) | DC30: =IF(CS30="","",IF(CS30="","",DB30-C30)) | DE30: =IF(CS30="","",10%-DD30) | DF30: =IF(CS30="","",CU30*AI30) | DG30: =IF(CS30="","",IF(DA30>2,2*DA30*CT30*CY30,DA30*CT30*CY30)) | DH30: =IF(CS30="","",IF(DA30>2,2*(DA30-2*CT30*CY30),0)) | DI30: =IF(CS30="","",IF(DC30>0,DC30*0.5*CT30,0)) | DJ30: =IF(CS30="","",IF(DE30<0,DE30*CT30*AI30*1%,0)) | DK30: =IF(CS30="","",SUM(DF30:DJ30)) | DN30: =IF(CS30="","",SUM(DK30:DL30)) | DO30: =IF(CS30="","",BJ30*AI30-DN30) | DP30: =IF(CS30="","",AZ30+CQ30) | DQ30: =IF(CS30="","",IF((DP30-DO30)>0,DP30-DO30,"")) | DR30: =IF(CS30="","",IF((DO30-DP30)>0,(DO30-DP30),"")) | DS30: =IF(CS30="","",IF(DQ30="",H30,"VALENCY")) | DT30: =IF(DN30="","",IF(DN30>0,"CN", "DN")) | DY30: NO VINA/RBS REPORT | EA30: =IF(CS30="","", MIN(0,(IF(DA30>2,2,1)*DA30*CT30*CY30)) ) | EH30: Valency Nigeria | EN30: =EK30*EJ30 -> 0 | EV30: =IF(CR30<>0,"Final Pmt Recd",IF(CM30<>0,"Export Loan",IF(BZ30<>0,"Nego Pending",IF(Z30<>0,"Yet to load","Yet to load")))) -> Final Pmt Recd | EX30: =EW30/BJ30 -> 0 | EY30: Freight paid by origin | FD30: =FC30*BJ30 -> 0 | FL30: =IFERROR(EZ30-BY30,"") -> 0 | FM30: =IFERROR(BM30-FB30,"") -> 46099 | FS30: =Y30 -> 20010050 | FT30: =AA30 -> 32016264
A31: =IF(DZ31="CLOSE","Trade closed",IF(DZ31="PMT Pending","FNF Settlement is Due",IF(CS31<>0,"FNF Reconcillation Onging",IF(CR31<>0," Final Pmt Recd , FNF Pending",IF(CM31<>0,"Exp Dox Presented to Bank, Pmt Pending",IF(BZ31<>0,"OBL Scan Recd, Nego Pending",IF(BM31<>0,"Sailed, OBL & Certs Pending",IF(BJ31<>0,"Stuffed, Yet to Sail",IF(BB31<>0,"SI Sent, Shipment Awaited",IF(BA31<>0,"Advance Rcvd, SI Pending",IF(Z31<>0,"SC Raised, Advance Pending",IF(X31<>0,"Deal Ticket Rcvd SC Pending", "Entry Pending")))))))))))) -> SI Sent, Shipment Awaited | B31: 48 | C31: 200 | D31: RCN | E31: =IF(AND(LEFT(TRIM(AA31&""),1)="3",BI31<>""),"CLOSE POSITION", IF(AND(LEFT(TRIM(AA31&""),1)="3",BI31=""),"SHORT POSITION", IF(AND(LEFT(TRIM(AA31&""),1)<>"3",BI31<>""),"LONG POSITION","ENTRY PENDING"))) -> CLOSE POSITION | F31: =AA31 -> 32014499 | H31: =AB31 -> SHANKARNARAYANA CASHEWS | I31: IVC | J31: INDIA | K31: =IF(BQ31<>0,BQ31,"") -> MANGALORE, INDIA | L31: =IF(BI31<>0,BI31,"") -> 267490043 | M31: =IF(BJ31<>0,BJ31,"") | N31: =IF(BM31<>0,BM31,"") | O31: =IF(BO31<>0,BO31,"") -> 46202 | P31: =CE31 -> No OBL Yet | R31: =CK31 -> No CERTS Yet | S31: =CP31 | T31: CLARIFICATION ON LATEST SOB | U31: RCVD COUNTERSIGNED + ADVANCE RCVD 26/02-267489943 | X31: 46076 | Y31: 20009554 | Z31: 46074 | AA31: 32014499 | AB31: SHANKARNARAYANA CASHEWS | AC31: April - 26 | AD31: 46142 | AE31: 0.1 | AF31: 100 | AG31: =AF31*(1-AE31) -> 90 | AH31: MT | AI31: 1510 | AJ31: =AI31*AF31 -> 151000 | AK31: CIF | AL31: DP SIGHT | AM31: 0.1 | AN31: 0.9 | AO31: 0 | AP31: 180 DAYS | AQ31: Mr. George | AR31: Mr. Rao | AS31: 5 | AT31: - | AU31: - | AV31: - | AZ31: =AF31*AI31*AM31 -> 15100 | BA31: 46079 | BB31: 46083 | BF31: 46083 | BI31: 267490043 | BK31: 40' | BO31: 46202 | BP31: IVC | BQ31: MANGALORE, INDIA | BX31: =BJ31*AI31 -> 0 | CE31: =IF(J31="VIETNAM", IF(CG31<>"","OBL in Vietnam Office", IF(CF31<>"","OBL in Transit from Vietnam Office", IF(CD31<>0,"OBL In Destination - "&J31, IF(CC31<>0,"OBL in Transit to Destination - "&J31, IF(CB31<>0,"OBL in SIG Office", IF(CA31<>0,"OBL in Transit from Origin to SIG", IF(BZ31<>0,"OBL in Origin - "&I31, IF(BY31<>0,"Draft Rcvd","No OBL Yet")))))))), IF(CO31<>0,"OBL In Destination - "&J31, IF(CM31<>0,"OBL in Transit with Nego Docs - "&J31, IF(CB31<>0,"OBL in SIG Office", IF(CA31<>0,"OBL in Transit from Origin to SIG", IF(BZ31<>0,"OBL in Origin - "&I31, IF(BY31<>0,"Draft Rcvd","No OBL Yet"))))))) -> No OBL Yet | CK31: =IF(CJ31<>0,"CERTS in Destination - "&J31,IF(CI31<>0,"CERT in Transit to -"&J31,IF(CH31<>0,"CERT in Origin - "&I31,IF(CH31="","No CERTS Yet")))) -> No CERTS Yet | CP31: =IF(CO31<>0,"Docs in Buyer's Nego Bank",IF(CN31<>0,"Docs in Transit to Buyer's Nego Bank",IF(CM31<>0,"Docs in Our Nego Bank",IF(CL31="TT PAYMENT","Not Applicable","")))) | CQ31: =(AN31*AI31*BJ31)-AZ31 -> -15100 | CU31: =IF(CS31="","",BJ31-CT31) | CV31: =IF(CS31="","",CU31/BJ31) | CW31: =IF(CS31="","",AZ31+CQ31) | CX31: =IF(CS31="","",BX31*2%) | CY31: =IF(CS31="","",AI31/B31) | DA31: =IF(CS31="","",B31-CZ31) | DC31: =IF(CS31="","",IF(CS31="","",DB31-C31)) | DE31: =IF(CS31="","",10%-DD31) | DF31: =IF(CS31="","",CU31*AI31) | DG31: =IF(CS31="","",IF(DA31>2,2*DA31*CT31*CY31,DA31*CT31*CY31)) | DH31: =IF(CS31="","",IF(DA31>2,2*(DA31-2*CT31*CY31),0)) | DI31: =IF(CS31="","",IF(DC31>0,DC31*0.5*CT31,0)) | DJ31: =IF(CS31="","",IF(DE31<0,DE31*CT31*AI31*1%,0)) | DK31: =IF(CS31="","",SUM(DF31:DJ31)) | DN31: =IF(CS31="","",SUM(DK31:DL31)) | DO31: =IF(CS31="","",BJ31*AI31-DN31) | DP31: =IF(CS31="","",AZ31+CQ31) | DQ31: =IF(CS31="","",IF((DP31-DO31)>0,DP31-DO31,"")) | DR31: =IF(CS31="","",IF((DO31-DP31)>0,(DO31-DP31),"")) | DS31: =IF(CS31="","",IF(DQ31="",H31,"VALENCY")) | DT31: =IF(DN31="","",IF(DN31>0,"CN", "DN")) | DY31: NO VINA/RBS REPORT | EA31: =IF(CS31="","", MIN(0,(IF(DA31>2,2,1)*DA31*CT31*CY31)) ) | EH31: VALENCY IVC | EN31: =EK31*EJ31 -> 0 | EV31: =IF(CR31<>0,"Final Pmt Recd",IF(CM31<>0,"Export Loan",IF(BZ31<>0,"Nego Pending",IF(Z31<>0,"Yet to load","Yet to load")))) -> Yet to load | EX31: =EW31/BJ31 -> #DIV/0! | EY31: Freight paid by origin | FD31: =FC31*BJ31 -> 0 | FL31: =IFERROR(EZ31-BY31,"") -> 0 | FM31: =IFERROR(BM31-FB31,"") -> 0 | FS31: =Y31 -> 20009554 | FT31: =AA31 -> 32014499
A32: =IF(DZ32="CLOSE","Trade closed",IF(DZ32="PMT Pending","FNF Settlement is Due",IF(CS32<>0,"FNF Reconcillation Onging",IF(CR32<>0," Final Pmt Recd , FNF Pending",IF(CM32<>0,"Exp Dox Presented to Bank, Pmt Pending",IF(BZ32<>0,"OBL Scan Recd, Nego Pending",IF(BM32<>0,"Sailed, OBL & Certs Pending",IF(BJ32<>0,"Stuffed, Yet to Sail",IF(BB32<>0,"SI Sent, Shipment Awaited",IF(BA32<>0,"Advance Rcvd, SI Pending",IF(Z32<>0,"SC Raised, Advance Pending",IF(X32<>0,"Deal Ticket Rcvd SC Pending", "Entry Pending")))))))))))) -> Final Pmt Recd , FNF Pending | B32: 47 | C32: 185 | D32: RCN | E32: =IF(AND(LEFT(TRIM(AA32&""),1)="3",BI32<>""),"CLOSE POSITION", IF(AND(LEFT(TRIM(AA32&""),1)="3",BI32=""),"SHORT POSITION", IF(AND(LEFT(TRIM(AA32&""),1)<>"3",BI32<>""),"LONG POSITION","ENTRY PENDING"))) -> CLOSE POSITION | F32: =AA32 -> 32015281-2 | H32: =AB32 -> Valency Agro (Processing) | I32: GHANA | J32: INDIA | K32: =IF(BQ32<>0,BQ32,"") -> MANGALORE, INDIA | L32: =IF(BI32<>0,BI32,"") -> 267377584 | M32: =IF(BJ32<>0,BJ32,"") -> 177.52 | N32: =IF(BM32<>0,BM32,"") -> 46095 | O32: =IF(BO32<>0,BO32,"") -> 46160 | P32: =CE32 -> OBL In Destination - INDIA | R32: =CK32 -> CERTS in Destination - INDIA | S32: =CP32 -> Docs in Buyer's Nego Bank | T32: =IFERROR(_xlfn.XLOOKUP(F32, '[2]Data 2026'!$H$12:$H$111, '[2]Data 2026'!$CL$12:$CL$111),"") | U32: PAYMENT RCVD 14/05 | X32: 46093 | Y32: 20009747 | Z32: =X32 -> 46093 | AA32: 32015281-2 | AB32: Valency Agro (Processing) | AC32: March - 26 | AD32: 46112 | AE32: 0.1 | AF32: 175 | AG32: =AF32*(1-AE32) -> 157.5 | AH32: MT | AI32: 1585 | AJ32: =AI32*AF32 -> 277375 | AK32: CIF | AL32: DP SIGHT | AM32: 0 | AN32: 1 | AO32: 0 | AP32: 180 DAYS | AQ32: Mr. Naveen | AR32: Direct | AT32: - | AU32: - | AV32: - | AZ32: =AF32*AI32*AM32 -> 0 | BA32: =Z32 -> 46093 | BB32: 46078 | BF32: 46078 | BI32: 267377584 | BJ32: 177.52 | BK32: 40' | BL32: 7 | BM32: 46095 | BO32: 46160 | BP32: GHANA | BQ32: MANGALORE, INDIA | BR32: MAERSK LINE | BT32: RDO GRACE | BU32: 611E | BV32: 90082895 | BX32: =BJ32*AI32 -> 281369.2 | CE32: =IF(J32="VIETNAM", IF(CG32<>"","OBL in Vietnam Office", IF(CF32<>"","OBL in Transit from Vietnam Office", IF(CD32<>0,"OBL In Destination - "&J32, IF(CC32<>0,"OBL in Transit to Destination - "&J32, IF(CB32<>0,"OBL in SIG Office", IF(CA32<>0,"OBL in Transit from Origin to SIG", IF(BZ32<>0,"OBL in Origin - "&I32, IF(BY32<>0,"Draft Rcvd","No OBL Yet")))))))), IF(CO32<>0,"OBL In Destination - "&J32, IF(CM32<>0,"OBL in Transit with Nego Docs - "&J32, IF(CB32<>0,"OBL in SIG Office", IF(CA32<>0,"OBL in Transit from Origin to SIG", IF(BZ32<>0,"OBL in Origin - "&I32, IF(BY32<>0,"Draft Rcvd","No OBL Yet"))))))) -> OBL In Destination - INDIA | CH32: 4-25 | CI32: 2363213101 | CJ32: 46146 | CK32: =IF(CJ32<>0,"CERTS in Destination - "&J32,IF(CI32<>0,"CERT in Transit to -"&J32,IF(CH32<>0,"CERT in Origin - "&I32,IF(CH32="","No CERTS Yet")))) -> CERTS in Destination - INDIA | CL32: ICICI BANK | CM32: 46119 | CN32: 2365151644 | CO32: 46155 | CP32: =IF(CO32<>0,"Docs in Buyer's Nego Bank",IF(CN32<>0,"Docs in Transit to Buyer's Nego Bank",IF(CM32<>0,"Docs in Our Nego Bank",IF(CL32="TT PAYMENT","Not Applicable","")))) -> Docs in Buyer's Nego Bank | CQ32: =(AN32*AI32*BJ32)-AZ32 -> 281369.2 | CR32: 46156 | CU32: =IF(CS32="","",BJ32-CT32) | CV32: =IF(CS32="","",CU32/BJ32) | CW32: =IF(CS32="","",AZ32+CQ32) | CX32: =IF(CS32="","",BX32*2%) | CY32: =IF(CS32="","",AI32/B32) | DA32: =IF(CS32="","",B32-CZ32) | DC32: =IF(CS32="","",IF(CS32="","",DB32-C32)) | DE32: =IF(CS32="","",10%-DD32) | DF32: =IF(CS32="","",CU32*AI32) | DG32: =IF(CS32="","",IF(DA32>2,2*DA32*CT32*CY32,DA32*CT32*CY32)) | DH32: =IF(CS32="","",IF(DA32>2,2*(DA32-2*CT32*CY32),0)) | DI32: =IF(CS32="","",IF(DC32>0,DC32*0.5*CT32,0)) | DJ32: =IF(CS32="","",IF(DE32<0,DE32*CT32*AI32*1%,0)) | DK32: =IF(CS32="","",SUM(DF32:DJ32)) | DN32: =IF(CS32="","",SUM(DK32:DL32)) | DO32: =IF(CS32="","",BJ32*AI32-DN32) | DP32: =IF(CS32="","",AZ32+CQ32) | DQ32: =IF(CS32="","",IF((DP32-DO32)>0,DP32-DO32,"")) | DR32: =IF(CS32="","",IF((DO32-DP32)>0,(DO32-DP32),"")) | DS32: =IF(CS32="","",IF(DQ32="",H32,"VALENCY")) | DT32: =IF(DN32="","",IF(DN32>0,"CN", "DN")) | DY32: NO VINA/RBS REPORT | EA32: =IF(CS32="","", MIN(0,(IF(DA32>2,2,1)*DA32*CT32*CY32)) ) | EH32: Valora Exim | EI32: FOB | EN32: =EK32*EJ32 -> 0 | EV32: =IF(CR32<>0,"Final Pmt Recd",IF(CM32<>0,"Export Loan",IF(BZ32<>0,"Nego Pending",IF(Z32<>0,"Yet to load","Yet to load")))) -> Final Pmt Recd | EX32: =EW32/BJ32 -> 0 | EY32: Freight paid by origin | FD32: =FC32*BJ32 -> 0 | FL32: =IFERROR(EZ32-BY32,"") -> 0 | FM32: =IFERROR(BM32-FB32,"") -> 46095 | FS32: =Y32 -> 20009747 | FT32: =AA32 -> 32015281-2 | GD32: 90082895 | GF32: done
A33: =IF(DZ33="CLOSE","Trade closed",IF(DZ33="PMT Pending","FNF Settlement is Due",IF(CS33<>0,"FNF Reconcillation Onging",IF(CR33<>0," Final Pmt Recd , FNF Pending",IF(CM33<>0,"Exp Dox Presented to Bank, Pmt Pending",IF(BZ33<>0,"OBL Scan Recd, Nego Pending",IF(BM33<>0,"Sailed, OBL & Certs Pending",IF(BJ33<>0,"Stuffed, Yet to Sail",IF(BB33<>0,"SI Sent, Shipment Awaited",IF(BA33<>0,"Advance Rcvd, SI Pending",IF(Z33<>0,"SC Raised, Advance Pending",IF(X33<>0,"Deal Ticket Rcvd SC Pending", "Entry Pending")))))))))))) -> SI Sent, Shipment Awaited | B33: 48 | C33: 200 | D33: RCN | E33: =IF(AND(LEFT(TRIM(AA33&""),1)="3",BI33<>""),"CLOSE POSITION", IF(AND(LEFT(TRIM(AA33&""),1)="3",BI33=""),"SHORT POSITION", IF(AND(LEFT(TRIM(AA33&""),1)<>"3",BI33<>""),"LONG POSITION","ENTRY PENDING"))) -> CLOSE POSITION | F33: =AA33 -> 32014588 | H33: =AB33 -> SHREE KRISHNAKRUPA CASHEWS PVT LTD | I33: IVC | J33: INDIA | K33: =IF(BQ33<>0,BQ33,"") -> MANGALORE, INDIA | L33: =IF(BI33<>0,BI33,"") -> 267490043 | M33: =IF(BJ33<>0,BJ33,"") | N33: =IF(BM33<>0,BM33,"") | O33: =IF(BO33<>0,BO33,"") | P33: =CE33 -> No OBL Yet | R33: =CK33 -> No CERTS Yet | S33: =CP33 | T33: CLARIFICATION ON LATEST SOB | U33: ADVANCE RCVD 02/03-267490043 | X33: 46076 | Y33: 20009596 | Z33: 46076 | AA33: 32014588 | AB33: SHREE KRISHNAKRUPA CASHEWS PVT LTD | AC33: April - 26 | AD33: 46142 | AE33: 0.1 | AF33: 100 | AG33: =AF33*(1-AE33) -> 90 | AH33: MT | AI33: 1510 | AJ33: =AI33*AF33 -> 151000 | AK33: CIF | AL33: DP SIGHT | AM33: 0.1 | AN33: 0.9 | AO33: 0 | AP33: 180 DAYS | AQ33: Mr. George | AR33: Mr. Rao | AS33: 5 | AT33: - | AU33: - | AV33: - | AZ33: =AF33*AI33*AM33 -> 15100 | BA33: 46083 | BB33: 46083 | BF33: 46083 | BI33: 267490043 | BK33: 40' | BP33: IVC | BQ33: MANGALORE, INDIA | BX33: =BJ33*AI33 -> 0 | CE33: =IF(J33="VIETNAM", IF(CG33<>"","OBL in Vietnam Office", IF(CF33<>"","OBL in Transit from Vietnam Office", IF(CD33<>0,"OBL In Destination - "&J33, IF(CC33<>0,"OBL in Transit to Destination - "&J33, IF(CB33<>0,"OBL in SIG Office", IF(CA33<>0,"OBL in Transit from Origin to SIG", IF(BZ33<>0,"OBL in Origin - "&I33, IF(BY33<>0,"Draft Rcvd","No OBL Yet")))))))), IF(CO33<>0,"OBL In Destination - "&J33, IF(CM33<>0,"OBL in Transit with Nego Docs - "&J33, IF(CB33<>0,"OBL in SIG Office", IF(CA33<>0,"OBL in Transit from Origin to SIG", IF(BZ33<>0,"OBL in Origin - "&I33, IF(BY33<>0,"Draft Rcvd","No OBL Yet"))))))) -> No OBL Yet | CK33: =IF(CJ33<>0,"CERTS in Destination - "&J33,IF(CI33<>0,"CERT in Transit to -"&J33,IF(CH33<>0,"CERT in Origin - "&I33,IF(CH33="","No CERTS Yet")))) -> No CERTS Yet | CP33: =IF(CO33<>0,"Docs in Buyer's Nego Bank",IF(CN33<>0,"Docs in Transit to Buyer's Nego Bank",IF(CM33<>0,"Docs in Our Nego Bank",IF(CL33="TT PAYMENT","Not Applicable","")))) | CQ33: =(AN33*AI33*BJ33)-AZ33 -> -15100 | CU33: =IF(CS33="","",BJ33-CT33) | CV33: =IF(CS33="","",CU33/BJ33) | CW33: =IF(CS33="","",AZ33+CQ33) | CX33: =IF(CS33="","",BX33*2%) | CY33: =IF(CS33="","",AI33/B33) | DA33: =IF(CS33="","",B33-CZ33) | DC33: =IF(CS33="","",IF(CS33="","",DB33-C33)) | DE33: =IF(CS33="","",10%-DD33) | DF33: =IF(CS33="","",CU33*AI33) | DG33: =IF(CS33="","",IF(DA33>2,2*DA33*CT33*CY33,DA33*CT33*CY33)) | DH33: =IF(CS33="","",IF(DA33>2,2*(DA33-2*CT33*CY33),0)) | DI33: =IF(CS33="","",IF(DC33>0,DC33*0.5*CT33,0)) | DJ33: =IF(CS33="","",IF(DE33<0,DE33*CT33*AI33*1%,0)) | DK33: =IF(CS33="","",SUM(DF33:DJ33)) | DN33: =IF(CS33="","",SUM(DK33:DL33)) | DO33: =IF(CS33="","",BJ33*AI33-DN33) | DP33: =IF(CS33="","",AZ33+CQ33) | DQ33: =IF(CS33="","",IF((DP33-DO33)>0,DP33-DO33,"")) | DR33: =IF(CS33="","",IF((DO33-DP33)>0,(DO33-DP33),"")) | DS33: =IF(CS33="","",IF(DQ33="",H33,"VALENCY")) | DT33: =IF(DN33="","",IF(DN33>0,"CN", "DN")) | DY33: NO VINA/RBS REPORT | EA33: =IF(CS33="","", MIN(0,(IF(DA33>2,2,1)*DA33*CT33*CY33)) ) | EH33: VALENCY IVC | EN33: =EK33*EJ33 -> 0 | EV33: =IF(CR33<>0,"Final Pmt Recd",IF(CM33<>0,"Export Loan",IF(BZ33<>0,"Nego Pending",IF(Z33<>0,"Yet to load","Yet to load")))) -> Yet to load | EX33: =EW33/BJ33 -> #DIV/0! | EY33: Freight paid by origin | FD33: =FC33*BJ33 -> 0 | FL33: =IFERROR(EZ33-BY33,"") -> 0 | FM33: =IFERROR(BM33-FB33,"") -> 0 | FS33: =Y33 -> 20009596 | FT33: =AA33 -> 32014588
A34: =IF(DZ34="CLOSE","Trade closed",IF(DZ34="PMT Pending","FNF Settlement is Due",IF(CS34<>0,"FNF Reconcillation Onging",IF(CR34<>0," Final Pmt Recd , FNF Pending",IF(CM34<>0,"Exp Dox Presented to Bank, Pmt Pending",IF(BZ34<>0,"OBL Scan Recd, Nego Pending",IF(BM34<>0,"Sailed, OBL & Certs Pending",IF(BJ34<>0,"Stuffed, Yet to Sail",IF(BB34<>0,"SI Sent, Shipment Awaited",IF(BA34<>0,"Advance Rcvd, SI Pending",IF(Z34<>0,"SC Raised, Advance Pending",IF(X34<>0,"Deal Ticket Rcvd SC Pending", "Entry Pending")))))))))))) -> SI Sent, Shipment Awaited | B34: 49 | C34: 200 | D34: RCN | E34: =IF(AND(LEFT(TRIM(AA34&""),1)="3",BI34<>""),"CLOSE POSITION", IF(AND(LEFT(TRIM(AA34&""),1)="3",BI34=""),"SHORT POSITION", IF(AND(LEFT(TRIM(AA34&""),1)<>"3",BI34<>""),"LONG POSITION","ENTRY PENDING"))) -> SHORT POSITION | F34: =AA34 -> 32014455 | H34: =AB34 -> SREE DEVI CASHEW INDUSTRIES | I34: IVC | J34: INDIA | K34: =IF(BQ34<>0,BQ34,"") -> MANGALORE, INDIA | L34: =IF(BI34<>0,BI34,"") | M34: =IF(BJ34<>0,BJ34,"") | N34: =IF(BM34<>0,BM34,"") | O34: =IF(BO34<>0,BO34,"") | P34: =CE34 -> No OBL Yet | R34: =CK34 -> No CERTS Yet | S34: =CP34 | T34: MEARSK CUANZA, ETD: 30/5 | U34: RCVD COUNTERSIGNED-BUYER WANTS TO DELAY THE SHIPMENT-267489622 & 267489622-1 | X34: 46069 | Y34: 20009505 | Z34: 46069 | AA34: 32014455 | AB34: SREE DEVI CASHEW INDUSTRIES | AC34: April - 26 | AD34: 46142 | AE34: 0.1 | AF34: 200 | AG34: =AF34*(1-AE34) -> 180 | AH34: MT | AI34: 1565 | AJ34: =AI34*AF34 -> 313000 | AK34: CIF | AL34: DP SIGHT | AM34: 0 | AN34: 1 | AO34: 0 | AP34: 180 DAYS | AQ34: Mr. George | AR34: Mr. Rao | AS34: 5 | AT34: - | AU34: - | AV34: - | AZ34: =AF34*AI34*AM34 -> 0 | BA34: 46073 | BB34: 46083 | BF34: 46083 | BK34: 40' | BP34: IVC | BQ34: MANGALORE, INDIA | BR34: MAERSK LINE | BX34: =BJ34*AI34 -> 0 | CE34: =IF(J34="VIETNAM", IF(CG34<>"","OBL in Vietnam Office", IF(CF34<>"","OBL in Transit from Vietnam Office", IF(CD34<>0,"OBL In Destination - "&J34, IF(CC34<>0,"OBL in Transit to Destination - "&J34, IF(CB34<>0,"OBL in SIG Office", IF(CA34<>0,"OBL in Transit from Origin to SIG", IF(BZ34<>0,"OBL in Origin - "&I34, IF(BY34<>0,"Draft Rcvd","No OBL Yet")))))))), IF(CO34<>0,"OBL In Destination - "&J34, IF(CM34<>0,"OBL in Transit with Nego Docs - "&J34, IF(CB34<>0,"OBL in SIG Office", IF(CA34<>0,"OBL in Transit from Origin to SIG", IF(BZ34<>0,"OBL in Origin - "&I34, IF(BY34<>0,"Draft Rcvd","No OBL Yet"))))))) -> No OBL Yet | CK34: =IF(CJ34<>0,"CERTS in Destination - "&J34,IF(CI34<>0,"CERT in Transit to -"&J34,IF(CH34<>0,"CERT in Origin - "&I34,IF(CH34="","No CERTS Yet")))) -> No CERTS Yet | CP34: =IF(CO34<>0,"Docs in Buyer's Nego Bank",IF(CN34<>0,"Docs in Transit to Buyer's Nego Bank",IF(CM34<>0,"Docs in Our Nego Bank",IF(CL34="TT PAYMENT","Not Applicable","")))) | CQ34: =(AN34*AI34*BJ34)-AZ34 -> 0 | CU34: =IF(CS34="","",BJ34-CT34) | CV34: =IF(CS34="","",CU34/BJ34) | CW34: =IF(CS34="","",AZ34+CQ34) | CX34: =IF(CS34="","",BX34*2%) | CY34: =IF(CS34="","",AI34/B34) | DA34: =IF(CS34="","",B34-CZ34) | DC34: =IF(CS34="","",IF(CS34="","",DB34-C34)) | DE34: =IF(CS34="","",10%-DD34) | DF34: =IF(CS34="","",CU34*AI34) | DG34: =IF(CS34="","",IF(DA34>2,2*DA34*CT34*CY34,DA34*CT34*CY34)) | DH34: =IF(CS34="","",IF(DA34>2,2*(DA34-2*CT34*CY34),0)) | DI34: =IF(CS34="","",IF(DC34>0,DC34*0.5*CT34,0)) | DJ34: =IF(CS34="","",IF(DE34<0,DE34*CT34*AI34*1%,0)) | DK34: =IF(CS34="","",SUM(DF34:DJ34)) | DN34: =IF(CS34="","",SUM(DK34:DL34)) | DO34: =IF(CS34="","",BJ34*AI34-DN34) | DP34: =IF(CS34="","",AZ34+CQ34) | DQ34: =IF(CS34="","",IF((DP34-DO34)>0,DP34-DO34,"")) | DR34: =IF(CS34="","",IF((DO34-DP34)>0,(DO34-DP34),"")) | DS34: =IF(CS34="","",IF(DQ34="",H34,"VALENCY")) | DT34: =IF(DN34="","",IF(DN34>0,"CN", "DN")) | DY34: NO VINA/RBS REPORT | EA34: =IF(CS34="","", MIN(0,(IF(DA34>2,2,1)*DA34*CT34*CY34)) ) | EH34: VALENCY IVC | EI34: FOB | EN34: =EK34*EJ34 -> 0 | EV34: =IF(CR34<>0,"Final Pmt Recd",IF(CM34<>0,"Export Loan",IF(BZ34<>0,"Nego Pending",IF(Z34<>0,"Yet to load","Yet to load")))) -> Yet to load | EX34: =EW34/BJ34 -> #DIV/0! | EY34: Freight paid by origin | FD34: =FC34*BJ34 -> 0 | FL34: =IFERROR(EZ34-BY34,"") -> 0 | FM34: =IFERROR(BM34-FB34,"") -> 0 | FS34: =Y34 -> 20009505 | FT34: =AA34 -> 32014455
A35: =IF(DZ35="CLOSE","Trade closed",IF(DZ35="PMT Pending","FNF Settlement is Due",IF(CS35<>0,"FNF Reconcillation Onging",IF(CR35<>0," Final Pmt Recd , FNF Pending",IF(CM35<>0,"Exp Dox Presented to Bank, Pmt Pending",IF(BZ35<>0,"OBL Scan Recd, Nego Pending",IF(BM35<>0,"Sailed, OBL & Certs Pending",IF(BJ35<>0,"Stuffed, Yet to Sail",IF(BB35<>0,"SI Sent, Shipment Awaited",IF(BA35<>0,"Advance Rcvd, SI Pending",IF(Z35<>0,"SC Raised, Advance Pending",IF(X35<>0,"Deal Ticket Rcvd SC Pending", "Entry Pending")))))))))))) -> SI Sent, Shipment Awaited | B35: 49 | C35: 200 | D35: RCN | E35: =IF(AND(LEFT(TRIM(AA35&""),1)="3",BI35<>""),"CLOSE POSITION", IF(AND(LEFT(TRIM(AA35&""),1)="3",BI35=""),"SHORT POSITION", IF(AND(LEFT(TRIM(AA35&""),1)<>"3",BI35<>""),"LONG POSITION","ENTRY PENDING"))) -> SHORT POSITION | F35: =AA35 -> 32014486 | H35: =AB35 -> SRI MAHAGANAPATHI CASHEW INDUSTRIES | I35: IVC | J35: INDIA | K35: =IF(BQ35<>0,BQ35,"") -> MANGALORE, INDIA | L35: =IF(BI35<>0,BI35,"") | M35: =IF(BJ35<>0,BJ35,"") | N35: =IF(BM35<>0,BM35,"") | O35: =IF(BO35<>0,BO35,"") | P35: =CE35 -> No OBL Yet | R35: =CK35 -> No CERTS Yet | S35: =CP35 | T35: CLARIFICATION ON LATEST SOB | U35: ADVANCE RCVD 18/03-267489832 | X35: 46073 | Y35: 20009539 | Z35: 46073 | AA35: 32014486 | AB35: SRI MAHAGANAPATHI CASHEW INDUSTRIES | AC35: April - 26 | AD35: 46142 | AE35: 0.1 | AF35: 100 | AG35: =AF35*(1-AE35) -> 90 | AH35: MT | AI35: 1545 | AJ35: =AI35*AF35 -> 154500 | AK35: CIF | AL35: DP SIGHT | AM35: 0.1 | AN35: 0.9 | AO35: 0 | AP35: 180 DAYS | AQ35: Mr. George | AR35: Mr. Rao | AS35: 5 | AT35: - | AU35: - | AV35: - | AZ35: =AF35*AI35*AM35 -> 15450 | BA35: 46099 | BB35: 46083 | BF35: 46083 | BK35: 40' | BP35: IVC | BQ35: MANGALORE, INDIA | BX35: =BJ35*AI35 -> 0 | CE35: =IF(J35="VIETNAM", IF(CG35<>"","OBL in Vietnam Office", IF(CF35<>"","OBL in Transit from Vietnam Office", IF(CD35<>0,"OBL In Destination - "&J35, IF(CC35<>0,"OBL in Transit to Destination - "&J35, IF(CB35<>0,"OBL in SIG Office", IF(CA35<>0,"OBL in Transit from Origin to SIG", IF(BZ35<>0,"OBL in Origin - "&I35, IF(BY35<>0,"Draft Rcvd","No OBL Yet")))))))), IF(CO35<>0,"OBL In Destination - "&J35, IF(CM35<>0,"OBL in Transit with Nego Docs - "&J35, IF(CB35<>0,"OBL in SIG Office", IF(CA35<>0,"OBL in Transit from Origin to SIG", IF(BZ35<>0,"OBL in Origin - "&I35, IF(BY35<>0,"Draft Rcvd","No OBL Yet"))))))) -> No OBL Yet | CK35: =IF(CJ35<>0,"CERTS in Destination - "&J35,IF(CI35<>0,"CERT in Transit to -"&J35,IF(CH35<>0,"CERT in Origin - "&I35,IF(CH35="","No CERTS Yet")))) -> No CERTS Yet | CP35: =IF(CO35<>0,"Docs in Buyer's Nego Bank",IF(CN35<>0,"Docs in Transit to Buyer's Nego Bank",IF(CM35<>0,"Docs in Our Nego Bank",IF(CL35="TT PAYMENT","Not Applicable","")))) | CQ35: =(AN35*AI35*BJ35)-AZ35 -> -15450 | CU35: =IF(CS35="","",BJ35-CT35) | CV35: =IF(CS35="","",CU35/BJ35) | CW35: =IF(CS35="","",AZ35+CQ35) | CX35: =IF(CS35="","",BX35*2%) | CY35: =IF(CS35="","",AI35/B35) | DA35: =IF(CS35="","",B35-CZ35) | DC35: =IF(CS35="","",IF(CS35="","",DB35-C35)) | DE35: =IF(CS35="","",10%-DD35) | DF35: =IF(CS35="","",CU35*AI35) | DG35: =IF(CS35="","",IF(DA35>2,2*DA35*CT35*CY35,DA35*CT35*CY35)) | DH35: =IF(CS35="","",IF(DA35>2,2*(DA35-2*CT35*CY35),0)) | DI35: =IF(CS35="","",IF(DC35>0,DC35*0.5*CT35,0)) | DJ35: =IF(CS35="","",IF(DE35<0,DE35*CT35*AI35*1%,0)) | DK35: =IF(CS35="","",SUM(DF35:DJ35)) | DN35: =IF(CS35="","",SUM(DK35:DL35)) | DO35: =IF(CS35="","",BJ35*AI35-DN35) | DP35: =IF(CS35="","",AZ35+CQ35) | DQ35: =IF(CS35="","",IF((DP35-DO35)>0,DP35-DO35,"")) | DR35: =IF(CS35="","",IF((DO35-DP35)>0,(DO35-DP35),"")) | DS35: =IF(CS35="","",IF(DQ35="",H35,"VALENCY")) | DT35: =IF(DN35="","",IF(DN35>0,"CN", "DN")) | DY35: NO VINA/RBS REPORT | EA35: =IF(CS35="","", MIN(0,(IF(DA35>2,2,1)*DA35*CT35*CY35)) ) | EH35: VALENCY IVC | EN35: =EK35*EJ35 -> 0 | EV35: =IF(CR35<>0,"Final Pmt Recd",IF(CM35<>0,"Export Loan",IF(BZ35<>0,"Nego Pending",IF(Z35<>0,"Yet to load","Yet to load")))) -> Yet to load | EX35: =EW35/BJ35 -> #DIV/0! | EY35: Freight paid by origin | FD35: =FC35*BJ35 -> 0 | FL35: =IFERROR(EZ35-BY35,"") -> 0 | FM35: =IFERROR(BM35-FB35,"") -> 0 | FS35: =Y35 -> 20009539 | FT35: =AA35 -> 32014486
A36: =IF(DZ36="CLOSE","Trade closed",IF(DZ36="PMT Pending","FNF Settlement is Due",IF(CS36<>0,"FNF Reconcillation Onging",IF(CR36<>0," Final Pmt Recd , FNF Pending",IF(CM36<>0,"Exp Dox Presented to Bank, Pmt Pending",IF(BZ36<>0,"OBL Scan Recd, Nego Pending",IF(BM36<>0,"Sailed, OBL & Certs Pending",IF(BJ36<>0,"Stuffed, Yet to Sail",IF(BB36<>0,"SI Sent, Shipment Awaited",IF(BA36<>0,"Advance Rcvd, SI Pending",IF(Z36<>0,"SC Raised, Advance Pending",IF(X36<>0,"Deal Ticket Rcvd SC Pending", "Entry Pending")))))))))))) -> Sailed, OBL & Certs Pending | B36: 46 | C36: 200 | D36: RCN | E36: =IF(AND(LEFT(TRIM(AA36&""),1)="3",BI36<>""),"CLOSE POSITION", IF(AND(LEFT(TRIM(AA36&""),1)="3",BI36=""),"SHORT POSITION", IF(AND(LEFT(TRIM(AA36&""),1)<>"3",BI36<>""),"LONG POSITION","ENTRY PENDING"))) -> CLOSE POSITION | F36: =AA36 -> 32016289-1 | H36: =AB36 -> VIET PHI AGRICULTURE JOINT STOCK COMPANY | I36: IVC | J36: VIETNAM | K36: =IF(BQ36<>0,BQ36,"") -> HCMC, VIETNAM | L36: =IF(BI36<>0,BI36,"") -> HLCUAB1260401247 | M36: =IF(BJ36<>0,BJ36,"") -> 248.33 | N36: =IF(BM36<>0,BM36,"") -> 46163 | O36: =IF(BO36<>0,BO36,"") -> 46208 | P36: =CE36 -> No OBL Yet | Q36: TPSCR26010661 | R36: =CK36 -> No CERTS Yet | S36: =CP36 | T36: DRAFT BL RCVD 20/5 | U36: DRAFT BL RCVD 20/5,DRAFT HBL SENT TO BUYER 20/5 | W36: NTT - OBL PRINTING ISSUE IN SIG , ETA 5/7 | X36: 46126 | Y36: 20010094 | Z36: 46126 | AA36: 32016289-1 | AB36: VIET PHI AGRICULTURE JOINT STOCK COMPANY | AC36: 46168 | AD36: 46173 | AE36: 0.05 | AF36: 250 | AG36: =AF36*(1-AE36) -> 237.5 | AH36: MT | AI36: 1520 | AJ36: =AI36*AF36 -> 380000 | AK36: CFR | AL36: DP SIGHT | AM36: 0.1 | AN36: 0.88 | AO36: 0.02 | AP36: 180 DAYS | AQ36: Mr. Prashant | AR36: Direct | AT36: - | AU36: - | AV36: - | AY36: 46129 | AZ36: =AF36*AI36*AM36 -> 38000 | BA36: 46135 | BB36: 46129 | BI36: HLCUAB1260401247 | BJ36: 248.33 | BK36: 40' | BL36: 10 | BM36: 46163 | BO36: 46208 | BP36: IVC | BQ36: HCMC, VIETNAM | BR36: HAPAG LLOYD | BT36: ACHELOOS | BX36: =BJ36*AI36 -> 377461.6 | CE36: =IF(J36="VIETNAM", IF(CG36<>"","OBL in Vietnam Office", IF(CF36<>"","OBL in Transit from Vietnam Office", IF(CD36<>0,"OBL In Destination - "&J36, IF(CC36<>0,"OBL in Transit to Destination - "&J36, IF(CB36<>0,"OBL in SIG Office", IF(CA36<>0,"OBL in Transit from Origin to SIG", IF(BZ36<>0,"OBL in Origin - "&I36, IF(BY36<>0,"Draft Rcvd","No OBL Yet")))))))), IF(CO36<>0,"OBL In Destination - "&J36, IF(CM36<>0,"OBL in Transit with Nego Docs - "&J36, IF(CB36<>0,"OBL in SIG Office", IF(CA36<>0,"OBL in Transit from Origin to SIG", IF(BZ36<>0,"OBL in Origin - "&I36, IF(BY36<>0,"Draft Rcvd","No OBL Yet"))))))) -> No OBL Yet | CK36: =IF(CJ36<>0,"CERTS in Destination - "&J36,IF(CI36<>0,"CERT in Transit to -"&J36,IF(CH36<>0,"CERT in Origin - "&I36,IF(CH36="","No CERTS Yet")))) -> No CERTS Yet | CP36: =IF(CO36<>0,"Docs in Buyer's Bank",IF(CN36<>0,"Docs in Transit to Buyer's Bank",IF(CM36<>0,"Docs in Our Bank",IF(CL36="TT PAYMENT","Not Applicable","")))) | CQ36: =(AN36*AI36*BJ36)-AZ36 -> 294166.21 | CU36: =IF(CS36="","",BJ36-CT36) | CV36: =IF(CS36="","",CU36/BJ36) | CW36: =IF(CS36="","",AZ36+CQ36) | CX36: =IF(CS36="","",BX36*2%) | CY36: =IF(CS36="","",AI36/B36) | DA36: =IF(CS36="","",B36-CZ36) | DC36: =IF(CS36="","",IF(CS36="","",DB36-C36)) | DE36: =IF(CS36="","",10%-DD36) | DF36: =IF(CS36="","",CU36*AI36) | DG36: =IF(CS36="","",IF(DA36>2,2*DA36*CT36*CY36,DA36*CT36*CY36)) | DH36: =IF(CS36="","",IF(DA36>2,2*(DA36-2*CT36*CY36),0)) | DI36: =IF(CS36="","",IF(DC36>0,DC36*0.5*CT36,0)) | DJ36: =IF(CS36="","",IF(DE36<0,DE36*CT36*AI36*10%,0)) | DK36: =IF(CS36="","",SUM(DF36:DJ36)) | DN36: =IF(CS36="","",SUM(DK36:DL36)) | DO36: =IF(CS36="","",BJ36*AI36-DN36) | DP36: =IF(CS36="","",AZ36+CQ36) | DQ36: =IF(CS36="","",IF((DP36-DO36)>0,DP36-DO36,"")) | DR36: =IF(CS36="","",IF((DO36-DP36)>0,(DO36-DP36),"")) | DS36: =IF(CS36="","",IF(DQ36="",H36,"VALENCY")) | DT36: =IF(DN36="","",IF(DN36>0,"CN", "DN")) | DY36: NO VINA/RBS REPORT | EA36: =IF(CS36="","", MIN(0,(IF(DA36>2,2,1)*DA36*CT36*CY36)) ) | EH36: VALENCY IVC | EN36: =EK36*EJ36 -> 0 | EV36: =IF(CR36<>0,"Final Pmt Recd",IF(CM36<>0,"Export Loan",IF(BZ36<>0,"Nego Pending",IF(Z36<>0,"Yet to load","Yet to load")))) -> Yet to load | EX36: =EW36/BJ36 -> 0 | EY36: Freight paid by origin | FD36: =FC36*BJ36 -> 0 | FL36: =IFERROR(EZ36-BY36,"") -> 0 | FM36: =IFERROR(BM36-FB36,"") -> 46163 | FS36: =Y36 -> 20010094 | FT36: =AA36 -> 32016289-1
A37: =IF(DZ37="CLOSE","Trade closed",IF(DZ37="PMT Pending","FNF Settlement is Due",IF(CS37<>0,"FNF Reconcillation Onging",IF(CR37<>0," Final Pmt Recd , FNF Pending",IF(CM37<>0,"Exp Dox Presented to Bank, Pmt Pending",IF(BZ37<>0,"OBL Scan Recd, Nego Pending",IF(BM37<>0,"Sailed, OBL & Certs Pending",IF(BJ37<>0,"Stuffed, Yet to Sail",IF(BB37<>0,"SI Sent, Shipment Awaited",IF(BA37<>0,"Advance Rcvd, SI Pending",IF(Z37<>0,"SC Raised, Advance Pending",IF(X37<>0,"Deal Ticket Rcvd SC Pending", "Entry Pending")))))))))))) -> Sailed, OBL & Certs Pending | B37: 46 | C37: 200 | D37: RCN | E37: =IF(AND(LEFT(TRIM(AA37&""),1)="3",BI37<>""),"CLOSE POSITION", IF(AND(LEFT(TRIM(AA37&""),1)="3",BI37=""),"SHORT POSITION", IF(AND(LEFT(TRIM(AA37&""),1)<>"3",BI37<>""),"LONG POSITION","ENTRY PENDING"))) -> CLOSE POSITION | F37: =AA37 -> 32016289-2 | H37: =AB37 -> VIET PHI AGRICULTURE JOINT STOCK COMPANY | I37: IVC | J37: VIETNAM | K37: =IF(BQ37<>0,BQ37,"") -> HCMC, VIETNAM | L37: =IF(BI37<>0,BI37,"") -> HLCUAB1260401258 | M37: =IF(BJ37<>0,BJ37,"") -> 252.18 | N37: =IF(BM37<>0,BM37,"") -> 46163 | O37: =IF(BO37<>0,BO37,"") -> 46208 | P37: =CE37 -> No OBL Yet | Q37: TPSCR26010664 | R37: =CK37 -> No CERTS Yet | S37: =CP37 | T37: DRAFT BL RCVD 20/5 | U37: DRAFT BL RCVD 20/5,DRAFT HBL REQUEST SENT 21/5 | W37: NTT - OBL PRINTING ISSUE IN SIG , ETA 5/7 | X37: 46126 | Y37: 20010094 | Z37: 46126 | AA37: 32016289-2 | AB37: VIET PHI AGRICULTURE JOINT STOCK COMPANY | AC37: 46168 | AD37: 46173 | AE37: 0.05 | AF37: 250 | AG37: =AF37*(1-AE37) -> 237.5 | AH37: MT | AI37: 1520 | AJ37: =AI37*AF37 -> 380000 | AK37: CFR | AL37: DP SIGHT | AM37: 0.1 | AN37: 0.88 | AO37: 0.02 | AP37: 180 DAYS | AQ37: Mr. Prashant | AR37: Direct | AT37: - | AU37: - | AV37: - | AY37: 46129 | AZ37: =AF37*AI37*AM37 -> 38000 | BA37: 46135 | BB37: 46129 | BI37: HLCUAB1260401258 | BJ37: 252.18 | BK37: 40' | BL37: 10 | BM37: 46163 | BO37: 46208 | BP37: IVC | BQ37: HCMC, VIETNAM | BR37: HAPAG LLOYD | BT37: ACHELOOS | BX37: =BJ37*AI37 -> 383313.6 | CE37: =IF(J37="VIETNAM", IF(CG37<>"","OBL in Vietnam Office", IF(CF37<>"","OBL in Transit from Vietnam Office", IF(CD37<>0,"OBL In Destination - "&J37, IF(CC37<>0,"OBL in Transit to Destination - "&J37, IF(CB37<>0,"OBL in SIG Office", IF(CA37<>0,"OBL in Transit from Origin to SIG", IF(BZ37<>0,"OBL in Origin - "&I37, IF(BY37<>0,"Draft Rcvd","No OBL Yet")))))))), IF(CO37<>0,"OBL In Destination - "&J37, IF(CM37<>0,"OBL in Transit with Nego Docs - "&J37, IF(CB37<>0,"OBL in SIG Office", IF(CA37<>0,"OBL in Transit from Origin to SIG", IF(BZ37<>0,"OBL in Origin - "&I37, IF(BY37<>0,"Draft Rcvd","No OBL Yet"))))))) -> No OBL Yet | CK37: =IF(CJ37<>0,"CERTS in Destination - "&J37,IF(CI37<>0,"CERT in Transit to -"&J37,IF(CH37<>0,"CERT in Origin - "&I37,IF(CH37="","No CERTS Yet")))) -> No CERTS Yet | CP37: =IF(CO37<>0,"Docs in Buyer's Bank",IF(CN37<>0,"Docs in Transit to Buyer's Bank",IF(CM37<>0,"Docs in Our Bank",IF(CL37="TT PAYMENT","Not Applicable","")))) | CQ37: =(AN37*AI37*BJ37)-AZ37 -> 299315.97 | CU37: =IF(CS37="","",BJ37-CT37) | CV37: =IF(CS37="","",CU37/BJ37) | CW37: =IF(CS37="","",AZ37+CQ37) | CX37: =IF(CS37="","",BX37*2%) | CY37: =IF(CS37="","",AI37/B37) | DA37: =IF(CS37="","",B37-CZ37) | DC37: =IF(CS37="","",IF(CS37="","",DB37-C37)) | DE37: =IF(CS37="","",10%-DD37) | DF37: =IF(CS37="","",CU37*AI37) | DG37: =IF(CS37="","",IF(DA37>2,2*DA37*CT37*CY37,DA37*CT37*CY37)) | DH37: =IF(CS37="","",IF(DA37>2,2*(DA37-2*CT37*CY37),0)) | DI37: =IF(CS37="","",IF(DC37>0,DC37*0.5*CT37,0)) | DJ37: =IF(CS37="","",IF(DE37<0,DE37*CT37*AI37*10%,0)) | DK37: =IF(CS37="","",SUM(DF37:DJ37)) | DN37: =IF(CS37="","",SUM(DK37:DL37)) | DO37: =IF(CS37="","",BJ37*AI37-DN37) | DP37: =IF(CS37="","",AZ37+CQ37) | DQ37: =IF(CS37="","",IF((DP37-DO37)>0,DP37-DO37,"")) | DR37: =IF(CS37="","",IF((DO37-DP37)>0,(DO37-DP37),"")) | DS37: =IF(CS37="","",IF(DQ37="",H37,"VALENCY")) | DT37: =IF(DN37="","",IF(DN37>0,"CN", "DN")) | DY37: NO VINA/RBS REPORT | EA37: =IF(CS37="","", MIN(0,(IF(DA37>2,2,1)*DA37*CT37*CY37)) ) | EH37: VALENCY IVC | EN37: =EK37*EJ37 -> 0 | EV37: =IF(CR37<>0,"Final Pmt Recd",IF(CM37<>0,"Export Loan",IF(BZ37<>0,"Nego Pending",IF(Z37<>0,"Yet to load","Yet to load")))) -> Yet to load | EX37: =EW37/BJ37 -> 0 | EY37: Freight paid by origin | FD37: =FC37*BJ37 -> 0 | FL37: =IFERROR(EZ37-BY37,"") -> 0 | FM37: =IFERROR(BM37-FB37,"") -> 46163 | FS37: =Y37 -> 20010094 | FT37: =AA37 -> 32016289-2
A38: =IF(DZ38="CLOSE","Trade closed",IF(DZ38="PMT Pending","FNF Settlement is Due",IF(CS38<>0,"FNF Reconcillation Onging",IF(CR38<>0," Final Pmt Recd , FNF Pending",IF(CM38<>0,"Exp Dox Presented to Bank, Pmt Pending",IF(BZ38<>0,"OBL Scan Recd, Nego Pending",IF(BM38<>0,"Sailed, OBL & Certs Pending",IF(BJ38<>0,"Stuffed, Yet to Sail",IF(BB38<>0,"SI Sent, Shipment Awaited",IF(BA38<>0,"Advance Rcvd, SI Pending",IF(Z38<>0,"SC Raised, Advance Pending",IF(X38<>0,"Deal Ticket Rcvd SC Pending", "Entry Pending")))))))))))) -> Sailed, OBL & Certs Pending | B38: 46 | C38: 200 | D38: RCN | E38: =IF(AND(LEFT(TRIM(AA38&""),1)="3",BI38<>""),"CLOSE POSITION", IF(AND(LEFT(TRIM(AA38&""),1)="3",BI38=""),"SHORT POSITION", IF(AND(LEFT(TRIM(AA38&""),1)<>"3",BI38<>""),"LONG POSITION","ENTRY PENDING"))) -> CLOSE POSITION | F38: =AA38 -> 32016289-3 | H38: =AB38 -> VIET PHI AGRICULTURE JOINT STOCK COMPANY | I38: IVC | J38: VIETNAM | K38: =IF(BQ38<>0,BQ38,"") -> HCMC, VIETNAM | L38: =IF(BI38<>0,BI38,"") -> HLCUAB1260400752 | M38: =IF(BJ38<>0,BJ38,"") -> 244.67 | N38: =IF(BM38<>0,BM38,"") -> 46163 | O38: =IF(BO38<>0,BO38,"") -> 46215 | P38: =CE38 -> No OBL Yet | Q38: TPSCR26010654 | R38: =CK38 -> No CERTS Yet | S38: =CP38 | T38: DRAFT BL RCVD 20/5 | U38: DRAFT BL RCVD 20/5,HBL DRAFT SENT TO BUYER 20/5 | W38: NTT - OBL PRINTING ISSUE IN SIG, ETA 12/7 | X38: 46126 | Y38: 20010094 | Z38: 46126 | AA38: 32016289-3 | AB38: VIET PHI AGRICULTURE JOINT STOCK COMPANY | AC38: 46168 | AD38: 46173 | AE38: 0.05 | AF38: 250 | AG38: =AF38*(1-AE38) -> 237.5 | AH38: MT | AI38: 1520 | AJ38: =AI38*AF38 -> 380000 | AK38: CFR | AL38: DP SIGHT | AM38: 0.1 | AN38: 0.88 | AO38: 0.02 | AP38: 180 DAYS | AQ38: Mr. Prashant | AR38: Direct | AT38: - | AU38: - | AV38: - | AY38: 46129 | AZ38: =AF38*AI38*AM38 -> 38000 | BA38: 46135 | BB38: 46129 | BI38: HLCUAB1260400752 | BJ38: 244.67 | BK38: 40' | BL38: 10 | BM38: 46163 | BO38: 46215 | BP38: IVC | BQ38: HCMC, VIETNAM | BR38: HAPAG LLOYD | BT38: ACHELOOS | BX38: =BJ38*AI38 -> 371898.4 | CE38: =IF(J38="VIETNAM", IF(CG38<>"","OBL in Vietnam Office", IF(CF38<>"","OBL in Transit from Vietnam Office", IF(CD38<>0,"OBL In Destination - "&J38, IF(CC38<>0,"OBL in Transit to Destination - "&J38, IF(CB38<>0,"OBL in SIG Office", IF(CA38<>0,"OBL in Transit from Origin to SIG", IF(BZ38<>0,"OBL in Origin - "&I38, IF(BY38<>0,"Draft Rcvd","No OBL Yet")))))))), IF(CO38<>0,"OBL In Destination - "&J38, IF(CM38<>0,"OBL in Transit with Nego Docs - "&J38, IF(CB38<>0,"OBL in SIG Office", IF(CA38<>0,"OBL in Transit from Origin to SIG", IF(BZ38<>0,"OBL in Origin - "&I38, IF(BY38<>0,"Draft Rcvd","No OBL Yet"))))))) -> No OBL Yet | CK38: =IF(CJ38<>0,"CERTS in Destination - "&J38,IF(CI38<>0,"CERT in Transit to -"&J38,IF(CH38<>0,"CERT in Origin - "&I38,IF(CH38="","No CERTS Yet")))) -> No CERTS Yet | CP38: =IF(CO38<>0,"Docs in Buyer's Bank",IF(CN38<>0,"Docs in Transit to Buyer's Bank",IF(CM38<>0,"Docs in Our Bank",IF(CL38="TT PAYMENT","Not Applicable","")))) | CQ38: =(AN38*AI38*BJ38)-AZ38 -> 289270.59 | CU38: =IF(CS38="","",BJ38-CT38) | CV38: =IF(CS38="","",CU38/BJ38) | CW38: =IF(CS38="","",AZ38+CQ38) | CX38: =IF(CS38="","",BX38*2%) | CY38: =IF(CS38="","",AI38/B38) | DA38: =IF(CS38="","",B38-CZ38) | DC38: =IF(CS38="","",IF(CS38="","",DB38-C38)) | DE38: =IF(CS38="","",10%-DD38) | DF38: =IF(CS38="","",CU38*AI38) | DG38: =IF(CS38="","",IF(DA38>2,2*DA38*CT38*CY38,DA38*CT38*CY38)) | DH38: =IF(CS38="","",IF(DA38>2,2*(DA38-2*CT38*CY38),0)) | DI38: =IF(CS38="","",IF(DC38>0,DC38*0.5*CT38,0)) | DJ38: =IF(CS38="","",IF(DE38<0,DE38*CT38*AI38*10%,0)) | DK38: =IF(CS38="","",SUM(DF38:DJ38)) | DN38: =IF(CS38="","",SUM(DK38:DL38)) | DO38: =IF(CS38="","",BJ38*AI38-DN38) | DP38: =IF(CS38="","",AZ38+CQ38) | DQ38: =IF(CS38="","",IF((DP38-DO38)>0,DP38-DO38,"")) | DR38: =IF(CS38="","",IF((DO38-DP38)>0,(DO38-DP38),"")) | DS38: =IF(CS38="","",IF(DQ38="",H38,"VALENCY")) | DT38: =IF(DN38="","",IF(DN38>0,"CN", "DN")) | DY38: NO VINA/RBS REPORT | EA38: =IF(CS38="","", MIN(0,(IF(DA38>2,2,1)*DA38*CT38*CY38)) ) | EH38: VALENCY IVC | EN38: =EK38*EJ38 -> 0 | EV38: =IF(CR38<>0,"Final Pmt Recd",IF(CM38<>0,"Export Loan",IF(BZ38<>0,"Nego Pending",IF(Z38<>0,"Yet to load","Yet to load")))) -> Yet to load | EX38: =EW38/BJ38 -> 0 | EY38: Freight paid by origin | FD38: =FC38*BJ38 -> 0 | FL38: =IFERROR(EZ38-BY38,"") -> 0 | FM38: =IFERROR(BM38-FB38,"") -> 46163 | FS38: =Y38 -> 20010094 | FT38: =AA38 -> 32016289-3
A39: =IF(DZ39="CLOSE","Trade closed",IF(DZ39="PMT Pending","FNF Settlement is Due",IF(CS39<>0,"FNF Reconcillation Onging",IF(CR39<>0," Final Pmt Recd , FNF Pending",IF(CM39<>0,"Exp Dox Presented to Bank, Pmt Pending",IF(BZ39<>0,"OBL Scan Recd, Nego Pending",IF(BM39<>0,"Sailed, OBL & Certs Pending",IF(BJ39<>0,"Stuffed, Yet to Sail",IF(BB39<>0,"SI Sent, Shipment Awaited",IF(BA39<>0,"Advance Rcvd, SI Pending",IF(Z39<>0,"SC Raised, Advance Pending",IF(X39<>0,"Deal Ticket Rcvd SC Pending", "Entry Pending")))))))))))) -> Final Pmt Recd , FNF Pending | B39: 47 | C39: 185 | D39: RCN | E39: =IF(AND(LEFT(TRIM(AA39&""),1)="3",BI39<>""),"CLOSE POSITION", IF(AND(LEFT(TRIM(AA39&""),1)="3",BI39=""),"SHORT POSITION", IF(AND(LEFT(TRIM(AA39&""),1)<>"3",BI39<>""),"LONG POSITION","ENTRY PENDING"))) -> CLOSE POSITION | F39: =AA39 -> 32015281-3 | H39: =AB39 -> Valency Agro (Processing) | I39: GHANA | J39: INDIA | K39: =IF(BQ39<>0,BQ39,"") -> MANGALORE, INDIA | L39: =IF(BI39<>0,BI39,"") -> 267603567 | M39: =IF(BJ39<>0,BJ39,"") -> 25.62 | N39: =IF(BM39<>0,BM39,"") -> 46105 | O39: =IF(BO39<>0,BO39,"") -> 46161 | P39: =CE39 -> OBL In Destination - INDIA | R39: =CK39 -> CERTS in Destination - INDIA | S39: =CP39 -> Docs in Buyer's Nego Bank | T39: =IFERROR(_xlfn.XLOOKUP(F39, '[2]Data 2026'!$H$12:$H$111, '[2]Data 2026'!$CL$12:$CL$111),"") | U39: PAYMENT RCVD 14/05 | X39: 46093 | Y39: 20009747 | Z39: =X39 -> 46093 | AA39: 32015281-3 | AB39: Valency Agro (Processing) | AC39: March - 26 | AD39: 46112 | AE39: 0.1 | AF39: 25 | AG39: =AF39*(1-AE39) -> 22.5 | AH39: MT | AI39: 1585 | AJ39: =AI39*AF39 -> 39625 | AK39: CIF | AL39: DP SIGHT | AM39: 0 | AN39: 1 | AO39: 0 | AP39: 180 DAYS | AQ39: Mr. Naveen | AR39: Direct | AT39: - | AU39: - | AV39: - | AZ39: =AF39*AI39*AM39 -> 0 | BA39: =Z39 -> 46093 | BB39: 46078 | BF39: 46078 | BI39: 267603567 | BJ39: 25.62 | BK39: 40' | BL39: 1 | BM39: 46105 | BO39: 46161 | BP39: GHANA | BQ39: MANGALORE, INDIA | BR39: MAERSK LINE | BT39: MAERSK ARAS | BU39: 612E | BV39: 90082919 | BX39: =BJ39*AI39 -> 40607.7 | CE39: =IF(J39="VIETNAM", IF(CG39<>"","OBL in Vietnam Office", IF(CF39<>"","OBL in Transit from Vietnam Office", IF(CD39<>0,"OBL In Destination - "&J39, IF(CC39<>0,"OBL in Transit to Destination - "&J39, IF(CB39<>0,"OBL in SIG Office", IF(CA39<>0,"OBL in Transit from Origin to SIG", IF(BZ39<>0,"OBL in Origin - "&I39, IF(BY39<>0,"Draft Rcvd","No OBL Yet")))))))), IF(CO39<>0,"OBL In Destination - "&J39, IF(CM39<>0,"OBL in Transit with Nego Docs - "&J39, IF(CB39<>0,"OBL in SIG Office", IF(CA39<>0,"OBL in Transit from Origin to SIG", IF(BZ39<>0,"OBL in Origin - "&I39, IF(BY39<>0,"Draft Rcvd","No OBL Yet"))))))) -> OBL In Destination - INDIA | CH39: 46137 | CI39: 2363213101 | CJ39: 46146 | CK39: =IF(CJ39<>0,"CERTS in Destination - "&J39,IF(CI39<>0,"CERT in Transit to -"&J39,IF(CH39<>0,"CERT in Origin - "&I39,IF(CH39="","No CERTS Yet")))) -> CERTS in Destination - INDIA | CL39: ICICI BANK | CM39: 46119 | CN39: 2365151644 | CO39: 46155 | CP39: =IF(CO39<>0,"Docs in Buyer's Nego Bank",IF(CN39<>0,"Docs in Transit to Buyer's Nego Bank",IF(CM39<>0,"Docs in Our Nego Bank",IF(CL39="TT PAYMENT","Not Applicable","")))) -> Docs in Buyer's Nego Bank | CQ39: =(AN39*AI39*BJ39)-AZ39 -> 40607.7 | CR39: 46156 | CU39: =IF(CS39="","",BJ39-CT39) | CV39: =IF(CS39="","",CU39/BJ39) | CW39: =IF(CS39="","",AZ39+CQ39) | CX39: =IF(CS39="","",BX39*2%) | CY39: =IF(CS39="","",AI39/B39) | DA39: =IF(CS39="","",B39-CZ39) | DC39: =IF(CS39="","",IF(CS39="","",DB39-C39)) | DE39: =IF(CS39="","",10%-DD39) | DF39: =IF(CS39="","",CU39*AI39) | DG39: =IF(CS39="","",IF(DA39>2,2*DA39*CT39*CY39,DA39*CT39*CY39)) | DH39: =IF(CS39="","",IF(DA39>2,2*(DA39-2*CT39*CY39),0)) | DI39: =IF(CS39="","",IF(DC39>0,DC39*0.5*CT39,0)) | DJ39: =IF(CS39="","",IF(DE39<0,DE39*CT39*AI39*1%,0)) | DK39: =IF(CS39="","",SUM(DF39:DJ39)) | DN39: =IF(CS39="","",SUM(DK39:DL39)) | DO39: =IF(CS39="","",BJ39*AI39-DN39) | DP39: =IF(CS39="","",AZ39+CQ39) | DQ39: =IF(CS39="","",IF((DP39-DO39)>0,DP39-DO39,"")) | DR39: =IF(CS39="","",IF((DO39-DP39)>0,(DO39-DP39),"")) | DS39: =IF(CS39="","",IF(DQ39="",H39,"VALENCY")) | DT39: =IF(DN39="","",IF(DN39>0,"CN", "DN")) | DY39: NO VINA/RBS REPORT | EA39: =IF(CS39="","", MIN(0,(IF(DA39>2,2,1)*DA39*CT39*CY39)) ) | EH39: Valora Exim | EI39: FOB | EN39: =EK39*EJ39 -> 0 | EV39: =IF(CR39<>0,"Final Pmt Recd",IF(CM39<>0,"Export Loan",IF(BZ39<>0,"Nego Pending",IF(Z39<>0,"Yet to load","Yet to load")))) -> Final Pmt Recd | EX39: =EW39/BJ39 -> 0 | EY39: Freight paid by origin | FD39: =FC39*BJ39 -> 0 | FL39: =IFERROR(EZ39-BY39,"") -> 0 | FM39: =IFERROR(BM39-FB39,"") -> 46105 | FS39: =Y39 -> 20009747 | FT39: =AA39 -> 32015281-3 | GD39: 90082919 | GF39: done
A40: =IF(DZ40="CLOSE","Trade closed",IF(DZ40="PMT Pending","FNF Settlement is Due",IF(CS40<>0,"FNF Reconcillation Onging",IF(CR40<>0," Final Pmt Recd , FNF Pending",IF(CM40<>0,"Exp Dox Presented to Bank, Pmt Pending",IF(BZ40<>0,"OBL Scan Recd, Nego Pending",IF(BM40<>0,"Sailed, OBL & Certs Pending",IF(BJ40<>0,"Stuffed, Yet to Sail",IF(BB40<>0,"SI Sent, Shipment Awaited",IF(BA40<>0,"Advance Rcvd, SI Pending",IF(Z40<>0,"SC Raised, Advance Pending",IF(X40<>0,"Deal Ticket Rcvd SC Pending", "Entry Pending")))))))))))) -> Final Pmt Recd , FNF Pending | B40: 48 | C40: 185 | D40: RCN | E40: =IF(AND(LEFT(TRIM(AA40&""),1)="3",BI40<>""),"CLOSE POSITION", IF(AND(LEFT(TRIM(AA40&""),1)="3",BI40=""),"SHORT POSITION", IF(AND(LEFT(TRIM(AA40&""),1)<>"3",BI40<>""),"LONG POSITION","ENTRY PENDING"))) -> CLOSE POSITION | F40: =AA40 -> 32016277 | H40: =AB40 -> LIEN VIET TRADING | I40: NIGERIA(OGB) | J40: VIETNAM | K40: =IF(BQ40<>0,BQ40,"") -> HCMC, VIETNAM | L40: =IF(BI40<>0,BI40,"") -> MEDULG619470 | M40: =IF(BJ40<>0,BJ40,"") -> 203.169 | N40: =IF(BM40<>0,BM40,"") -> 46097 | O40: =IF(BO40<>0,BO40,"") -> 46161 | P40: =CE40 -> OBL In Destination - VIETNAM | Q40: TPSCR26010505 | R40: =CK40 -> CERTS in Destination - VIETNAM | S40: =CP40 -> Docs in Buyer's Nego Bank | T40: =IFERROR(_xlfn.XLOOKUP(F40, '[2]Data 2026'!$H$12:$H$111, '[2]Data 2026'!$CL$12:$CL$111),"") | U40: PAYMENT RCVD 26/05 | X40: 46125 | Y40: 20010090 | Z40: 46125 | AA40: 32016277 | AB40: LIEN VIET TRADING | AC40: April - 26 | AD40: 46142 | AE40: 0.1 | AF40: 200 | AG40: =AF40*(1-AE40) -> 180 | AH40: MT | AI40: 1580 | AJ40: =AI40*AF40 -> 316000 | AK40: CFR | AL40: 10% ADVANCE 88% DP AT SIGHT 2% after vina | AM40: 0.1 | AN40: 0.88 | AO40: 0.02 | AP40: 180 DAYS | AQ40: PRASHANT | AR40: Global Link | AS40: 5 | AT40: - | AU40: - | AV40: - | AY40: 46127 | AZ40: =AF40*AI40*AM40 -> 31600 | BA40: 46127 | BI40: MEDULG619470 | BJ40: 203.169 | BK40: 40' | BM40: 46097 | BN40: TRHU7216691 Nansha, CN 05-05 | BO40: 46161 | BP40: NIGERIA | BQ40: HCMC, VIETNAM | BR40: MSC | BV40: 90085132 | BW40: 46142 | BX40: =BJ40*AI40 -> 321007.02 | BZ40: 46135 | CC40: 25 2898 9820 | CD40: 46150 | CE40: =IF(J40="VIETNAM", IF(CG40<>"","OBL in Vietnam Office", IF(CF40<>"","OBL in Transit from Vietnam Office", IF(CD40<>0,"OBL In Destination - "&J40, IF(CC40<>0,"OBL in Transit to Destination - "&J40, IF(CB40<>0,"OBL in SIG Office", IF(CA40<>0,"OBL in Transit from Origin to SIG", IF(BZ40<>0,"OBL in Origin - "&I40, IF(BY40<>0,"Draft Rcvd","No OBL Yet")))))))), IF(CO40<>0,"OBL In Destination - "&J40, IF(CM40<>0,"OBL in Transit with Nego Docs - "&J40, IF(CB40<>0,"OBL in SIG Office", IF(CA40<>0,"OBL in Transit from Origin to SIG", IF(BZ40<>0,"OBL in Origin - "&I40, IF(BY40<>0,"Draft Rcvd","No OBL Yet"))))))) -> OBL In Destination - VIETNAM | CH40: 46135 | CI40: 25 2898 9820 | CJ40: 46150 | CK40: =IF(CJ40<>0,"CERTS in Destination - "&J40,IF(CI40<>0,"CERT in Transit to -"&J40,IF(CH40<>0,"CERT in Origin - "&I40,IF(CH40="","No CERTS Yet")))) -> CERTS in Destination - VIETNAM | CL40: Habib Bank | CM40: 46149 | CN40: 7291530002 | CO40: 46154 | CP40: =IF(CO40<>0,"Docs in Buyer's Nego Bank",IF(CN40<>0,"Docs in Transit to Buyer's Nego Bank",IF(CM40<>0,"Docs in Our Nego Bank",IF(CL40="TT PAYMENT","Not Applicable","")))) -> Docs in Buyer's Nego Bank | CQ40: 282986.88 | CR40: 46168 | CU40: =IF(CS40="","",BJ40-CT40) | CV40: =IF(CS40="","",CU40/BJ40) | CW40: =IF(CS40="","",AZ40+CQ40) | CX40: =IF(CS40="","",BX40*2%) | CY40: =IF(CS40="","",AI40/B40) | DA40: =IF(CS40="","",B40-CZ40) | DC40: =IF(CS40="","",IF(CS40="","",DB40-C40)) | DE40: =IF(CS40="","",10%-DD40) | DF40: =IF(CS40="","",CU40*AI40) | DG40: =IF(CS40="","",IF(DA40>2,2*DA40*CT40*CY40,DA40*CT40*CY40)) | DH40: =IF(CS40="","",IF(DA40>2,2*(DA40-2*CT40*CY40),0)) | DI40: =IF(CS40="","",IF(DC40>0,DC40*0.5*CT40,0)) | DJ40: =IF(CS40="","",IF(DE40<0,DE40*CT40*AI40*1%,0)) | DK40: =IF(CS40="","",SUM(DF40:DJ40)) | DN40: =IF(CS40="","",SUM(DK40:DL40)) | DO40: =IF(CS40="","",BJ40*AI40-DN40) | DP40: =IF(CS40="","",AZ40+CQ40) | DQ40: =IF(CS40="","",IF((DP40-DO40)>0,DP40-DO40,"")) | DR40: =IF(CS40="","",IF((DO40-DP40)>0,(DO40-DP40),"")) | DS40: =IF(CS40="","",IF(DQ40="",H40,"VALENCY")) | DT40: =IF(DN40="","",IF(DN40>0,"CN", "DN")) | DY40: NO VINA/RBS REPORT | EA40: =IF(CS40="","", MIN(0,(IF(DA40>2,2,1)*DA40*CT40*CY40)) ) | EH40: Valency Nigeria | EN40: =EK40*EJ40 -> 0 | EV40: =IF(CR40<>0,"Final Pmt Recd",IF(CM40<>0,"Export Loan",IF(BZ40<>0,"Nego Pending",IF(Z40<>0,"Yet to load","Yet to load")))) -> Final Pmt Recd | EX40: =EW40/BJ40 -> 0 | EY40: Freight paid by origin | FD40: =FC40*BJ40 -> 0 | FL40: =IFERROR(EZ40-BY40,"") -> 0 | FM40: =IFERROR(BM40-FB40,"") -> 46097 | FS40: =Y40 -> 20010090 | FT40: =AA40 -> 32016277
A41: =IF(DZ41="CLOSE","Trade closed",IF(DZ41="PMT Pending","FNF Settlement is Due",IF(CS41<>0,"FNF Reconcillation Onging",IF(CR41<>0," Final Pmt Recd , FNF Pending",IF(CM41<>0,"Exp Dox Presented to Bank, Pmt Pending",IF(BZ41<>0,"OBL Scan Recd, Nego Pending",IF(BM41<>0,"Sailed, OBL & Certs Pending",IF(BJ41<>0,"Stuffed, Yet to Sail",IF(BB41<>0,"SI Sent, Shipment Awaited",IF(BA41<>0,"Advance Rcvd, SI Pending",IF(Z41<>0,"SC Raised, Advance Pending",IF(X41<>0,"Deal Ticket Rcvd SC Pending", "Entry Pending")))))))))))) -> SI Sent, Shipment Awaited | B41: 48 | C41: 200 | D41: RCN | E41: =IF(AND(LEFT(TRIM(AA41&""),1)="3",BI41<>""),"CLOSE POSITION", IF(AND(LEFT(TRIM(AA41&""),1)="3",BI41=""),"SHORT POSITION", IF(AND(LEFT(TRIM(AA41&""),1)<>"3",BI41<>""),"LONG POSITION","ENTRY PENDING"))) -> CLOSE POSITION | F41: =AA41 -> 32014498 | H41: =AB41 -> SRI VIJAYALAXMI CASHEW INDUSTRIES | I41: IVC | J41: INDIA | K41: =IF(BQ41<>0,BQ41,"") -> MANGALORE, INDIA | L41: =IF(BI41<>0,BI41,"") -> 267490003 | M41: =IF(BJ41<>0,BJ41,"") | N41: =IF(BM41<>0,BM41,"") | O41: =IF(BO41<>0,BO41,"") | P41: =CE41 -> No OBL Yet | R41: =CK41 -> No CERTS Yet | S41: =CP41 | T41: CLARIFICATION ON LATEST SOB | U41: RCVD COUNTERSIGNED-267490003 | X41: 46076 | Y41: 20009555 | Z41: 46074 | AA41: 32014498 | AB41: SRI VIJAYALAXMI CASHEW INDUSTRIES | AC41: April - 26 | AD41: 46142 | AE41: 0.1 | AF41: 100 | AG41: =AF41*(1-AE41) -> 90 | AH41: MT | AI41: 1505 | AJ41: =AI41*AF41 -> 150500 | AK41: CIF | AL41: DP SIGHT | AM41: 0 | AN41: 1 | AO41: 0 | AP41: 180 DAYS | AQ41: Mr. George | AR41: Direct | AT41: - | AU41: - | AV41: - | AZ41: =AF41*AI41*AM41 -> 0 | BB41: 46083 | BF41: 46083 | BI41: 267490003 | BK41: 40' | BP41: IVC | BQ41: MANGALORE, INDIA | BX41: =BJ41*AI41 -> 0 | CE41: =IF(J41="VIETNAM", IF(CG41<>"","OBL in Vietnam Office", IF(CF41<>"","OBL in Transit from Vietnam Office", IF(CD41<>0,"OBL In Destination - "&J41, IF(CC41<>0,"OBL in Transit to Destination - "&J41, IF(CB41<>0,"OBL in SIG Office", IF(CA41<>0,"OBL in Transit from Origin to SIG", IF(BZ41<>0,"OBL in Origin - "&I41, IF(BY41<>0,"Draft Rcvd","No OBL Yet")))))))), IF(CO41<>0,"OBL In Destination - "&J41, IF(CM41<>0,"OBL in Transit with Nego Docs - "&J41, IF(CB41<>0,"OBL in SIG Office", IF(CA41<>0,"OBL in Transit from Origin to SIG", IF(BZ41<>0,"OBL in Origin - "&I41, IF(BY41<>0,"Draft Rcvd","No OBL Yet"))))))) -> No OBL Yet | CK41: =IF(CJ41<>0,"CERTS in Destination - "&J41,IF(CI41<>0,"CERT in Transit to -"&J41,IF(CH41<>0,"CERT in Origin - "&I41,IF(CH41="","No CERTS Yet")))) -> No CERTS Yet | CP41: =IF(CO41<>0,"Docs in Buyer's Nego Bank",IF(CN41<>0,"Docs in Transit to Buyer's Nego Bank",IF(CM41<>0,"Docs in Our Nego Bank",IF(CL41="TT PAYMENT","Not Applicable","")))) | CQ41: =(AN41*AI41*BJ41)-AZ41 -> 0 | CU41: =IF(CS41="","",BJ41-CT41) | CV41: =IF(CS41="","",CU41/BJ41) | CW41: =IF(CS41="","",AZ41+CQ41) | CX41: =IF(CS41="","",BX41*2%) | CY41: =IF(CS41="","",AI41/B41) | DA41: =IF(CS41="","",B41-CZ41) | DC41: =IF(CS41="","",IF(CS41="","",DB41-C41)) | DE41: =IF(CS41="","",10%-DD41) | DF41: =IF(CS41="","",CU41*AI41) | DG41: =IF(CS41="","",IF(DA41>2,2*DA41*CT41*CY41,DA41*CT41*CY41)) | DH41: =IF(CS41="","",IF(DA41>2,2*(DA41-2*CT41*CY41),0)) | DI41: =IF(CS41="","",IF(DC41>0,DC41*0.5*CT41,0)) | DJ41: =IF(CS41="","",IF(DE41<0,DE41*CT41*AI41*1%,0)) | DK41: =IF(CS41="","",SUM(DF41:DJ41)) | DN41: =IF(CS41="","",SUM(DK41:DL41)) | DO41: =IF(CS41="","",BJ41*AI41-DN41) | DP41: =IF(CS41="","",AZ41+CQ41) | DQ41: =IF(CS41="","",IF((DP41-DO41)>0,DP41-DO41,"")) | DR41: =IF(CS41="","",IF((DO41-DP41)>0,(DO41-DP41),"")) | DS41: =IF(CS41="","",IF(DQ41="",H41,"VALENCY")) | DT41: =IF(DN41="","",IF(DN41>0,"CN", "DN")) | DY41: NO VINA/RBS REPORT | EA41: =IF(CS41="","", MIN(0,(IF(DA41>2,2,1)*DA41*CT41*CY41)) ) | EH41: VALENCY IVC | EN41: =EK41*EJ41 -> 0 | EV41: =IF(CR41<>0,"Final Pmt Recd",IF(CM41<>0,"Export Loan",IF(BZ41<>0,"Nego Pending",IF(Z41<>0,"Yet to load","Yet to load")))) -> Yet to load | EX41: =EW41/BJ41 -> #DIV/0! | EY41: Freight paid by origin | FD41: =FC41*BJ41 -> 0 | FL41: =IFERROR(EZ41-BY41,"") -> 0 | FM41: =IFERROR(BM41-FB41,"") -> 0 | FS41: =Y41 -> 20009555 | FT41: =AA41 -> 32014498
A42: =IF(DZ42="CLOSE","Trade closed",IF(DZ42="PMT Pending","FNF Settlement is Due",IF(CS42<>0,"FNF Reconcillation Onging",IF(CR42<>0," Final Pmt Recd , FNF Pending",IF(CM42<>0,"Exp Dox Presented to Bank, Pmt Pending",IF(BZ42<>0,"OBL Scan Recd, Nego Pending",IF(BM42<>0,"Sailed, OBL & Certs Pending",IF(BJ42<>0,"Stuffed, Yet to Sail",IF(BB42<>0,"SI Sent, Shipment Awaited",IF(BA42<>0,"Advance Rcvd, SI Pending",IF(Z42<>0,"SC Raised, Advance Pending",IF(X42<>0,"Deal Ticket Rcvd SC Pending", "Entry Pending")))))))))))) -> SI Sent, Shipment Awaited | B42: 49 | C42: 200 | D42: RCN | E42: =IF(AND(LEFT(TRIM(AA42&""),1)="3",BI42<>""),"CLOSE POSITION", IF(AND(LEFT(TRIM(AA42&""),1)="3",BI42=""),"SHORT POSITION", IF(AND(LEFT(TRIM(AA42&""),1)<>"3",BI42<>""),"LONG POSITION","ENTRY PENDING"))) -> CLOSE POSITION | F42: =AA42 -> 32014483 | H42: =AB42 -> SRI VIJAYALAXMI CASHEW INDUSTRIES | I42: IVC | J42: INDIA | K42: =IF(BQ42<>0,BQ42,"") -> MANGALORE, INDIA | L42: =IF(BI42<>0,BI42,"") -> 269658785 | M42: =IF(BJ42<>0,BJ42,"") | N42: =IF(BM42<>0,BM42,"") | O42: =IF(BO42<>0,BO42,"") | P42: =CE42 -> No OBL Yet | R42: =CK42 -> No CERTS Yet | S42: =CP42 | T42: CLARIFICATION ON LATEST SOB | U42: RCVD COUNTERSIGNED-267489736-1 267489736-2 | X42: 46073 | Y42: 20009535 | Z42: 46073 | AA42: 32014483 | AB42: SRI VIJAYALAXMI CASHEW INDUSTRIES | AC42: April - 26 | AD42: 46142 | AE42: 0.1 | AF42: 200 | AG42: =AF42*(1-AE42) -> 180 | AH42: MT | AI42: 1540 | AJ42: =AI42*AF42 -> 308000 | AK42: CIF | AL42: DP SIGHT | AM42: 0 | AN42: 1 | AO42: 0 | AP42: 180 DAYS | AQ42: Mr. George | AR42: Direct | AT42: - | AU42: - | AV42: - | AZ42: =AF42*AI42*AM42 -> 0 | BA42: 46076 | BB42: 46083 | BF42: 46083 | BI42: 269658785 | BK42: 40' | BP42: IVC | BQ42: MANGALORE, INDIA | BX42: =BJ42*AI42 -> 0 | CE42: =IF(J42="VIETNAM", IF(CG42<>"","OBL in Vietnam Office", IF(CF42<>"","OBL in Transit from Vietnam Office", IF(CD42<>0,"OBL In Destination - "&J42, IF(CC42<>0,"OBL in Transit to Destination - "&J42, IF(CB42<>0,"OBL in SIG Office", IF(CA42<>0,"OBL in Transit from Origin to SIG", IF(BZ42<>0,"OBL in Origin - "&I42, IF(BY42<>0,"Draft Rcvd","No OBL Yet")))))))), IF(CO42<>0,"OBL In Destination - "&J42, IF(CM42<>0,"OBL in Transit with Nego Docs - "&J42, IF(CB42<>0,"OBL in SIG Office", IF(CA42<>0,"OBL in Transit from Origin to SIG", IF(BZ42<>0,"OBL in Origin - "&I42, IF(BY42<>0,"Draft Rcvd","No OBL Yet"))))))) -> No OBL Yet | CK42: =IF(CJ42<>0,"CERTS in Destination - "&J42,IF(CI42<>0,"CERT in Transit to -"&J42,IF(CH42<>0,"CERT in Origin - "&I42,IF(CH42="","No CERTS Yet")))) -> No CERTS Yet | CP42: =IF(CO42<>0,"Docs in Buyer's Nego Bank",IF(CN42<>0,"Docs in Transit to Buyer's Nego Bank",IF(CM42<>0,"Docs in Our Nego Bank",IF(CL42="TT PAYMENT","Not Applicable","")))) | CQ42: =(AN42*AI42*BJ42)-AZ42 -> 0 | CU42: =IF(CS42="","",BJ42-CT42) | CV42: =IF(CS42="","",CU42/BJ42) | CW42: =IF(CS42="","",AZ42+CQ42) | CX42: =IF(CS42="","",BX42*2%) | CY42: =IF(CS42="","",AI42/B42) | DA42: =IF(CS42="","",B42-CZ42) | DC42: =IF(CS42="","",IF(CS42="","",DB42-C42)) | DE42: =IF(CS42="","",10%-DD42) | DF42: =IF(CS42="","",CU42*AI42) | DG42: =IF(CS42="","",IF(DA42>2,2*DA42*CT42*CY42,DA42*CT42*CY42)) | DH42: =IF(CS42="","",IF(DA42>2,2*(DA42-2*CT42*CY42),0)) | DI42: =IF(CS42="","",IF(DC42>0,DC42*0.5*CT42,0)) | DJ42: =IF(CS42="","",IF(DE42<0,DE42*CT42*AI42*1%,0)) | DK42: =IF(CS42="","",SUM(DF42:DJ42)) | DN42: =IF(CS42="","",SUM(DK42:DL42)) | DO42: =IF(CS42="","",BJ42*AI42-DN42) | DP42: =IF(CS42="","",AZ42+CQ42) | DQ42: =IF(CS42="","",IF((DP42-DO42)>0,DP42-DO42,"")) | DR42: =IF(CS42="","",IF((DO42-DP42)>0,(DO42-DP42),"")) | DS42: =IF(CS42="","",IF(DQ42="",H42,"VALENCY")) | DT42: =IF(DN42="","",IF(DN42>0,"CN", "DN")) | DY42: NO VINA/RBS REPORT | EA42: =IF(CS42="","", MIN(0,(IF(DA42>2,2,1)*DA42*CT42*CY42)) ) | EH42: VALENCY IVC | EN42: =EK42*EJ42 -> 0 | EV42: =IF(CR42<>0,"Final Pmt Recd",IF(CM42<>0,"Export Loan",IF(BZ42<>0,"Nego Pending",IF(Z42<>0,"Yet to load","Yet to load")))) -> Yet to load | EX42: =EW42/BJ42 -> #DIV/0! | EY42: Freight paid by origin | FD42: =FC42*BJ42 -> 0 | FL42: =IFERROR(EZ42-BY42,"") -> 0 | FM42: =IFERROR(BM42-FB42,"") -> 0 | FS42: =Y42 -> 20009535 | FT42: =AA42 -> 32014483
A43: =IF(DZ43="CLOSE","Trade closed",IF(DZ43="PMT Pending","FNF Settlement is Due",IF(CS43<>0,"FNF Reconcillation Onging",IF(CR43<>0," Final Pmt Recd , FNF Pending",IF(CM43<>0,"Exp Dox Presented to Bank, Pmt Pending",IF(BZ43<>0,"OBL Scan Recd, Nego Pending",IF(BM43<>0,"Sailed, OBL & Certs Pending",IF(BJ43<>0,"Stuffed, Yet to Sail",IF(BB43<>0,"SI Sent, Shipment Awaited",IF(BA43<>0,"Advance Rcvd, SI Pending",IF(Z43<>0,"SC Raised, Advance Pending",IF(X43<>0,"Deal Ticket Rcvd SC Pending", "Entry Pending")))))))))))) -> SI Sent, Shipment Awaited | B43: 49 | C43: 200 | D43: RCN | E43: =IF(AND(LEFT(TRIM(AA43&""),1)="3",BI43<>""),"CLOSE POSITION", IF(AND(LEFT(TRIM(AA43&""),1)="3",BI43=""),"SHORT POSITION", IF(AND(LEFT(TRIM(AA43&""),1)<>"3",BI43<>""),"LONG POSITION","ENTRY PENDING"))) -> CLOSE POSITION | F43: =AA43 -> 32014461 | H43: =AB43 -> ST. GREGORIOUS CASHEW | I43: IVC | J43: INDIA | K43: =IF(BQ43<>0,BQ43,"") -> TUTICORIN, INDIA | L43: 268716278 | M43: 96.56 | N43: =IF(BM43<>0,BM43,"") | O43: 46189 | P43: =CE43 -> Draft Rcvd | R43: =CK43 -> No CERTS Yet | S43: =CP43 | T43: CLARIFICATION ON LATEST SOB | U43: DRAFT BL RCVD 23/5 | W43: DRAFT BL RCVD 23/5 | X43: 46067 | Y43: 20009513 | Z43: 46067 | AA43: 32014461 | AB43: ST. GREGORIOUS CASHEW | AC43: March/April - 26 | AD43: 46142 | AE43: 0.1 | AF43: 100 | AG43: =AF43*(1-AE43) -> 90 | AH43: MT | AI43: 1565 | AJ43: =AI43*AF43 -> 156500 | AK43: CIF | AL43: DP SIGHT | AM43: 0 | AN43: 1 | AO43: 0 | AP43: 180 DAYS | AQ43: Mr. George | AR43: Direct | AT43: - | AU43: - | AV43: - | AZ43: =AF43*AI43*AM43 -> 0 | BA43: 46067 | BB43: 46083 | BF43: 46083 | BI43: 268716278 | BK43: 40' | BP43: IVC | BQ43: TUTICORIN, INDIA | BX43: =BJ43*AI43 -> 0 | BY43: 46165 | CE43: =IF(J43="VIETNAM", IF(CG43<>"","OBL in Vietnam Office", IF(CF43<>"","OBL in Transit from Vietnam Office", IF(CD43<>0,"OBL In Destination - "&J43, IF(CC43<>0,"OBL in Transit to Destination - "&J43, IF(CB43<>0,"OBL in SIG Office", IF(CA43<>0,"OBL in Transit from Origin to SIG", IF(BZ43<>0,"OBL in Origin - "&I43, IF(BY43<>0,"Draft Rcvd","No OBL Yet")))))))), IF(CO43<>0,"OBL In Destination - "&J43, IF(CM43<>0,"OBL in Transit with Nego Docs - "&J43, IF(CB43<>0,"OBL in SIG Office", IF(CA43<>0,"OBL in Transit from Origin to SIG", IF(BZ43<>0,"OBL in Origin - "&I43, IF(BY43<>0,"Draft Rcvd","No OBL Yet"))))))) -> Draft Rcvd | CK43: =IF(CJ43<>0,"CERTS in Destination - "&J43,IF(CI43<>0,"CERT in Transit to -"&J43,IF(CH43<>0,"CERT in Origin - "&I43,IF(CH43="","No CERTS Yet")))) -> No CERTS Yet | CP43: =IF(CO43<>0,"Docs in Buyer's Nego Bank",IF(CN43<>0,"Docs in Transit to Buyer's Nego Bank",IF(CM43<>0,"Docs in Our Nego Bank",IF(CL43="TT PAYMENT","Not Applicable","")))) | CQ43: =(AN43*AI43*BJ43)-AZ43 -> 0 | CU43: =IF(CS43="","",BJ43-CT43) | CV43: =IF(CS43="","",CU43/BJ43) | CW43: =IF(CS43="","",AZ43+CQ43) | CX43: =IF(CS43="","",BX43*2%) | CY43: =IF(CS43="","",AI43/B43) | DA43: =IF(CS43="","",B43-CZ43) | DC43: =IF(CS43="","",IF(CS43="","",DB43-C43)) | DE43: =IF(CS43="","",10%-DD43) | DF43: =IF(CS43="","",CU43*AI43) | DG43: =IF(CS43="","",IF(DA43>2,2*DA43*CT43*CY43,DA43*CT43*CY43)) | DH43: =IF(CS43="","",IF(DA43>2,2*(DA43-2*CT43*CY43),0)) | DI43: =IF(CS43="","",IF(DC43>0,DC43*0.5*CT43,0)) | DJ43: =IF(CS43="","",IF(DE43<0,DE43*CT43*AI43*1%,0)) | DK43: =IF(CS43="","",SUM(DF43:DJ43)) | DN43: =IF(CS43="","",SUM(DK43:DL43)) | DO43: =IF(CS43="","",BJ43*AI43-DN43) | DP43: =IF(CS43="","",AZ43+CQ43) | DQ43: =IF(CS43="","",IF((DP43-DO43)>0,DP43-DO43,"")) | DR43: =IF(CS43="","",IF((DO43-DP43)>0,(DO43-DP43),"")) | DS43: =IF(CS43="","",IF(DQ43="",H43,"VALENCY")) | DT43: =IF(DN43="","",IF(DN43>0,"CN", "DN")) | DY43: NO VINA/RBS REPORT | EA43: =IF(CS43="","", MIN(0,(IF(DA43>2,2,1)*DA43*CT43*CY43)) ) | EH43: VALENCY IVC | EI43: FOB | EN43: =EK43*EJ43 -> 0 | EV43: =IF(CR43<>0,"Final Pmt Recd",IF(CM43<>0,"Export Loan",IF(BZ43<>0,"Nego Pending",IF(Z43<>0,"Yet to load","Yet to load")))) -> Yet to load | EX43: =EW43/BJ43 -> #DIV/0! | EY43: Freight paid by origin | FD43: =FC43*BJ43 -> 0 | FL43: =IFERROR(EZ43-BY43,"") -> -46165 | FM43: =IFERROR(BM43-FB43,"") -> 0 | FS43: =Y43 -> 20009513 | FT43: =AA43 -> 32014461
A44: =IF(DZ44="CLOSE","Trade closed",IF(DZ44="PMT Pending","FNF Settlement is Due",IF(CS44<>0,"FNF Reconcillation Onging",IF(CR44<>0," Final Pmt Recd , FNF Pending",IF(CM44<>0,"Exp Dox Presented to Bank, Pmt Pending",IF(BZ44<>0,"OBL Scan Recd, Nego Pending",IF(BM44<>0,"Sailed, OBL & Certs Pending",IF(BJ44<>0,"Stuffed, Yet to Sail",IF(BB44<>0,"SI Sent, Shipment Awaited",IF(BA44<>0,"Advance Rcvd, SI Pending",IF(Z44<>0,"SC Raised, Advance Pending",IF(X44<>0,"Deal Ticket Rcvd SC Pending", "Entry Pending")))))))))))) -> SI Sent, Shipment Awaited | B44: 48 | C44: 200 | D44: RCN | E44: =IF(AND(LEFT(TRIM(AA44&""),1)="3",BI44<>""),"CLOSE POSITION", IF(AND(LEFT(TRIM(AA44&""),1)="3",BI44=""),"SHORT POSITION", IF(AND(LEFT(TRIM(AA44&""),1)<>"3",BI44<>""),"LONG POSITION","ENTRY PENDING"))) -> SHORT POSITION | F44: =AA44 -> 32014537 | H44: =AB44 -> ST. GREGORIOUS CASHEW | I44: IVC | J44: INDIA | K44: =IF(BQ44<>0,BQ44,"") -> COCHIN, INDIA | L44: =IF(BI44<>0,BI44,"") | M44: =IF(BJ44<>0,BJ44,"") | N44: =IF(BM44<>0,BM44,"") | O44: =IF(BO44<>0,BO44,"") | P44: =CE44 -> No OBL Yet | R44: =CK44 -> No CERTS Yet | S44: =CP44 | T44: CLARIFICATION ON LATEST SOB | U44: RCVD COUNTERSIGNED-267465107-1 | X44: 46076 | Y44: 20009545 | Z44: 46074 | AA44: 32014537 | AB44: ST. GREGORIOUS CASHEW | AC44: March/April - 26 | AD44: 46142 | AE44: 0.1 | AF44: 400 | AG44: =AF44*(1-AE44) -> 360 | AH44: MT | AI44: 1515 | AJ44: =AI44*AF44 -> 606000 | AK44: CIF | AL44: DP SIGHT | AM44: 0 | AN44: 1 | AO44: 0 | AP44: 180 DAYS | AQ44: Mr. George | AR44: Direct | AT44: - | AU44: - | AV44: - | AZ44: =AF44*AI44*AM44 -> 0 | BB44: 46083 | BF44: 46083 | BK44: 40' | BP44: IVC | BQ44: COCHIN, INDIA | BX44: =BJ44*AI44 -> 0 | CE44: =IF(J44="VIETNAM", IF(CG44<>"","OBL in Vietnam Office", IF(CF44<>"","OBL in Transit from Vietnam Office", IF(CD44<>0,"OBL In Destination - "&J44, IF(CC44<>0,"OBL in Transit to Destination - "&J44, IF(CB44<>0,"OBL in SIG Office", IF(CA44<>0,"OBL in Transit from Origin to SIG", IF(BZ44<>0,"OBL in Origin - "&I44, IF(BY44<>0,"Draft Rcvd","No OBL Yet")))))))), IF(CO44<>0,"OBL In Destination - "&J44, IF(CM44<>0,"OBL in Transit with Nego Docs - "&J44, IF(CB44<>0,"OBL in SIG Office", IF(CA44<>0,"OBL in Transit from Origin to SIG", IF(BZ44<>0,"OBL in Origin - "&I44, IF(BY44<>0,"Draft Rcvd","No OBL Yet"))))))) -> No OBL Yet | CK44: =IF(CJ44<>0,"CERTS in Destination - "&J44,IF(CI44<>0,"CERT in Transit to -"&J44,IF(CH44<>0,"CERT in Origin - "&I44,IF(CH44="","No CERTS Yet")))) -> No CERTS Yet | CP44: =IF(CO44<>0,"Docs in Buyer's Nego Bank",IF(CN44<>0,"Docs in Transit to Buyer's Nego Bank",IF(CM44<>0,"Docs in Our Nego Bank",IF(CL44="TT PAYMENT","Not Applicable","")))) | CQ44: =(AN44*AI44*BJ44)-AZ44 -> 0 | CU44: =IF(CS44="","",BJ44-CT44) | CV44: =IF(CS44="","",CU44/BJ44) | CW44: =IF(CS44="","",AZ44+CQ44) | CX44: =IF(CS44="","",BX44*2%) | CY44: =IF(CS44="","",AI44/B44) | DA44: =IF(CS44="","",B44-CZ44) | DC44: =IF(CS44="","",IF(CS44="","",DB44-C44)) | DE44: =IF(CS44="","",10%-DD44) | DF44: =IF(CS44="","",CU44*AI44) | DG44: =IF(CS44="","",IF(DA44>2,2*DA44*CT44*CY44,DA44*CT44*CY44)) | DH44: =IF(CS44="","",IF(DA44>2,2*(DA44-2*CT44*CY44),0)) | DI44: =IF(CS44="","",IF(DC44>0,DC44*0.5*CT44,0)) | DJ44: =IF(CS44="","",IF(DE44<0,DE44*CT44*AI44*1%,0)) | DK44: =IF(CS44="","",SUM(DF44:DJ44)) | DN44: =IF(CS44="","",SUM(DK44:DL44)) | DO44: =IF(CS44="","",BJ44*AI44-DN44) | DP44: =IF(CS44="","",AZ44+CQ44) | DQ44: =IF(CS44="","",IF((DP44-DO44)>0,DP44-DO44,"")) | DR44: =IF(CS44="","",IF((DO44-DP44)>0,(DO44-DP44),"")) | DS44: =IF(CS44="","",IF(DQ44="",H44,"VALENCY")) | DT44: =IF(DN44="","",IF(DN44>0,"CN", "DN")) | DY44: NO VINA/RBS REPORT | EA44: =IF(CS44="","", MIN(0,(IF(DA44>2,2,1)*DA44*CT44*CY44)) ) | EH44: VALENCY IVC | EN44: =EK44*EJ44 -> 0 | EV44: =IF(CR44<>0,"Final Pmt Recd",IF(CM44<>0,"Export Loan",IF(BZ44<>0,"Nego Pending",IF(Z44<>0,"Yet to load","Yet to load")))) -> Yet to load | EX44: =EW44/BJ44 -> #DIV/0! | EY44: Freight paid by origin | FD44: =FC44*BJ44 -> 0 | FL44: =IFERROR(EZ44-BY44,"") -> 0 | FM44: =IFERROR(BM44-FB44,"") -> 0 | FS44: =Y44 -> 20009545 | FT44: =AA44 -> 32014537
A45: =IF(DZ45="CLOSE","Trade closed",IF(DZ45="PMT Pending","FNF Settlement is Due",IF(CS45<>0,"FNF Reconcillation Onging",IF(CR45<>0," Final Pmt Recd , FNF Pending",IF(CM45<>0,"Exp Dox Presented to Bank, Pmt Pending",IF(BZ45<>0,"OBL Scan Recd, Nego Pending",IF(BM45<>0,"Sailed, OBL & Certs Pending",IF(BJ45<>0,"Stuffed, Yet to Sail",IF(BB45<>0,"SI Sent, Shipment Awaited",IF(BA45<>0,"Advance Rcvd, SI Pending",IF(Z45<>0,"SC Raised, Advance Pending",IF(X45<>0,"Deal Ticket Rcvd SC Pending", "Entry Pending")))))))))))) -> Stuffed, Yet to Sail | B45: 49 | C45: 200 | D45: RCN | E45: =IF(AND(LEFT(TRIM(AA45&""),1)="3",BI45<>""),"CLOSE POSITION", IF(AND(LEFT(TRIM(AA45&""),1)="3",BI45=""),"SHORT POSITION", IF(AND(LEFT(TRIM(AA45&""),1)<>"3",BI45<>""),"LONG POSITION","ENTRY PENDING"))) -> CLOSE POSITION | F45: =AA45 -> 32014450 | H45: =AB45 -> ST. PAULS CASHEW FACTORY | I45: IVC | J45: INDIA | K45: =IF(BQ45<>0,BQ45,"") -> TUTICORIN, INDIA | L45: 268715415 | M45: 192.61 | N45: =IF(BM45<>0,BM45,"") | O45: 46189 | P45: =CE45 -> Draft Rcvd | R45: =CK45 -> No CERTS Yet | S45: =CP45 | T45: CLARIFICATION ON LATEST SOB | U45: DRAFT BL APPROVED 25/5 | W45: DRAFT BL APPROVED 25/5 | X45: 46067 | Y45: 20009500 | Z45: 46067 | AA45: 32014450 | AB45: ST. PAULS CASHEW FACTORY | AC45: March/April - 26 | AD45: 46142 | AE45: 0.1 | AF45: 200 | AG45: =AF45*(1-AE45) -> 180 | AH45: MT | AI45: 1560 | AJ45: =AI45*AF45 -> 312000 | AK45: CIF | AL45: DP SIGHT | AM45: 0 | AN45: 1 | AO45: 0 | AP45: 180 DAYS | AQ45: Mr. George | AR45: Direct | AT45: - | AU45: - | AV45: - | AZ45: =AF45*AI45*AM45 -> 0 | BA45: 46070 | BB45: 46083 | BF45: 46083 | BI45: 268715415 | BJ45: 192.61 | BK45: 40' | BL45: 8 | BO45: 46189 | BP45: IVC | BQ45: TUTICORIN, INDIA | BR45: MAERSK LINE | BT45: MAERSK CUANZA | BU45: 617E | BX45: =BJ45*AI45 -> 300471.6 | BY45: 46165 | CE45: =IF(J45="VIETNAM", IF(CG45<>"","OBL in Vietnam Office", IF(CF45<>"","OBL in Transit from Vietnam Office", IF(CD45<>0,"OBL In Destination - "&J45, IF(CC45<>0,"OBL in Transit to Destination - "&J45, IF(CB45<>0,"OBL in SIG Office", IF(CA45<>0,"OBL in Transit from Origin to SIG", IF(BZ45<>0,"OBL in Origin - "&I45, IF(BY45<>0,"Draft Rcvd","No OBL Yet")))))))), IF(CO45<>0,"OBL In Destination - "&J45, IF(CM45<>0,"OBL in Transit with Nego Docs - "&J45, IF(CB45<>0,"OBL in SIG Office", IF(CA45<>0,"OBL in Transit from Origin to SIG", IF(BZ45<>0,"OBL in Origin - "&I45, IF(BY45<>0,"Draft Rcvd","No OBL Yet"))))))) -> Draft Rcvd | CK45: =IF(CJ45<>0,"CERTS in Destination - "&J45,IF(CI45<>0,"CERT in Transit to -"&J45,IF(CH45<>0,"CERT in Origin - "&I45,IF(CH45="","No CERTS Yet")))) -> No CERTS Yet | CP45: =IF(CO45<>0,"Docs in Buyer's Nego Bank",IF(CN45<>0,"Docs in Transit to Buyer's Nego Bank",IF(CM45<>0,"Docs in Our Nego Bank",IF(CL45="TT PAYMENT","Not Applicable","")))) | CQ45: =(AN45*AI45*BJ45)-AZ45 -> 300471.6 | CU45: =IF(CS45="","",BJ45-CT45) | CV45: =IF(CS45="","",CU45/BJ45) | CW45: =IF(CS45="","",AZ45+CQ45) | CX45: =IF(CS45="","",BX45*2%) | CY45: =IF(CS45="","",AI45/B45) | DA45: =IF(CS45="","",B45-CZ45) | DC45: =IF(CS45="","",IF(CS45="","",DB45-C45)) | DE45: =IF(CS45="","",10%-DD45) | DF45: =IF(CS45="","",CU45*AI45) | DG45: =IF(CS45="","",IF(DA45>2,2*DA45*CT45*CY45,DA45*CT45*CY45)) | DH45: =IF(CS45="","",IF(DA45>2,2*(DA45-2*CT45*CY45),0)) | DI45: =IF(CS45="","",IF(DC45>0,DC45*0.5*CT45,0)) | DJ45: =IF(CS45="","",IF(DE45<0,DE45*CT45*AI45*1%,0)) | DK45: =IF(CS45="","",SUM(DF45:DJ45)) | DN45: =IF(CS45="","",SUM(DK45:DL45)) | DO45: =IF(CS45="","",BJ45*AI45-DN45) | DP45: =IF(CS45="","",AZ45+CQ45) | DQ45: =IF(CS45="","",IF((DP45-DO45)>0,DP45-DO45,"")) | DR45: =IF(CS45="","",IF((DO45-DP45)>0,(DO45-DP45),"")) | DS45: =IF(CS45="","",IF(DQ45="",H45,"VALENCY")) | DT45: =IF(DN45="","",IF(DN45>0,"CN", "DN")) | DY45: NO VINA/RBS REPORT | EA45: =IF(CS45="","", MIN(0,(IF(DA45>2,2,1)*DA45*CT45*CY45)) ) | EH45: VALENCY IVC | EI45: FOB | EN45: =EK45*EJ45 -> 0 | EV45: =IF(CR45<>0,"Final Pmt Recd",IF(CM45<>0,"Export Loan",IF(BZ45<>0,"Nego Pending",IF(Z45<>0,"Yet to load","Yet to load")))) -> Yet to load | EX45: =EW45/BJ45 -> 0 | EY45: Freight paid by origin | FD45: =FC45*BJ45 -> 0 | FL45: =IFERROR(EZ45-BY45,"") -> -46165 | FM45: =IFERROR(BM45-FB45,"") -> 0 | FS45: =Y45 -> 20009500 | FT45: =AA45 -> 32014450
